Workbook

Sheet FY26-27
B1: FY26-27 Budgeted vs Actual MIS
B2: Food Matters Group | FY26-27
C3: Total with HO (Amount) | G3: HO | K3: Outlets Total | O3: Table Total | S3: Iktara | W3: Mg St Colaba | AA3: Mg St LP | AE3: Mg St Bandra | AI3: MSK Events | AM3: MSBC | AQ3: Kaspers | AU3: MSBC Andheri | AY3: MSBC Dahisar | BC3: MSBC Juhu/Goregaon | BG3: MSBC Loudmouth
C4: Amount | D4: %age | E4: Budgeted | F4: %age | G4: Actual | H4: %age | I4: Budgeted | J4: %age | K4: Amount | L4: %age | M4: Budgeted | N4: %age | O4: Amount | P4: %age | Q4: Budgeted | R4: %age | S4: Amount | T4: %age | U4: Budgeted | V4: %age | W4: Amount | X4: %age | Y4: Budgeted | Z4: %age | AA4: Amount | AB4: %age | AC4: Budgeted | AD4: %age | AE4: Amount | AF4: %age | AG4: Budgeted | AH4: %age | AI4: Amount | AJ4: %age | AK4: Budgeted | AL4: %age | AM4: Amount | AN4: %age | AO4: Budgeted | AP4: %age | AQ4: Amount | AR4: %age | AS4: Budgeted | AT4: %age | AU4: Amount | AV4: %age | AW4: Budgeted | AX4: %age | AY4: Amount | AZ4: %age | BA4: Budgeted | BB4: %age | BC4: Amount | BD4: %age | BE4: Budgeted | BF4: %age | BG4: Amount | BH4: %age | BI4: Budgeted | BJ4: %age
B5: Beverage | C5: =G5+K5 -> 11608400 | D5: =C5/$C$10 -> 0.078003476 | E5: =I5+M5 -> 0 | F5: =E5/E$10 -> #DIV/0! | G5: ='Q1 FY26-27'!G5 -> 0 | I5: ='Q1 FY26-27'!I5 -> 0 | K5: =O5+S5+W5+AA5+AE5+AI5+AM5+AQ5+AU5+AY5+BC5+BG5 -> 11608400 | L5: =K5/$K$10 -> 0.078003476 | M5: =Q5+U5+Y5+AC5+AG5+AK5+AO5 -> 0 | N5: =M5/M$10 -> #DIV/0! | O5: ='Q1 FY26-27'!O5 -> 2407580 | P5: =O5/O$10 -> 0.058815722 | Q5: ='Q1 FY26-27'!Q5 -> 0 | R5: =Q5/Q$10 -> #DIV/0! | S5: ='Q1 FY26-27'!S5 -> 0 | T5: =S5/S$10 -> 0 | U5: ='Q1 FY26-27'!U5 -> 0 | V5: =U5/U$10 -> #DIV/0! | W5: ='Q1 FY26-27'!W5 -> 2398144 | X5: =W5/W$10 -> 0.094851748 | Y5: ='Q1 FY26-27'!Y5 -> 0 | Z5: =Y5/Y$10 -> #DIV/0! | AA5: ='Q1 FY26-27'!AA5 -> 2390099.8 | AB5: =AA5/AA$10 -> 0.12483768 | AC5: ='Q1 FY26-27'!AC5 -> 0 | AD5: =AC5/AC$10 -> #DIV/0! | AE5: ='Q1 FY26-27'!AE5 -> 3237788.5 | AF5: =AE5/AE$10 -> 0.094581636 | AG5: ='Q1 FY26-27'!AG5 -> 0 | AH5: =AG5/AG$10 -> #DIV/0! | AI5: ='Q1 FY26-27'!AI5 -> 0 | AJ5: =AI5/AI$10 -> #DIV/0! | AK5: ='Q1 FY26-27'!AK5 -> 0 | AL5: =AK5/AK$10 -> #DIV/0! | AM5: ='Q1 FY26-27'!AM5 -> 0 | AN5: =AM5/AM$10 -> 0 | AO5: ='Q1 FY26-27'!AO5 -> 0 | AP5: =AO5/AO$10 -> #DIV/0! | AQ5: ='Q1 FY26-27'!AQ5 -> 1174787.5 | AR5: =AQ5/AQ$10 -> 0.048653213 | AS5: ='Q1 FY26-27'!AS5 -> 0 | AU5: 0 | AV5: =AU5/AU$10 -> 0 | AW5: ='Q1 FY26-27'!AW5 -> 0 | AY5: ='Q1 FY26-27'!AY5 -> 0 | BA5: ='Q1 FY26-27'!BA5 -> 0 | BC5: ='Q1 FY26-27'!BC5 -> 0 | BE5: ='Q1 FY26-27'!BE5 -> 0 | BG5: ='Q1 FY26-27'!BG5 -> 0 | BI5: ='Q1 FY26-27'!BI5 -> 0
B6: Liquor | C6: =G6+K6 -> 24020516 | D6: =C6/$C$10 -> 0.16140758 | E6: =I6+M6 -> 0 | F6: =E6/E$10 -> #DIV/0! | G6: ='Q1 FY26-27'!G6 -> 0 | I6: ='Q1 FY26-27'!I6 -> 0 | K6: =O6+S6+W6+AA6+AE6+AI6+AM6+AQ6+AU6+AY6+BC6+BG6 -> 24020516 | L6: =K6/$K$10 -> 0.16140758 | M6: =Q6+U6+Y6+AC6+AG6+AK6+AO6 -> 0 | N6: =M6/M$10 -> #DIV/0! | O6: ='Q1 FY26-27'!O6 -> 9818016 | P6: =O6/O$10 -> 0.23984819 | Q6: ='Q1 FY26-27'!Q6 -> 0 | R6: =Q6/Q$10 -> #DIV/0! | S6: ='Q1 FY26-27'!S6 -> 0 | T6: =S6/S$10 -> 0 | U6: ='Q1 FY26-27'!U6 -> 0 | V6: =U6/U$10 -> #DIV/0! | W6: ='Q1 FY26-27'!W6 -> 1505040 | X6: =W6/W$10 -> 0.059527566 | Y6: ='Q1 FY26-27'!Y6 -> 0 | Z6: =Y6/Y$10 -> #DIV/0! | AA6: ='Q1 FY26-27'!AA6 -> 0 | AB6: =AA6/AA$10 -> 0 | AC6: ='Q1 FY26-27'!AC6 -> 0 | AD6: =AC6/AC$10 -> #DIV/0! | AE6: ='Q1 FY26-27'!AE6 -> 4194442.5 | AF6: =AE6/AE$10 -> 0.12252722 | AG6: ='Q1 FY26-27'!AG6 -> 0 | AH6: =AG6/AG$10 -> #DIV/0! | AI6: ='Q1 FY26-27'!AI6 -> 0 | AJ6: =AI6/AI$10 -> #DIV/0! | AK6: ='Q1 FY26-27'!AK6 -> 0 | AL6: =AK6/AK$10 -> #DIV/0! | AM6: ='Q1 FY26-27'!AM6 -> 0 | AN6: =AM6/AM$10 -> 0 | AO6: ='Q1 FY26-27'!AO6 -> 0 | AP6: =AO6/AO$10 -> #DIV/0! | AQ6: ='Q1 FY26-27'!AQ6 -> 8503017.5 | AR6: =AQ6/AQ$10 -> 0.35214804 | AS6: ='Q1 FY26-27'!AS6 -> 0 | AU6: 0 | AV6: =AU6/AU$10 -> 0 | AW6: ='Q1 FY26-27'!AW6 -> 0 | AY6: ='Q1 FY26-27'!AY6 -> 0 | BA6: ='Q1 FY26-27'!BA6 -> 0 | BC6: ='Q1 FY26-27'!BC6 -> 0 | BE6: ='Q1 FY26-27'!BE6 -> 0 | BG6: ='Q1 FY26-27'!BG6 -> 0 | BI6: ='Q1 FY26-27'!BI6 -> 0
B7: Food | C7: =G7+K7 -> 108260254 | D7: =C7/$C$10 -> 0.72746255 | E7: =I7+M7 -> 0 | F7: =E7/E$10 -> #DIV/0! | G7: ='Q1 FY26-27'!G7 -> 0 | I7: ='Q1 FY26-27'!I7 -> 0 | K7: =O7+S7+W7+AA7+AE7+AI7+AM7+AQ7+AU7+AY7+BC7+BG7 -> 108260254 | L7: =K7/$K$10 -> 0.72746255 | M7: =Q7+U7+Y7+AC7+AG7+AK7+AO7 -> 0 | N7: =M7/M$10 -> #DIV/0! | O7: ='Q1 FY26-27'!O7 -> 26989559 | P7: =O7/O$10 -> 0.65933859 | Q7: ='Q1 FY26-27'!Q7 -> 0 | R7: =Q7/Q$10 -> #DIV/0! | S7: ='Q1 FY26-27'!S7 -> 1667248 | T7: =S7/S$10 -> 1 | U7: ='Q1 FY26-27'!U7 -> 0 | V7: =U7/U$10 -> #DIV/0! | W7: ='Q1 FY26-27'!W7 -> 20658266 | X7: =W7/W$10 -> 0.81707883 | Y7: ='Q1 FY26-27'!Y7 -> 0 | Z7: =Y7/Y$10 -> #DIV/0! | AA7: ='Q1 FY26-27'!AA7 -> 16390588 | AB7: =AA7/AA$10 -> 0.85609941 | AC7: ='Q1 FY26-27'!AC7 -> 0 | AD7: =AC7/AC$10 -> #DIV/0! | AE7: ='Q1 FY26-27'!AE7 -> 25758068 | AF7: =AE7/AE$10 -> 0.75243959 | AG7: ='Q1 FY26-27'!AG7 -> 0 | AH7: =AG7/AG$10 -> #DIV/0! | AI7: ='Q1 FY26-27'!AI7 -> 0 | AJ7: =AI7/AI$10 -> #DIV/0! | AK7: ='Q1 FY26-27'!AK7 -> 0 | AL7: =AK7/AK$10 -> #DIV/0! | AM7: ='Q1 FY26-27'!AM7 -> 970993.82 | AN7: =AM7/AM$10 -> 1 | AO7: ='Q1 FY26-27'!AO7 -> 0 | AP7: =AO7/AO$10 -> #DIV/0! | AQ7: ='Q1 FY26-27'!AQ7 -> 13386680 | AR7: =AQ7/AQ$10 -> 0.55440236 | AS7: ='Q1 FY26-27'!AS7 -> 0 | AU7: ='Q1 FY26-27'!AU7 -> 666826.99 | AV7: =AU7/AU$10 -> 1 | AW7: ='Q1 FY26-27'!AW7 -> 0 | AY7: ='Q1 FY26-27'!AY7 -> 228077.89 | BA7: ='Q1 FY26-27'!BA7 -> 0 | BC7: ='Q1 FY26-27'!BC7 -> 306961.08 | BE7: ='Q1 FY26-27'!BE7 -> 0 | BG7: ='Q1 FY26-27'!BG7 -> 1236985 | BI7: ='Q1 FY26-27'!BI7 -> 0
B8: Service Charge | C8: =G8+K8 -> 4894605 | D8: =C8/$C$10 -> 0.03288965 | E8: =I8+M8 -> 0 | F8: =E8/E$10 -> #DIV/0! | G8: ='Q1 FY26-27'!G8 -> 0 | I8: ='Q1 FY26-27'!I8 -> 0 | K8: =O8+S8+W8+AA8+AE8+AI8+AM8+AQ8+AU8+AY8+BC8+BG8 -> 4894605 | L8: =K8/$K$10 -> 0.03288965 | M8: =Q8+U8+Y8+AC8+AG8+AK8+AO8 -> 0 | N8: =M8/M$10 -> #DIV/0! | O8: ='Q1 FY26-27'!O8 -> 1719138 | P8: =O8/O$10 -> 0.041997501 | Q8: ='Q1 FY26-27'!Q8 -> 0 | R8: =Q8/Q$10 -> #DIV/0! | S8: ='Q1 FY26-27'!S8 -> 0 | T8: =S8/S$10 -> 0 | U8: ='Q1 FY26-27'!U8 -> 0 | V8: =U8/U$10 -> #DIV/0! | W8: ='Q1 FY26-27'!W8 -> 721626 | X8: =W8/W$10 -> 0.028541859 | Y8: ='Q1 FY26-27'!Y8 -> 0 | Z8: =Y8/Y$10 -> #DIV/0! | AA8: ='Q1 FY26-27'!AA8 -> 356972.05 | AB8: =AA8/AA$10 -> 0.018645064 | AC8: ='Q1 FY26-27'!AC8 -> 0 | AD8: =AC8/AC$10 -> #DIV/0! | AE8: ='Q1 FY26-27'!AE8 -> 1028709 | AF8: =AE8/AE$10 -> 0.030050444 | AG8: ='Q1 FY26-27'!AG8 -> 0 | AH8: =AG8/AG$10 -> #DIV/0! | AI8: ='Q1 FY26-27'!AI8 -> 0 | AJ8: =AI8/AI$10 -> #DIV/0! | AK8: ='Q1 FY26-27'!AK8 -> 0 | AL8: =AK8/AK$10 -> #DIV/0! | AM8: ='Q1 FY26-27'!AM8 -> 0 | AN8: =AM8/AM$10 -> 0 | AO8: ='Q1 FY26-27'!AO8 -> 0 | AP8: =AO8/AO$10 -> #DIV/0! | AQ8: ='Q1 FY26-27'!AQ8 -> 1068160 | AR8: =AQ8/AQ$10 -> 0.04423729 | AS8: ='Q1 FY26-27'!AS8 -> 0 | AU8: 0 | AV8: =AU8/AU$10 -> 0 | AW8: ='Q1 FY26-27'!AW8 -> 0 | AY8: ='Q1 FY26-27'!AY8 -> 0 | BA8: ='Q1 FY26-27'!BA8 -> 0 | BC8: ='Q1 FY26-27'!BC8 -> 0 | BE8: ='Q1 FY26-27'!BE8 -> 0 | BG8: ='Q1 FY26-27'!BG8 -> 0 | BI8: ='Q1 FY26-27'!BI8 -> 0
B9: Scrap Sales | C9: =G9+K9 -> 35231 | D9: =C9/$C$10 -> 0.00023673724 | E9: =I9+M9 -> 0 | F9: =E9/E$10 -> #DIV/0! | G9: ='Q1 FY26-27'!G9 -> 0 | I9: ='Q1 FY26-27'!I9 -> 0 | K9: =O9+S9+W9+AA9+AE9+AI9+AM9+AQ9+AU9+AY9+BC9+BG9 -> 35231 | L9: =K9/$K$10 -> 0.00023673724 | M9: =Q9+U9+Y9+AC9+AG9+AK9+AO9 -> 0 | N9: =M9/M$10 -> #DIV/0! | O9: ='Q1 FY26-27'!O9 -> 0 | P9: =O9/O$10 -> 0 | Q9: ='Q1 FY26-27'!Q9 -> 0 | R9: =Q9/Q$10 -> #DIV/0! | S9: ='Q1 FY26-27'!S9 -> 0 | T9: =S9/S$10 -> 0 | U9: ='Q1 FY26-27'!U9 -> 0 | V9: =U9/U$10 -> #DIV/0! | W9: ='Q1 FY26-27'!W9 -> 0 | X9: =W9/W$10 -> 0 | Y9: ='Q1 FY26-27'!Y9 -> 0 | Z9: =Y9/Y$10 -> #DIV/0! | AA9: ='Q1 FY26-27'!AA9 -> 8000 | AB9: =AA9/AA$10 -> 0.00041784927 | AC9: ='Q1 FY26-27'!AC9 -> 0 | AD9: =AC9/AC$10 -> #DIV/0! | AE9: ='Q1 FY26-27'!AE9 -> 13731 | AF9: =AE9/AE$10 -> 0.00040110725 | AG9: ='Q1 FY26-27'!AG9 -> 0 | AH9: =AG9/AG$10 -> #DIV/0! | AI9: ='Q1 FY26-27'!AI9 -> 0 | AJ9: =AI9/AI$10 -> #DIV/0! | AK9: ='Q1 FY26-27'!AK9 -> 0 | AL9: =AK9/AK$10 -> #DIV/0! | AM9: ='Q1 FY26-27'!AM9 -> 0 | AN9: =AM9/AM$10 -> 0 | AO9: ='Q1 FY26-27'!AO9 -> 0 | AP9: =AO9/AO$10 -> #DIV/0! | AQ9: ='Q1 FY26-27'!AQ9 -> 13500 | AR9: =AQ9/AQ$10 -> 0.00055909547 | AS9: ='Q1 FY26-27'!AS9 -> 0 | AU9: 0 | AV9: =AU9/AU$10 -> 0 | AW9: ='Q1 FY26-27'!AW9 -> 0 | AY9: ='Q1 FY26-27'!AY9 -> 0 | BA9: ='Q1 FY26-27'!BA9 -> 0 | BC9: ='Q1 FY26-27'!BC9 -> 0 | BE9: ='Q1 FY26-27'!BE9 -> 0 | BG9: ='Q1 FY26-27'!BG9 -> 0 | BI9: ='Q1 FY26-27'!BI9 -> 0
B10: Total Sales Revenue | C10: =SUM(C5:C9) -> 1.4881901e+08 | D10: =C10/C10 -> 1 | E10: =SUM(E5:E9) -> 0 | F10: =E10/E10 -> #DIV/0! | G10: =SUM(G5:G9) -> 0 | I10: =SUM(I5:I9) -> 0 | K10: =SUM(K5:K9) -> 1.4881901e+08 | L10: =K10/K10 -> 1 | M10: =SUM(M5:M9) -> 0 | N10: =M10/M10 -> #DIV/0! | O10: =SUM(O5:O9) -> 40934293 | Q10: =SUM(Q5:Q9) -> 0 | S10: =SUM(S5:S9) -> 1667248 | U10: =SUM(U5:U8) -> 0 | W10: =SUM(W5:W9) -> 25283076 | Y10: =SUM(Y5:Y8) -> 0 | AA10: =SUM(AA5:AA9) -> 19145660 | AC10: =SUM(AC5:AC8) -> 0 | AE10: =SUM(AE5:AE9) -> 34232739 | AG10: =SUM(AG5:AG8) -> 0 | AI10: =SUM(AI5:AI9) -> 0 | AK10: =SUM(AK5:AK9) -> 0 | AM10: =SUM(AM5:AM9) -> 970993.82 | AO10: =SUM(AO5:AO8) -> 0 | AQ10: =SUM(AQ5:AQ9) -> 24146144 | AS10: ='Q1 FY26-27'!AS10 -> 0 | AU10: =SUM(AU5:AU8) -> 666826.99 | AW10: =SUM(AW5:AW8) -> 0 | AY10: =SUM(AY5:AY8) -> 228077.89 | BA10: =SUM(BA5:BA8) -> 0 | BC10: =SUM(BC5:BC8) -> 306961.08 | BE10: =SUM(BE5:BE8) -> 0 | BG10: =SUM(BG5:BG8) -> 1236985 | BI10: =SUM(BI5:BI8) -> 0
B11: Average /Month | C11: =C10/12 -> 12401584 | E11: =E10/12 -> 0 | G11: ='Q1 FY26-27'!G11 | I11: ='Q1 FY26-27'!I11 | O11: ='Q1 FY26-27'!O11 | S11: =S10/12 -> 138937.33 | U11: =U10/12 -> 0 | W11: =W10/12 -> 2106923 | Y11: =Y10/12 -> 0 | AA11: =AA10/12 -> 1595471.7 | AE11: =AE10/12 -> 2852728.3 | AG11: ='Q1 FY26-27'!AG11 | AI11: ='Q1 FY26-27'!AI11 | AK11: ='Q1 FY26-27'!AK11 | AM11: =AM10/12 -> 80916.152 | AO11: ='Q1 FY26-27'!AO11 | AQ11: =AQ10/4.5 -> 5365809.9 | AS11: ='Q1 FY26-27'!AS11 | AU11: 0 | AW11: 0 | AY11: 0 | BA11: 0 | BC11: 0 | BE11: 0 | BG11: 0 | BI11: 0
B12: COGS | C12: =G12+K12 -> 55832434 | D12: =C12/$C$10 -> 0.37517005 | E12: =I12+M12 -> 0 | F12: =E12/E$10 -> #DIV/0! | G12: ='Q1 FY26-27'!G12 -> 0 | H12: =G12/$C$10 -> 0 | I12: ='Q1 FY26-27'!I12 -> 0 | J12: =I12/$C$10 -> 0 | K12: =O12+S12+W12+AA12+AE12+AI12+AM12+AQ12+AU12+AY12+BC12+BG12 -> 55832434 | L12: =K12/$K$10 -> 0.37517005 | M12: =Q12+U12+Y12+AC12+AG12+AK12+AO12 -> 0 | N12: =M12/M$10 -> #DIV/0! | O12: ='Q1 FY26-27'!O12 -> 14259873 | P12: =O12/O$10 -> 0.34836006 | Q12: ='Q1 FY26-27'!Q12 -> 0 | R12: =Q12/Q$10 -> #DIV/0! | S12: ='Q1 FY26-27'!S12 -> 573413.45 | T12: =S12/S$10 -> 0.34392811 | U12: ='Q1 FY26-27'!U12 -> 0 | V12: =U12/U$10 -> #DIV/0! | W12: ='Q1 FY26-27'!W12 -> 9869489.7 | X12: =W12/W$10 -> 0.39035952 | Y12: ='Q1 FY26-27'!Y12 -> 0 | Z12: =Y12/Y$10 -> #DIV/0! | AA12: ='Q1 FY26-27'!AA12 -> 6943290.1 | AB12: =AA12/AA$10 -> 0.36265609 | AC12: ='Q1 FY26-27'!AC12 -> 0 | AD12: =AC12/AC$10 -> #DIV/0! | AE12: ='Q1 FY26-27'!AE12 -> 11423138 | AF12: =AE12/AE$10 -> 0.33369043 | AG12: ='Q1 FY26-27'!AG12 -> 0 | AH12: =AG12/AG$10 -> #DIV/0! | AI12: ='Q1 FY26-27'!AI12 -> 0 | AJ12: =AI12/AI$10 -> #DIV/0! | AK12: ='Q1 FY26-27'!AK12 -> 0 | AL12: =AK12/AK$10 -> #DIV/0! | AM12: ='Q1 FY26-27'!AM12 -> 1697483.5 | AN12: =AM12/AM$10 -> 1.7481919 | AO12: ='Q1 FY26-27'!AO12 -> 0 | AP12: =AO12/AO$10 -> #DIV/0! | AQ12: ='Q1 FY26-27'!AQ12 -> 9435973 | AR12: =AQ12/AQ$10 -> 0.39078591 | AS12: ='Q1 FY26-27'!AS12 -> 0 | AU12: ='Q1 FY26-27'!AU12 -> 438745.12 | AV12: =AU12/AU$10 -> 0.65795945 | AW12: ='Q1 FY26-27'!AW12 -> 0 | AY12: ='Q1 FY26-27'!AY12 -> 339203.01 | BA12: ='Q1 FY26-27'!BA12 -> 0 | BC12: ='Q1 FY26-27'!BC12 -> 495419.73 | BE12: ='Q1 FY26-27'!BE12 -> 0 | BG12: ='Q1 FY26-27'!BG12 -> 356406.24 | BI12: ='Q1 FY26-27'!BI12 -> 0
B13: Packaging Cost | C13: =G13+K13 -> 1899950.2 | D13: =C13/$C$10 -> 0.012766852 | E13: =I13+M13 -> 0 | F13: =E13/E$10 -> #DIV/0! | G13: ='Q1 FY26-27'!G13 -> 0 | I13: ='Q1 FY26-27'!I13 -> 0 | K13: =O13+S13+W13+AA13+AE13+AI13+AM13+AQ13+AU13+AY13+BC13+BG13 -> 1899950.2 | L13: =K13/$K$10 -> 0.012766852 | M13: =Q13+U13+Y13+AC13+AG13+AK13+AO13 -> 0 | N13: =M13/M$10 -> #DIV/0! | O13: ='Q1 FY26-27'!O13 -> 106548 | P13: =O13/O$10 -> 0.0026029032 | Q13: ='Q1 FY26-27'!Q13 -> 0 | R13: =Q13/Q$10 -> #DIV/0! | S13: ='Q1 FY26-27'!S13 -> 73214 | T13: =S13/S$10 -> 0.043913083 | U13: ='Q1 FY26-27'!U13 -> 0 | V13: =U13/U$10 -> #DIV/0! | W13: ='Q1 FY26-27'!W13 -> 366401.4 | X13: =W13/W$10 -> 0.014491963 | Y13: ='Q1 FY26-27'!Y13 -> 0 | Z13: =Y13/Y$10 -> #DIV/0! | AA13: ='Q1 FY26-27'!AA13 -> 442124 | AB13: =AA13/AA$10 -> 0.023092649 | AC13: ='Q1 FY26-27'!AC13 -> 0 | AD13: =AC13/AC$10 -> #DIV/0! | AE13: ='Q1 FY26-27'!AE13 -> 512245.02 | AF13: =AE13/AE$10 -> 0.0149636 | AG13: ='Q1 FY26-27'!AG13 -> 0 | AH13: =AG13/AG$10 -> #DIV/0! | AI13: ='Q1 FY26-27'!AI13 -> 1030 | AJ13: =AI13/AI$10 -> #DIV/0! | AK13: ='Q1 FY26-27'!AK13 -> 0 | AL13: =AK13/AK$10 -> #DIV/0! | AM13: ='Q1 FY26-27'!AM13 -> 203076.5 | AN13: =AM13/AM$10 -> 0.20914294 | AO13: ='Q1 FY26-27'!AO13 -> 0 | AP13: =AO13/AO$10 -> #DIV/0! | AQ13: ='Q1 FY26-27'!AQ13 -> 85375.3 | AR13: =AQ13/AQ$10 -> 0.0035357736 | AS13: ='Q1 FY26-27'!AS13 -> 0 | AU13: ='Q1 FY26-27'!AU13 -> 8383 | AV13: =AU13/AU$10 -> 0.012571477 | AW13: ='Q1 FY26-27'!AW13 -> 0 | AY13: ='Q1 FY26-27'!AY13 -> 9422 | BA13: ='Q1 FY26-27'!BA13 -> 0 | BC13: ='Q1 FY26-27'!BC13 -> 5647 | BE13: ='Q1 FY26-27'!BE13 -> 0 | BG13: ='Q1 FY26-27'!BG13 -> 86484 | BI13: ='Q1 FY26-27'!BI13 -> 0
B14: Total COGS & Packaging | C14: =SUM(C12:C13) -> 57732384 | D14: =C14/C10 -> 0.3879369 | E14: =E12+E13 -> 0 | F14: =E14/E$10 -> #DIV/0! | G14: ='Q1 FY26-27'!G14 -> 0 | H14: =G14/C10 -> 0 | I14: ='Q1 FY26-27'!I14 -> 0 | J14: =I14/E10 -> #DIV/0! | K14: ='Q1 FY26-27'!K14 -> 57732384 | L14: =K14/K10 -> 0.3879369 | M14: =M12+M13 -> 0 | N14: =M14/M$10 -> #DIV/0! | O14: ='Q1 FY26-27'!O14 -> 14366421 | P14: =O14/O$10 -> 0.35096296 | Q14: =SUM(Q12:Q13) -> 0 | R14: =Q14/Q$10 -> #DIV/0! | S14: =SUM(S12:S13) -> 646627.45 | U14: =SUM(U12:U13) -> 0 | V14: =U14/U$10 -> #DIV/0! | W14: =SUM(W12:W13) -> 10235891 | Y14: =SUM(Y12:Y13) -> 0 | Z14: =Y14/Y$10 -> #DIV/0! | AA14: =SUM(AA12:AA13) -> 7385414.1 | AC14: =SUM(AC12:AC13) -> 0 | AD14: =AC14/AC$10 -> #DIV/0! | AE14: =SUM(AE12:AE13) -> 11935383 | AG14: =SUM(AG12:AG13) -> 0 | AH14: =AG14/AG$10 -> #DIV/0! | AI14: ='Q1 FY26-27'!AI14 -> 1030 | AJ14: =AI14/AI$10 -> #DIV/0! | AK14: ='Q1 FY26-27'!AK14 -> 0 | AL14: =AK14/AK$10 -> #DIV/0! | AM14: =SUM(AM12:AM13) -> 1900560 | AO14: =SUM(AO12:AO13) -> 0 | AQ14: ='Q1 FY26-27'!AQ14 -> 9521348.3 | AS14: =SUM(AS12:AS13) -> 0 | AU14: =AU12+AU13 -> 447128.12 | AW14: =AW12+AW13 -> 0 | AY14: =AY12+AY13 -> 348625.01 | BA14: =BA12+BA13 -> 0 | BC14: =BC12+BC13 -> 501066.73 | BE14: =BE12+BE13 -> 0 | BG14: =BG12+BG13 -> 442890.24 | BI14: =BI12+BI13 -> 0
B15: DEQ | G15: ='Q1 FY26-27'!G15 | I15: ='Q1 FY26-27'!I15 | O15: ='Q1 FY26-27'!O15 | S15: ='Q1 FY26-27'!S15 | U15: ='Q1 FY26-27'!U15 | W15: ='Q1 FY26-27'!W15 | Y15: ='Q1 FY26-27'!Y15 | AA15: ='Q1 FY26-27'!AA15 | AE15: ='Q1 FY26-27'!AE15 | AG15: ='Q1 FY26-27'!AG15 | AI15: ='Q1 FY26-27'!AI15 | AK15: ='Q1 FY26-27'!AK15 | AM15: ='Q1 FY26-27'!AM15 | AO15: ='Q1 FY26-27'!AO15 | AQ15: ='Q1 FY26-27'!AQ15 | AS15: ='Q1 FY26-27'!AS15 | AU15: 0 | AW15: 0 | AY15: 0 | BA15: 0 | BC15: 0 | BE15: 0 | BG15: 0 | BI15: 0
B16: Gross Margin | C16: =C10-C14 -> 91086622 | D16: =C16/C10 -> 0.6120631 | E16: =E10-E14 -> 0 | F16: =E16/E$10 -> #DIV/0! | G16: ='Q1 FY26-27'!G16 -> 0 | H16: =G16/C10 -> 0 | I16: ='Q1 FY26-27'!I16 -> 0 | J16: =I16/E10 -> #DIV/0! | K16: ='Q1 FY26-27'!K16 -> 91086622 | L16: =K16/K10 -> 0.6120631 | M16: =Q16+U16+Y16+AC16+AG16+AK16+AO16 -> 0 | N16: =M16/M$10 -> #DIV/0! | O16: ='Q1 FY26-27'!O16 -> 26567872 | P16: =O16/O$10 -> 0.64903704 | Q16: ='Q1 FY26-27'!Q16 -> 0 | R16: =Q16/Q$10 -> #DIV/0! | S16: ='Q1 FY26-27'!S16 -> 1020620.5 | T16: =S16/S$10 -> 0.61215881 | U16: ='Q1 FY26-27'!U16 -> 0 | V16: =U16/U$10 -> #DIV/0! | W16: ='Q1 FY26-27'!W16 -> 15047185 | X16: =W16/W$10 -> 0.59514851 | Y16: ='Q1 FY26-27'!Y16 -> 0 | Z16: =Y16/Y$10 -> #DIV/0! | AA16: ='Q1 FY26-27'!AA16 -> 11760246 | AB16: =AA16/AA$10 -> 0.61425127 | AC16: ='Q1 FY26-27'!AC16 -> 0 | AD16: =AC16/AC$10 -> #DIV/0! | AE16: ='Q1 FY26-27'!AE16 -> 22297357 | AF16: =AE16/AE$10 -> 0.65134597 | AG16: ='Q1 FY26-27'!AG16 -> 0 | AH16: =AG16/AG$10 -> #DIV/0! | AI16: ='Q1 FY26-27'!AI16 -> -1030 | AJ16: =AI16/AI$10 -> #DIV/0! | AK16: ='Q1 FY26-27'!AK16 -> 0 | AL16: =AK16/AK$10 -> #DIV/0! | AM16: ='Q1 FY26-27'!AM16 -> -929566.16 | AN16: =AM16/AM$10 -> -0.95733479 | AO16: ='Q1 FY26-27'!AO16 -> 0 | AP16: =AO16/AO$10 -> #DIV/0! | AQ16: ='Q1 FY26-27'!AQ16 -> 14624796 | AR16: =AQ16/AQ$10 -> 0.60567832 | AS16: ='Q1 FY26-27'!AS16 -> 0 | AU16: ='Q1 FY26-27'!AU16 -> 219698.87 | AV16: =AU16/AU$10 -> 0.32946907 | AW16: ='Q1 FY26-27'!AW16 -> 0 | AY16: ='Q1 FY26-27'!AY16 -> -120547.12 | BA16: =BA10-BA14 -> 0 | BC16: ='Q1 FY26-27'!BC16 -> -194105.65 | BE16: =BE10-BE14 -> 0 | BG16: ='Q1 FY26-27'!BG16 -> 794094.76 | BI16: =BI10-BI14 -> 0
B17: Average /Month | E17: =E16/12 -> 0 | G17: ='Q1 FY26-27'!G17 | I17: ='Q1 FY26-27'!I17 | O17: ='Q1 FY26-27'!O17 | S17: ='Q1 FY26-27'!S17 | U17: ='Q1 FY26-27'!U17 | W17: ='Q1 FY26-27'!W17 | Y17: ='Q1 FY26-27'!Y17 | AA17: ='Q1 FY26-27'!AA17 | AE17: ='Q1 FY26-27'!AE17 | AG17: ='Q1 FY26-27'!AG17 | AI17: ='Q1 FY26-27'!AI17 | AK17: ='Q1 FY26-27'!AK17 | AM17: ='Q1 FY26-27'!AM17 | AO17: ='Q1 FY26-27'!AO17 | AQ17: ='Q1 FY26-27'!AQ17 | AS17: ='Q1 FY26-27'!AS17 | AU17: 0 | AW17: 0 | AY17: 0 | BA17: 0 | BC17: 0 | BE17: 0 | BG17: 0 | BI17: 0
B18: Other Direct Expenses | C18: =G18+K18 -> 3971287.5 | D18: =C18/$C$10 -> 0.026685352 | E18: =I18+M18 -> 0 | F18: =E18/E$10 -> #DIV/0! | G18: ='Q1 FY26-27'!G18 -> 128002.51 | H18: =G18/$C$10 -> 0.00086012208 | I18: ='Q1 FY26-27'!I18 -> 0 | J18: =I18/$C$10 -> 0 | K18: =O18+S18+W18+AA18+AE18+AI18+AM18+AQ18+AU18+AY18+BC18+BG18 -> 3843285 | L18: =K18/$K$10 -> 0.02582523 | M18: =Q18+U18+Y18+AC18+AG18+AK18+AO18 -> 0 | N18: =M18/M$10 -> #DIV/0! | O18: ='Q1 FY26-27'!O18 -> 949580.56 | P18: =O18/O$10 -> 0.023197678 | Q18: ='Q1 FY26-27'!Q18 -> 0 | R18: =Q18/Q$10 -> #DIV/0! | S18: ='Q1 FY26-27'!S18 -> 91280.29 | T18: =S18/S$10 -> 0.054749078 | U18: ='Q1 FY26-27'!U18 -> 0 | V18: =U18/U$10 -> #DIV/0! | W18: ='Q1 FY26-27'!W18 -> 750009.87 | X18: =W18/W$10 -> 0.029664502 | Y18: ='Q1 FY26-27'!Y18 -> 0 | Z18: =Y18/Y$10 -> #DIV/0! | AA18: ='Q1 FY26-27'!AA18 -> 483204.82 | AB18: =AA18/AA$10 -> 0.025238348 | AC18: ='Q1 FY26-27'!AC18 -> 0 | AD18: =AC18/AC$10 -> #DIV/0! | AE18: ='Q1 FY26-27'!AE18 -> 989178.45 | AF18: =AE18/AE$10 -> 0.028895685 | AG18: ='Q1 FY26-27'!AG18 -> 0 | AH18: =AG18/AG$10 -> #DIV/0! | AI18: ='Q1 FY26-27'!AI18 -> 35514 | AJ18: =AI18/AI$10 -> #DIV/0! | AK18: ='Q1 FY26-27'!AK18 -> 0 | AL18: =AK18/AK$10 -> #DIV/0! | AM18: ='Q1 FY26-27'!AM18 -> 71198.86 | AN18: =AM18/AM$10 -> 0.07332576 | AO18: ='Q1 FY26-27'!AO18 -> 0 | AP18: =AO18/AO$10 -> #DIV/0! | AQ18: ='Q1 FY26-27'!AQ18 -> 467605.13 | AR18: =AQ18/AQ$10 -> 0.019365623 | AS18: ='Q1 FY26-27'!AS18 -> 0 | AU18: ='Q1 FY26-27'!AU18 -> 0 | AV18: =AU18/AU$10 -> 0 | AW18: ='Q1 FY26-27'!AW18 -> 0 | AY18: ='Q1 FY26-27'!AY18 -> 0 | BA18: ='Q1 FY26-27'!BA18 -> 0 | BC18: ='Q1 FY26-27'!BC18 -> 0 | BE18: ='Q1 FY26-27'!BE18 -> 0 | BG18: ='Q1 FY26-27'!BG18 -> 5713 | BI18: ='Q1 FY26-27'!BI18 -> 0
B19: Marketing Expenses | C19: =G19+K19 -> 1618158.4 | D19: =C19/$C$10 -> 0.010873332 | E19: =I19+M19 -> 53100 | F19: =E19/E$10 -> #DIV/0! | G19: ='Q1 FY26-27'!G19 -> 106200 | H19: =G19/$C$10 -> 0.00071361853 | I19: ='Q1 FY26-27'!I19 -> 53100 | J19: =I19/$C$10 -> 0.00035680926 | K19: =O19+S19+W19+AA19+AE19+AI19+AM19+AQ19+AU19+AY19+BC19+BG19 -> 1511958.4 | L19: =K19/$K$10 -> 0.010159713 | M19: =Q19+U19+Y19+AC19+AG19+AK19+AO19 -> 0 | N19: =M19/M$10 -> #DIV/0! | O19: ='Q1 FY26-27'!O19 -> 72049 | P19: =O19/O$10 -> 0.0017601135 | Q19: ='Q1 FY26-27'!Q19 -> 0 | R19: =Q19/Q$10 -> #DIV/0! | S19: ='Q1 FY26-27'!S19 -> 179253.69 | T19: =S19/S$10 -> 0.10751471 | U19: ='Q1 FY26-27'!U19 -> 0 | V19: =U19/U$10 -> #DIV/0! | W19: ='Q1 FY26-27'!W19 -> 406787.44 | X19: =W19/W$10 -> 0.016089317 | Y19: ='Q1 FY26-27'!Y19 -> 0 | Z19: =Y19/Y$10 -> #DIV/0! | AA19: ='Q1 FY26-27'!AA19 -> 215071.5 | AB19: =AA19/AA$10 -> 0.011233434 | AC19: ='Q1 FY26-27'!AC19 -> 0 | AD19: =AC19/AC$10 -> #DIV/0! | AE19: ='Q1 FY26-27'!AE19 -> 187484 | AF19: =AE19/AE$10 -> 0.0054767455 | AG19: ='Q1 FY26-27'!AG19 -> 0 | AH19: =AG19/AG$10 -> #DIV/0! | AI19: ='Q1 FY26-27'!AI19 -> 80000 | AJ19: =AI19/AI$10 -> #DIV/0! | AK19: ='Q1 FY26-27'!AK19 -> 0 | AL19: =AK19/AK$10 -> #DIV/0! | AM19: ='Q1 FY26-27'!AM19 -> 103790.78 | AN19: =AM19/AM$10 -> 0.10689129 | AO19: ='Q1 FY26-27'!AO19 -> 0 | AP19: =AO19/AO$10 -> #DIV/0! | AQ19: ='Q1 FY26-27'!AQ19 -> 52063.98 | AR19: =AQ19/AQ$10 -> 0.0021562026 | AS19: ='Q1 FY26-27'!AS19 -> 35000 | AU19: ='Q1 FY26-27'!AU19 -> 113959.52 | AV19: =AU19/AU$10 -> 0.17089818 | AW19: ='Q1 FY26-27'!AW19 -> 0 | AY19: ='Q1 FY26-27'!AY19 -> 43183.46 | BA19: ='Q1 FY26-27'!BA19 -> 0 | BC19: ='Q1 FY26-27'!BC19 -> 43467.03 | BE19: ='Q1 FY26-27'!BE19 -> 0 | BG19: ='Q1 FY26-27'!BG19 -> 14848 | BI19: ='Q1 FY26-27'!BI19 -> 0
B20: Sales Commission | C20: =G20+K20 -> 4609465.1 | D20: =C20/$C$10 -> 0.030973632 | E20: =I20+M20 -> #REF! | F20: =E20/E$10 -> #REF! | G20: ='Q1 FY26-27'!G20 -> 0 | H20: =G20/$C$10 -> 0 | I20: ='Q1 FY26-27'!I20 -> 0 | J20: =I20/$C$10 -> 0 | K20: =O20+S20+W20+AA20+AE20+AI20+AM20+AQ20+AU20+AY20+BC20+BG20 -> 4609465.1 | L20: =K20/$K$10 -> 0.030973632 | M20: =Q20+U20+Y20+AC20+AG20+AK20+AO20 -> #REF! | N20: =M20/M$10 -> #REF! | O20: ='Q1 FY26-27'!O20 -> 173480.51 | P20: =O20/O$10 -> 0.0042380239 | Q20: ='Q1 FY26-27'!Q20 -> 0 | R20: =Q20/Q$10 -> #DIV/0! | S20: ='Q1 FY26-27'!S20 -> 228974.03 | T20: =S20/S$10 -> 0.13733651 | U20: ='Q1 FY26-27'!U20 -> 0 | V20: =U20/U$10 -> #DIV/0! | W20: ='Q1 FY26-27'!W20 -> 960909.79 | X20: =W20/W$10 -> 0.038006047 | Y20: ='Q1 FY26-27'!Y20 -> #REF! | Z20: =Y20/Y$10 -> #REF! | AA20: ='Q1 FY26-27'!AA20 -> 1396555.2 | AB20: =AA20/AA$10 -> 0.072943698 | AC20: ='Q1 FY26-27'!AC20 -> 0 | AD20: =AC20/AC$10 -> #DIV/0! | AE20: ='Q1 FY26-27'!AE20 -> 1307943 | AF20: =AE20/AE$10 -> 0.038207372 | AG20: ='Q1 FY26-27'!AG20 -> 0 | AH20: =AG20/AG$10 -> #DIV/0! | AI20: ='Q1 FY26-27'!AI20 -> 0 | AJ20: =AI20/AI$10 -> #DIV/0! | AK20: ='Q1 FY26-27'!AK20 -> 0 | AL20: =AK20/AK$10 -> #DIV/0! | AM20: ='Q1 FY26-27'!AM20 -> 78387.37 | AN20: =AM20/AM$10 -> 0.08072901 | AO20: ='Q1 FY26-27'!AO20 -> 0 | AP20: =AO20/AO$10 -> #DIV/0! | AQ20: ='Q1 FY26-27'!AQ20 -> 0 | AR20: =AQ20/AQ$10 -> 0 | AS20: ='Q1 FY26-27'!AS20 -> 0 | AU20: ='Q1 FY26-27'!AU20 -> 162351.79 | AV20: =AU20/AU$10 -> 0.24346913 | AW20: ='Q1 FY26-27'!AW20 -> 0 | AY20: ='Q1 FY26-27'!AY20 -> 69035.85 | BA20: ='Q1 FY26-27'!BA20 -> 0 | BC20: ='Q1 FY26-27'!BC20 -> 85672.94 | BE20: ='Q1 FY26-27'!BE20 -> 0 | BG20: ='Q1 FY26-27'!BG20 -> 146154.56 | BI20: ='Q1 FY26-27'!BI20 -> 0
B21: Rental & Utility Expenses | C21: =G21+K21 -> 16374761 | D21: =C21/$C$10 -> 0.11003138 | E21: =I21+M21 -> 3057546 | F21: =E21/E$10 -> #DIV/0! | G21: ='Q1 FY26-27'!G21 -> 1627794.7 | H21: =G21/$C$10 -> 0.010938084 | I21: ='Q1 FY26-27'!I21 -> 0 | J21: =I21/$C$10 -> 0 | K21: =O21+S21+W21+AA21+AE21+AI21+AM21+AQ21+AU21+AY21+BC21+BG21 -> 14746966 | L21: =K21/$K$10 -> 0.099093299 | M21: =Q21+U21+Y21+AC21+AG21+AK21+AO21 -> 3057546 | N21: =M21/M$10 -> #DIV/0! | O21: ='Q1 FY26-27'!O21 -> 3665933.8 | P21: =O21/O$10 -> 0.089556545 | Q21: ='Q1 FY26-27'!Q21 -> 1419717 | R21: =Q21/Q$10 -> #DIV/0! | S21: ='Q1 FY26-27'!S21 -> 213175 | T21: =S21/S$10 -> 0.1278604 | U21: ='Q1 FY26-27'!U21 -> 76212 | V21: =U21/U$10 -> #DIV/0! | W21: ='Q1 FY26-27'!W21 -> 3480038.3 | X21: =W21/W$10 -> 0.13764299 | Y21: ='Q1 FY26-27'!Y21 -> 1314963 | Z21: =Y21/Y$10 -> #DIV/0! | AA21: ='Q1 FY26-27'!AA21 -> 2210248 | AB21: =AA21/AA$10 -> 0.11544382 | AC21: ='Q1 FY26-27'!AC21 -> 0 | AD21: =AC21/AC$10 -> #DIV/0! | AE21: ='Q1 FY26-27'!AE21 -> 2351243 | AF21: =AE21/AE$10 -> 0.068684045 | AG21: ='Q1 FY26-27'!AG21 -> 0 | AH21: =AG21/AG$10 -> #DIV/0! | AI21: ='Q1 FY26-27'!AI21 -> 370741 | AJ21: =AI21/AI$10 -> #DIV/0! | AK21: ='Q1 FY26-27'!AK21 -> 90931 | AL21: =AK21/AK$10 -> #DIV/0! | AM21: ='Q1 FY26-27'!AM21 -> 489829 | AN21: =AM21/AM$10 -> 0.5044615 | AO21: ='Q1 FY26-27'!AO21 -> 155723 | AP21: =AO21/AO$10 -> #DIV/0! | AQ21: ='Q1 FY26-27'!AQ21 -> 1965758 | AR21: =AQ21/AQ$10 -> 0.081410844 | AS21: ='Q1 FY26-27'!AS21 -> 2419 | AU21: ='Q1 FY26-27'!AU21 -> 0 | AV21: =AU21/AU$10 -> 0 | AW21: ='Q1 FY26-27'!AW21 -> 0 | AY21: ='Q1 FY26-27'!AY21 -> 0 | BA21: ='Q1 FY26-27'!BA21 -> 0 | BC21: ='Q1 FY26-27'!BC21 -> 0 | BE21: ='Q1 FY26-27'!BE21 -> 0 | BG21: ='Q1 FY26-27'!BG21 -> 0 | BI21: ='Q1 FY26-27'!BI21 -> 0
B22: Salary & Staff Expenses | C22: =G22+K22 -> 48806327 | D22: =C22/$C$10 -> 0.32795762 | E22: =I22+M22 -> 758150 | F22: =E22/E$10 -> #DIV/0! | G22: ='Q1 FY26-27'!G22 -> 7747821.5 | H22: =G22/$C$10 -> 0.052062043 | I22: ='Q1 FY26-27'!I22 -> 0 | J22: =I22/$C$10 -> 0 | K22: =O22+S22+W22+AA22+AE22+AI22+AM22+AQ22+AU22+AY22+BC22+BG22 -> 41058506 | L22: =K22/$K$10 -> 0.27589558 | M22: =Q22+U22+Y22+AC22+AG22+AK22+AO22 -> 758150 | N22: =M22/M$10 -> #DIV/0! | O22: ='Q1 FY26-27'!O22 -> 10602073 | P22: =O22/O$10 -> 0.25900224 | Q22: ='Q1 FY26-27'!Q22 -> 663750 | R22: =Q22/Q$10 -> #DIV/0! | S22: ='Q1 FY26-27'!S22 -> 679710.73 | T22: =S22/S$10 -> 0.40768424 | U22: ='Q1 FY26-27'!U22 -> 0 | V22: =U22/U$10 -> #DIV/0! | W22: ='Q1 FY26-27'!W22 -> 6422135 | X22: =W22/W$10 -> 0.25400924 | Y22: ='Q1 FY26-27'!Y22 -> 0 | Z22: =Y22/Y$10 -> #DIV/0! | AA22: ='Q1 FY26-27'!AA22 -> 3537149.7 | AB22: =AA22/AA$10 -> 0.18474943 | AC22: ='Q1 FY26-27'!AC22 -> 0 | AD22: =AC22/AC$10 -> #DIV/0! | AE22: ='Q1 FY26-27'!AE22 -> 7545416 | AF22: =AE22/AE$10 -> 0.2204152 | AG22: ='Q1 FY26-27'!AG22 -> 0 | AH22: =AG22/AG$10 -> #DIV/0! | AI22: ='Q1 FY26-27'!AI22 -> 460392 | AJ22: =AI22/AI$10 -> #DIV/0! | AK22: ='Q1 FY26-27'!AK22 -> 0 | AL22: =AK22/AK$10 -> #DIV/0! | AM22: ='Q1 FY26-27'!AM22 -> 3028630.6 | AN22: =AM22/AM$10 -> 3.1191039 | AO22: ='Q1 FY26-27'!AO22 -> 94400 | AP22: =AO22/AO$10 -> #DIV/0! | AQ22: ='Q1 FY26-27'!AQ22 -> 7579231.5 | AR22: =AQ22/AQ$10 -> 0.31388993 | AS22: ='Q1 FY26-27'!AS22 -> 0 | AU22: ='Q1 FY26-27'!AU22 -> 0 | AV22: =AU22/AU$10 -> 0 | AW22: ='Q1 FY26-27'!AW22 -> 0 | AY22: ='Q1 FY26-27'!AY22 -> 0 | BA22: ='Q1 FY26-27'!BA22 -> 0 | BC22: ='Q1 FY26-27'!BC22 -> 0 | BE22: ='Q1 FY26-27'!BE22 -> 0 | BG22: ='Q1 FY26-27'!BG22 -> 1203766.5 | BI22: ='Q1 FY26-27'!BI22 -> 0
B23: Bank and Finance Charges | C23: =G23+K23 -> 1958841 | D23: =C23/$C$10 -> 0.013162573 | E23: =I23+M23 -> 0 | F23: =E23/E$10 -> #DIV/0! | G23: ='Q1 FY26-27'!G23 -> 813941 | H23: =G23/$C$10 -> 0.005469335 | I23: ='Q1 FY26-27'!I23 -> 0 | J23: =I23/$C$10 -> 0 | K23: =O23+S23+W23+AA23+AE23+AI23+AM23+AQ23+AU23+AY23+BC23+BG23 -> 1144900 | L23: =K23/$K$10 -> 0.0076932376 | M23: =Q23+U23+Y23+AC23+AG23+AK23+AO23 -> 0 | N23: =M23/M$10 -> #DIV/0! | O23: ='Q1 FY26-27'!O23 -> 947509.88 | P23: =O23/O$10 -> 0.023147093 | Q23: ='Q1 FY26-27'!Q23 -> 0 | R23: =Q23/Q$10 -> #DIV/0! | S23: ='Q1 FY26-27'!S23 -> 0 | T23: =S23/S$10 -> 0 | U23: ='Q1 FY26-27'!U23 -> 0 | V23: =U23/U$10 -> #DIV/0! | W23: ='Q1 FY26-27'!W23 -> 46560.5 | X23: =W23/W$10 -> 0.0018415678 | Y23: ='Q1 FY26-27'!Y23 -> 0 | Z23: =Y23/Y$10 -> #DIV/0! | AA23: ='Q1 FY26-27'!AA23 -> 55147.82 | AB23: =AA23/AA$10 -> 0.0028804345 | AC23: ='Q1 FY26-27'!AC23 -> 0 | AD23: =AC23/AC$10 -> #DIV/0! | AE23: ='Q1 FY26-27'!AE23 -> 47677.73 | AF23: =AE23/AE$10 -> 0.0013927524 | AG23: ='Q1 FY26-27'!AG23 -> 0 | AH23: =AG23/AG$10 -> #DIV/0! | AI23: ='Q1 FY26-27'!AI23 -> 0 | AJ23: =AI23/AI$10 -> #DIV/0! | AK23: ='Q1 FY26-27'!AK23 -> 0 | AL23: =AK23/AK$10 -> #DIV/0! | AM23: ='Q1 FY26-27'!AM23 -> 11118.42 | AN23: =AM23/AM$10 -> 0.011450557 | AO23: ='Q1 FY26-27'!AO23 -> 0 | AP23: =AO23/AO$10 -> #DIV/0! | AQ23: ='Q1 FY26-27'!AQ23 -> 36885.62 | AR23: =AQ23/AQ$10 -> 0.0015275987 | AS23: ='Q1 FY26-27'!AS23 -> 0 | AU23: ='Q1 FY26-27'!AU23 -> 0 | AV23: =AU23/AU$10 -> 0 | AW23: ='Q1 FY26-27'!AW23 -> 0 | AY23: ='Q1 FY26-27'!AY23 -> 0 | BA23: ='Q1 FY26-27'!BA23 -> 0 | BC23: ='Q1 FY26-27'!BC23 -> 0 | BE23: ='Q1 FY26-27'!BE23 -> 0 | BG23: ='Q1 FY26-27'!BG23 -> 0 | BI23: ='Q1 FY26-27'!BI23 -> 0
B24: Software and Subscription | C24: =G24+K24 -> 964259.07 | D24: =C24/$C$10 -> 0.0064794081 | E24: =I24+M24 -> 134471.92 | F24: =E24/E$10 -> #DIV/0! | G24: ='Q1 FY26-27'!G24 -> 241237.57 | H24: =G24/$C$10 -> 0.0016210132 | I24: ='Q1 FY26-27'!I24 -> 0 | J24: =I24/$C$10 -> 0 | K24: =O24+S24+W24+AA24+AE24+AI24+AM24+AQ24+AU24+AY24+BC24+BG24 -> 723021.5 | L24: =K24/$K$10 -> 0.0048583949 | M24: =Q24+U24+Y24+AC24+AG24+AK24+AO24 -> 134471.92 | N24: =M24/M$10 -> #DIV/0! | O24: ='Q1 FY26-27'!O24 -> 48494.333 | P24: =O24/O$10 -> 0.0011846872 | Q24: ='Q1 FY26-27'!Q24 -> 0 | R24: =Q24/Q$10 -> #DIV/0! | S24: ='Q1 FY26-27'!S24 -> 46181 | T24: =S24/S$10 -> 0.027698939 | U24: ='Q1 FY26-27'!U24 -> 0 | V24: =U24/U$10 -> #DIV/0! | W24: ='Q1 FY26-27'!W24 -> 127370.67 | X24: =W24/W$10 -> 0.0050377835 | Y24: ='Q1 FY26-27'!Y24 -> 0 | Z24: =Y24/Y$10 -> #DIV/0! | AA24: ='Q1 FY26-27'!AA24 -> 99640.667 | AB24: =AA24/AA$10 -> 0.0052043475 | AC24: ='Q1 FY26-27'!AC24 -> 49820.333 | AD24: =AC24/AC$10 -> #DIV/0! | AE24: ='Q1 FY26-27'!AE24 -> 155690.67 | AF24: =AE24/AE$10 -> 0.0045480049 | AG24: ='Q1 FY26-27'!AG24 -> 77845.333 | AH24: =AG24/AG$10 -> #DIV/0! | AI24: ='Q1 FY26-27'!AI24 -> 13612.5 | AJ24: =AI24/AI$10 -> #DIV/0! | AK24: ='Q1 FY26-27'!AK24 -> 6806.25 | AL24: =AK24/AK$10 -> #DIV/0! | AM24: ='Q1 FY26-27'!AM24 -> 72561.333 | AN24: =AM24/AM$10 -> 0.074728934 | AO24: ='Q1 FY26-27'!AO24 -> 0 | AP24: =AO24/AO$10 -> #DIV/0! | AQ24: ='Q1 FY26-27'!AQ24 -> 6293.3333 | AR24: =AQ24/AQ$10 -> 0.00026063512 | AS24: ='Q1 FY26-27'!AS24 -> 3146.6667 | AU24: ='Q1 FY26-27'!AU24 -> 58819 | AV24: =AU24/AU$10 -> 0.088207287 | AW24: ='Q1 FY26-27'!AW24 -> 0 | AY24: ='Q1 FY26-27'!AY24 -> 46182 | BA24: ='Q1 FY26-27'!BA24 -> 0 | BC24: ='Q1 FY26-27'!BC24 -> 46182 | BE24: ='Q1 FY26-27'!BE24 -> 0 | BG24: ='Q1 FY26-27'!BG24 -> 1994 | BI24: ='Q1 FY26-27'!BI24 -> 0
B25: Other Outlet Costs | C25: =G25+K25 -> 9882304.1 | D25: =C25/$C$10 -> 0.066404852 | E25: =I25+M25 -> 356555.58 | F25: =E25/E$10 -> #DIV/0! | G25: ='Q1 FY26-27'!G25 -> 2184064 | H25: =G25/$C$10 -> 0.014675975 | I25: ='Q1 FY26-27'!I25 -> 737.5 | J25: =I25/$C$10 -> 4.9556842e-06 | K25: =O25+S25+W25+AA25+AE25+AI25+AM25+AQ25+AU25+AY25+BC25+BG25 -> 7698240.1 | L25: =K25/$K$10 -> 0.051728877 | M25: =Q25+U25+Y25+AC25+AG25+AK25+AO25 -> 355818.08 | N25: =M25/M$10 -> #DIV/0! | O25: ='Q1 FY26-27'!O25 -> 2374341.3 | P25: =O25/O$10 -> 0.05800372 | Q25: ='Q1 FY26-27'!Q25 -> 184154.58 | R25: =Q25/Q$10 -> #DIV/0! | S25: ='Q1 FY26-27'!S25 -> 155919 | T25: =S25/S$10 -> 0.093518781 | U25: ='Q1 FY26-27'!U25 -> 0 | V25: =U25/U$10 -> #DIV/0! | W25: ='Q1 FY26-27'!W25 -> 1114412.7 | X25: =W25/W$10 -> 0.044077415 | Y25: ='Q1 FY26-27'!Y25 -> 0 | Z25: =Y25/Y$10 -> #DIV/0! | AA25: ='Q1 FY26-27'!AA25 -> 468887.5 | AB25: =AA25/AA$10 -> 0.024490537 | AC25: ='Q1 FY26-27'!AC25 -> 15522.25 | AD25: =AC25/AC$10 -> #DIV/0! | AE25: ='Q1 FY26-27'!AE25 -> 922235.09 | AF25: =AE25/AE$10 -> 0.026940149 | AG25: ='Q1 FY26-27'!AG25 -> 133043 | AH25: =AG25/AG$10 -> #DIV/0! | AI25: ='Q1 FY26-27'!AI25 -> 1414742.5 | AJ25: =AI25/AI$10 -> #DIV/0! | AK25: ='Q1 FY26-27'!AK25 -> 5934.9167 | AL25: =AK25/AK$10 -> #DIV/0! | AM25: ='Q1 FY26-27'!AM25 -> 161457.6 | AN25: =AM25/AM$10 -> 0.16628077 | AO25: ='Q1 FY26-27'!AO25 -> 17163.333 | AP25: =AO25/AO$10 -> #DIV/0! | AQ25: ='Q1 FY26-27'!AQ25 -> 994208.45 | AR25: =AQ25/AQ$10 -> 0.041174625 | AS25: ='Q1 FY26-27'!AS25 -> 212632.08 | AU25: ='Q1 FY26-27'!AU25 -> 8100 | AV25: =AU25/AU$10 -> 0.012147079 | AW25: ='Q1 FY26-27'!AW25 -> 0 | AY25: ='Q1 FY26-27'!AY25 -> 8100 | BA25: ='Q1 FY26-27'!BA25 -> 0 | BC25: ='Q1 FY26-27'!BC25 -> 0 | BE25: ='Q1 FY26-27'!BE25 -> 0 | BG25: ='Q1 FY26-27'!BG25 -> 75836 | BI25: ='Q1 FY26-27'!BI25 -> 0
B26: Other Professional Fees | C26: =G26+K26 -> 925817 | D26: =C26/$C$10 -> 0.0062210938 | E26: =I26+M26 -> 10010 | F26: =E26/E$10 -> #DIV/0! | G26: ='Q1 FY26-27'!G26 -> 828298 | H26: =G26/$C$10 -> 0.0055658079 | I26: ='Q1 FY26-27'!I26 -> 0 | J26: =I26/$C$10 -> 0 | K26: =O26+S26+W26+AA26+AE26+AI26+AM26+AQ26+AU26+AY26+BC26+BG26 -> 97519 | L26: =K26/$K$10 -> 0.00065528593 | M26: =Q26+U26+Y26+AC26+AG26+AK26+AO26 -> 10010 | N26: =M26/M$10 -> #DIV/0! | O26: ='Q1 FY26-27'!O26 -> 40644 | P26: =O26/O$10 -> 0.00099290832 | Q26: ='Q1 FY26-27'!Q26 -> 0 | R26: =Q26/Q$10 -> #DIV/0! | S26: ='Q1 FY26-27'!S26 -> 0 | T26: =S26/S$10 -> 0 | U26: ='Q1 FY26-27'!U26 -> 0 | V26: =U26/U$10 -> #DIV/0! | W26: ='Q1 FY26-27'!W26 -> 20335 | X26: =W26/W$10 -> 0.00080429294 | Y26: ='Q1 FY26-27'!Y26 -> 0 | Z26: =Y26/Y$10 -> #DIV/0! | AA26: ='Q1 FY26-27'!AA26 -> 0 | AB26: =AA26/AA$10 -> 0 | AC26: ='Q1 FY26-27'!AC26 -> 0 | AD26: =AC26/AC$10 -> #DIV/0! | AE26: ='Q1 FY26-27'!AE26 -> 20020 | AF26: =AE26/AE$10 -> 0.00058482028 | AG26: ='Q1 FY26-27'!AG26 -> 10010 | AH26: =AG26/AG$10 -> #DIV/0! | AI26: ='Q1 FY26-27'!AI26 -> 0 | AJ26: =AI26/AI$10 -> #DIV/0! | AK26: ='Q1 FY26-27'!AK26 -> 0 | AL26: =AK26/AK$10 -> #DIV/0! | AM26: ='Q1 FY26-27'!AM26 -> 0 | AN26: =AM26/AM$10 -> 0 | AO26: ='Q1 FY26-27'!AO26 -> 0 | AP26: =AO26/AO$10 -> #DIV/0! | AQ26: ='Q1 FY26-27'!AQ26 -> 16520 | AR26: =AQ26/AQ$10 -> 0.0006841672 | AS26: ='Q1 FY26-27'!AS26 -> 8260 | AU26: ='Q1 FY26-27'!AU26 -> 0 | AV26: =AU26/AU$10 -> 0 | AW26: ='Q1 FY26-27'!AW26 -> 0 | AY26: ='Q1 FY26-27'!AY26 -> 0 | BA26: ='Q1 FY26-27'!BA26 -> 0 | BC26: ='Q1 FY26-27'!BC26 -> 0 | BE26: ='Q1 FY26-27'!BE26 -> 0 | BG26: ='Q1 FY26-27'!BG26 -> 0 | BI26: ='Q1 FY26-27'!BI26 -> 0
B27: Other Expenses | C27: =G27+K27 -> -3582848.6 | D27: =C27/$C$10 -> -0.024075208 | E27: =I27+M27 -> 0 | F27: =E27/E$10 -> #DIV/0! | G27: ='Q1 FY26-27'!G27 -> 423825.41 | H27: =G27/$C$10 -> 0.0028479253 | I27: ='Q1 FY26-27'!I27 -> 0 | J27: =I27/$C$10 -> 0 | K27: =O27+S27+W27+AA27+AE27+AI27+AM27+AQ27+AU27+AY27+BC27+BG27 -> -4006674 | L27: =K27/$K$10 -> -0.026923134 | M27: =Q27+U27+Y27+AC27+AG27+AK27+AO27 -> 0 | N27: =M27/M$10 -> #DIV/0! | O27: ='Q1 FY26-27'!O27 -> 0 | P27: =O27/O$10 -> 0 | Q27: ='Q1 FY26-27'!Q27 -> 0 | R27: =Q27/Q$10 -> #DIV/0! | S27: ='Q1 FY26-27'!S27 -> 0 | T27: =S27/S$10 -> 0 | U27: ='Q1 FY26-27'!U27 -> 0 | V27: =U27/U$10 -> #DIV/0! | W27: ='Q1 FY26-27'!W27 -> 0 | X27: =W27/W$10 -> 0 | Y27: ='Q1 FY26-27'!Y27 -> 0 | Z27: =Y27/Y$10 -> #DIV/0! | AA27: ='Q1 FY26-27'!AA27 -> 0 | AB27: =AA27/AA$10 -> 0 | AC27: ='Q1 FY26-27'!AC27 -> 0 | AD27: =AC27/AC$10 -> #DIV/0! | AE27: ='Q1 FY26-27'!AE27 -> 0 | AF27: =AE27/AE$10 -> 0 | AG27: ='Q1 FY26-27'!AG27 -> 0 | AH27: =AG27/AG$10 -> #DIV/0! | AI27: ='Q1 FY26-27'!AI27 -> 0 | AJ27: =AI27/AI$10 -> #DIV/0! | AK27: ='Q1 FY26-27'!AK27 -> 0 | AL27: =AK27/AK$10 -> #DIV/0! | AM27: ='Q1 FY26-27'!AM27 -> -4016974 | AN27: =AM27/AM$10 -> -4.1369717 | AO27: ='Q1 FY26-27'!AO27 -> 0 | AP27: =AO27/AO$10 -> #DIV/0! | AQ27: ='Q1 FY26-27'!AQ27 -> 0 | AR27: =AQ27/AQ$10 -> 0 | AS27: ='Q1 FY26-27'!AS27 -> 0 | AU27: ='Q1 FY26-27'!AU27 -> 0 | AV27: =AU27/AU$10 -> 0 | AW27: ='Q1 FY26-27'!AW27 -> 0 | AY27: ='Q1 FY26-27'!AY27 -> 0 | BA27: ='Q1 FY26-27'!BA27 -> 0 | BC27: ='Q1 FY26-27'!BC27 -> 0 | BE27: ='Q1 FY26-27'!BE27 -> 0 | BG27: ='Q1 FY26-27'!BG27 -> 10300 | BI27: ='Q1 FY26-27'!BI27 -> 0
B28: Total Other Expenses | C28: =SUM(C18:C27) -> 85528372 | D28: =C28/C10 -> 0.57471404 | E28: =I28+M28 -> #REF! | F28: =E28/E$10 -> #REF! | G28: ='Q1 FY26-27'!G28 -> 14101185 | H28: =G28/C10 -> 0.094753924 | I28: ='Q1 FY26-27'!I28 -> 53837.5 | J28: =I28/E10 -> #DIV/0! | K28: =SUM(K18:K27) -> 71427187 | L28: =K28/$K$10 -> 0.47996011 | M28: =SUM(M18:M27) -> #REF! | N28: =M28/M$10 -> #REF! | O28: =SUM(O18:O27) -> 18874107 | P28: =O28/O$10 -> 0.46108301 | Q28: =SUM(Q18:Q27) -> 2267621.6 | R28: =Q28/Q$10 -> #DIV/0! | S28: =SUM(S18:S27) -> 1594493.7 | T28: =S28/S$10 -> 0.95636266 | U28: ='Q1 FY26-27'!U28 -> 76212 | V28: =U28/U$10 -> #DIV/0! | W28: =SUM(W18:W27) -> 13328559 | X28: =W28/W$10 -> 0.52717316 | Y28: ='Q1 FY26-27'!Y28 -> #REF! | Z28: =Y28/Y$10 -> #REF! | AA28: =SUM(AA18:AA27) -> 8465905.3 | AB28: =AA28/AA$10 -> 0.44218404 | AC28: ='Q1 FY26-27'!AC28 -> 65342.583 | AD28: =AC28/AC$10 -> #DIV/0! | AE28: =SUM(AE18:AE27) -> 13526888 | AF28: =AE28/AE$10 -> 0.39514477 | AG28: ='Q1 FY26-27'!AG28 -> 220898.33 | AH28: =AG28/AG$10 -> #DIV/0! | AI28: =SUM(AI18:AI27) -> 2375002 | AJ28: =AI28/AI$10 -> #DIV/0! | AK28: ='Q1 FY26-27'!AK28 -> 103672.17 | AL28: =AK28/AK$10 -> #DIV/0! | AM28: =SUM(AM18:AM27) -> -0.06 | AN28: =AM28/AM$10 -> -6.179236e-08 | AO28: ='Q1 FY26-27'!AO28 -> 267286.33 | AP28: =AO28/AO$10 -> #DIV/0! | AQ28: =SUM(AQ18:AQ27) -> 11118566 | AR28: =AQ28/AQ$10 -> 0.46046962 | AS28: ='Q1 FY26-27'!AS28 -> 261457.75 | AU28: =SUM(AU18:AU27) -> 343230.31 | AV28: =AU28/AU$10 -> 0.51472168 | AW28: =SUM(AW18:AW27) -> 0 | AY28: =SUM(AY18:AY27) -> 166501.31 | BA28: =SUM(BA18:BA27) -> 0 | BC28: =SUM(BC18:BC27) -> 175321.97 | BE28: =SUM(BE18:BE27) -> 0 | BG28: =SUM(BG18:BG27) -> 1458612.1 | BI28: =SUM(BI18:BI27) -> 0
B30: EBIDTA | C30: =C16-C28 -> 5558250.2 | D30: =C30/C$10 -> 0.037349061 | E30: =E16-E28 -> #REF! | F30: =E30/E$10 -> #REF! | G30: =G16-G28 -> -14101185 | H30: =G30/C10 -> -0.094753924 | I30: =I16-I28 -> -53837.5 | J30: =I30/E10 -> #DIV/0! | K30: =K16-K28 -> 19659435 | L30: =K30/$K$10 -> 0.13210299 | M30: =M16-M28 -> #REF! | N30: =M30/M$10 -> #REF! | O30: =O16-O28 -> 7693765.5 | P30: =O30/O$10 -> 0.18795404 | Q30: =Q16-Q28 -> -2267621.6 | R30: =Q30/Q$10 -> #DIV/0! | S30: =S16-S28 -> -573873.19 | T30: =S30/S$10 -> -0.34420386 | U30: =U16-U28 -> -76212 | V30: =U30/U$10 -> #DIV/0! | W30: =W16-W28 -> 1718626.1 | X30: =W30/W$10 -> 0.067975355 | Y30: =Y16-Y28 -> #REF! | Z30: =Y30/Y$10 -> #REF! | AA30: =AA16-AA28 -> 3294340.5 | AB30: =AA30/AA$10 -> 0.17206722 | AC30: =AC16-AC28 -> -65342.583 | AD30: =AC30/AC$10 -> #DIV/0! | AE30: =AE16-AE28 -> 8770468.7 | AF30: =AE30/AE$10 -> 0.2562012 | AG30: =AG16-AG28 -> -220898.33 | AH30: =AG30/AG$10 -> #DIV/0! | AI30: =AI16-AI28 -> -2376032 | AJ30: =AI30/AI$10 -> #DIV/0! | AK30: =AK16-AK28 -> -103672.17 | AL30: =AK30/AK$10 -> #DIV/0! | AM30: =AM16-AM28 -> -929566.1 | AN30: =AM30/AM$10 -> -0.95733473 | AO30: =AO16-AO28 -> -267286.33 | AP30: =AO30/AO$10 -> #DIV/0! | AQ30: =AQ16-AQ28 -> 3506230.1 | AR30: =AQ30/AQ$10 -> 0.1452087 | AS30: =AS16-AS28 -> -261457.75 | AT30: =AS30/AS$10 -> #DIV/0! | AU30: =AU16-AU28 -> -123531.44 | AV30: =AU30/AU$10 -> -0.18525261 | AW30: =AW16-AW28 -> 0 | AY30: =AY16-AY28 -> -287048.43 | BA30: =BA16-BA28 -> 0 | BC30: =BC16-BC28 -> -369427.62 | BE30: =BE16-BE28 -> 0 | BG30: =BG16-BG28 -> -664517.3 | BI30: =BI16-BI28 -> 0
C33: ='Q1 FY26-27'!C10 -> 1.4881901e+08 | G33: ='Q1 FY26-27'!G10 -> 0 | K33: ='Q1 FY26-27'!K10 -> 1.4881901e+08 | O33: ='Q1 FY26-27'!O10 -> 40934293 | S33: ='Q1 FY26-27'!S10 -> 1667248 | W33: ='Q1 FY26-27'!W10 -> 25283076 | AA33: ='Q1 FY26-27'!AA10 -> 19145660 | AE33: ='Q1 FY26-27'!AE10 -> 34232739 | AI33: ='Q1 FY26-27'!AI10 -> 0 | AM33: ='Q1 FY26-27'!AM10 -> 970993.82 | AQ33: ='Q1 FY26-27'!AQ10 -> 24146144 | AU33: ='Q1 FY26-27'!AU10 -> 666826.99 | AY33: ='Q1 FY26-27'!AY10 -> 228077.89 | BC33: ='Q1 FY26-27'!BC10 -> 306961.08 | BG33: ='Q1 FY26-27'!BG10 -> 1236985
C35: =C10-C33 -> 0 | G35: =G10-G33 -> 0 | K35: =K10-K33 -> 0 | O35: =O10-O33 -> 0 | S35: =S10-S33 -> 0 | W35: =W10-W33 -> 0 | AA35: =AA10-AA33 -> 0 | AE35: =AE10-AE33 -> 0 | AI35: =AI10-AI33 -> 0 | AM35: =AM10-AM33 -> 0 | AQ35: =AQ10-AQ33 -> 0 | AU35: =AU10-AU33 -> 0 | AY35: =AY10-AY33 -> 0 | BC35: =BC10-BC33 -> 0 | BG35: =BG10-BG33 -> 0

Sheet Q1 FY26-27
B1: FY26-27 Budgeted vs Actual MIS
B2: Food Matters Group | Quarter 1 | FY26-27
C3: Total with HO | G3: HO | K3: Outlets Total | O3: Table Total | S3: Iktara | W3: Mg St Colaba | AA3: Mg St LP | AE3: Mg St Bandra | AI3: MSK Events | AM3: MSBC | AQ3: Kaspers | AU3: MSBC Andheri | AY3: MSBC Dahisar | BC3: MSBC Juhu/Goregaon | BG3: Loud Mouth
C4: Amount | D4: %age | E4: Budgeted | F4: %age | G4: Amount | H4: %age | I4: Budgeted | J4: %age | K4: Amount | L4: %age | M4: Budgeted | N4: %age | O4: Amount | P4: %age | Q4: Budgeted | R4: %age | S4: Amount | T4: %age | U4: Budgeted | V4: %age | W4: Amount | X4: %age | Y4: Budgeted | Z4: %age | AA4: Amount | AB4: %age | AC4: Budgeted | AD4: %age | AE4: Amount | AF4: %age | AG4: Budgeted | AH4: %age | AI4: Amount | AJ4: %age | AK4: Budgeted | AL4: %age | AM4: Amount | AN4: %age | AO4: Budgeted | AP4: %age | AQ4: Amount | AR4: %age | AS4: Budgeted | AT4: %age | AU4: Amount | AV4: %age | AW4: Budgeted | AX4: %age | AY4: Amount | AZ4: %age | BA4: Budgeted | BB4: %age | BC4: Amount | BD4: %age | BE4: Budgeted | BF4: %age | BG4: Amount | BH4: %age | BI4: Budgeted | BJ4: %age
B5: Beverage | C5: =G5+K5 -> 11608400 | D5: =C5/$C$10 -> 0.078003476 | E5: =I5+M5 -> 0 | F5: =E5/$E$10 -> #DIV/0! | G5: ='Summary Sheet - April 2026'!G5 + 'Summary Sheet - May 2026'!G5 + 'Summary Sheet - June 2026'!G5 -> 0 | I5: ='Summary Sheet - April 2026'!I5 + 'Summary Sheet - May 2026'!I5 + 'Summary Sheet - June 2026'!I5 -> 0 | K5: =O5+S5+W5+AA5+AE5+AI5+AM5+AQ5+AU5+AY5+BC5+BG5 -> 11608400 | M5: =Q5+U5+Y5+AC5+AG5+AK5+AO5 -> 0 | O5: ='Summary Sheet - April 2026'!O5 + 'Summary Sheet - May 2026'!O5 + 'Summary Sheet - June 2026'!O5 -> 2407580 | Q5: ='Summary Sheet - April 2026'!Q5 + 'Summary Sheet - May 2026'!Q5 + 'Summary Sheet - June 2026'!Q5 -> 0 | S5: ='Summary Sheet - April 2026'!S5 + 'Summary Sheet - May 2026'!S5 + 'Summary Sheet - June 2026'!S5 -> 0 | U5: ='Summary Sheet - April 2026'!U5 + 'Summary Sheet - May 2026'!U5 + 'Summary Sheet - June 2026'!U5 -> 0 | W5: ='Summary Sheet - April 2026'!W5+'Summary Sheet - May 2026'!W5 + 'Summary Sheet - June 2026'!W5 -> 2398144 | Y5: ='Summary Sheet - April 2026'!Y5+'Summary Sheet - May 2026'!Y5 + 'Summary Sheet - June 2026'!Y5 -> 0 | AA5: ='Summary Sheet - April 2026'!AA5 + 'Summary Sheet - May 2026'!AA5 + 'Summary Sheet - June 2026'!AA5 -> 2390099.8 | AC5: ='Summary Sheet - April 2026'!AC5 + 'Summary Sheet - May 2026'!AC5 + 'Summary Sheet - June 2026'!AC5 -> 0 | AE5: ='Summary Sheet - April 2026'!AE5 + 'Summary Sheet - May 2026'!AE5 + 'Summary Sheet - June 2026'!AE5 -> 3237788.5 | AG5: ='Summary Sheet - April 2026'!AG5 + 'Summary Sheet - May 2026'!AG5 + 'Summary Sheet - June 2026'!AG5 -> 0 | AI5: ='Summary Sheet - April 2026'!AI5 + 'Summary Sheet - May 2026'!AI5 + 'Summary Sheet - June 2026'!AI5 -> 0 | AK5: ='Summary Sheet - April 2026'!AK5 + 'Summary Sheet - May 2026'!AK5 + 'Summary Sheet - June 2026'!AK5 -> 0 | AM5: ='Summary Sheet - April 2026'!AM5 + 'Summary Sheet - May 2026'!AM5 + 'Summary Sheet - June 2026'!AM5 -> 0 | AO5: ='Summary Sheet - April 2026'!AO5 + 'Summary Sheet - May 2026'!AO5 + 'Summary Sheet - June 2026'!AO5 -> 0 | AQ5: ='Summary Sheet - April 2026'!AQ5 + 'Summary Sheet - May 2026'!AQ5 + 'Summary Sheet - June 2026'!AQ5 -> 1174787.5 | AS5: ='Summary Sheet - April 2026'!AS5 + 'Summary Sheet - May 2026'!AS5 + 'Summary Sheet - June 2026'!AS5 -> 0 | AU5: ='Summary Sheet - April 2026'!AU5 + 'Summary Sheet - May 2026'!AU5 + 'Summary Sheet - June 2026'!AU5 -> 0 | AW5: ='Summary Sheet - April 2026'!AW5 + 'Summary Sheet - May 2026'!AW5 + 'Summary Sheet - June 2026'!AW5 -> 0 | AY5: ='Summary Sheet - April 2026'!AY5 + 'Summary Sheet - May 2026'!AY5 + 'Summary Sheet - June 2026'!AY5 -> 0 | BA5: ='Summary Sheet - April 2026'!BA5 + 'Summary Sheet - May 2026'!BA5 + 'Summary Sheet - June 2026'!BA5 -> 0 | BC5: ='Summary Sheet - April 2026'!BC5 + 'Summary Sheet - May 2026'!BC5 + 'Summary Sheet - June 2026'!BC5 -> 0 | BE5: ='Summary Sheet - April 2026'!BE5 + 'Summary Sheet - May 2026'!BE5 + 'Summary Sheet - June 2026'!BE5 -> 0 | BG5: ='Summary Sheet - April 2026'!BG5 + 'Summary Sheet - May 2026'!BG5 + 'Summary Sheet - June 2026'!BG5 -> 0 | BI5: ='Summary Sheet - April 2026'!BI5 + 'Summary Sheet - May 2026'!BI5 + 'Summary Sheet - June 2026'!BI5 -> 0
B6: Liquor | C6: =G6+K6 -> 24020516 | D6: =C6/$C$10 -> 0.16140758 | E6: =I6+M6 -> 0 | F6: =E6/$E$10 -> #DIV/0! | G6: ='Summary Sheet - April 2026'!G6 + 'Summary Sheet - May 2026'!G6 + 'Summary Sheet - June 2026'!G6 -> 0 | I6: ='Summary Sheet - April 2026'!I6 + 'Summary Sheet - May 2026'!I6 + 'Summary Sheet - June 2026'!I6 -> 0 | K6: =O6+S6+W6+AA6+AE6+AI6+AM6+AQ6+AU6+AY6+BC6+BG6 -> 24020516 | M6: =Q6+U6+Y6+AC6+AG6+AK6+AO6 -> 0 | O6: ='Summary Sheet - April 2026'!O6 + 'Summary Sheet - May 2026'!O6 + 'Summary Sheet - June 2026'!O6 -> 9818016 | Q6: ='Summary Sheet - April 2026'!Q6 + 'Summary Sheet - May 2026'!Q6 + 'Summary Sheet - June 2026'!Q6 -> 0 | S6: ='Summary Sheet - April 2026'!S6 + 'Summary Sheet - May 2026'!S6 + 'Summary Sheet - June 2026'!S6 -> 0 | U6: ='Summary Sheet - April 2026'!U6 + 'Summary Sheet - May 2026'!U6 + 'Summary Sheet - June 2026'!U6 -> 0 | W6: ='Summary Sheet - April 2026'!W6+'Summary Sheet - May 2026'!W6 + 'Summary Sheet - June 2026'!W6 -> 1505040 | Y6: ='Summary Sheet - April 2026'!Y6+'Summary Sheet - May 2026'!Y6 + 'Summary Sheet - June 2026'!Y6 -> 0 | AA6: ='Summary Sheet - April 2026'!AA6 + 'Summary Sheet - May 2026'!AA6 + 'Summary Sheet - June 2026'!AA6 -> 0 | AC6: ='Summary Sheet - April 2026'!AC6 + 'Summary Sheet - May 2026'!AC6 + 'Summary Sheet - June 2026'!AC6 -> 0 | AE6: ='Summary Sheet - April 2026'!AE6 + 'Summary Sheet - May 2026'!AE6 + 'Summary Sheet - June 2026'!AE6 -> 4194442.5 | AG6: ='Summary Sheet - April 2026'!AG6 + 'Summary Sheet - May 2026'!AG6 + 'Summary Sheet - June 2026'!AG6 -> 0 | AI6: ='Summary Sheet - April 2026'!AI6 + 'Summary Sheet - May 2026'!AI6 + 'Summary Sheet - June 2026'!AI6 -> 0 | AK6: ='Summary Sheet - April 2026'!AK6 + 'Summary Sheet - May 2026'!AK6 + 'Summary Sheet - June 2026'!AK6 -> 0 | AM6: ='Summary Sheet - April 2026'!AM6 + 'Summary Sheet - May 2026'!AM6 + 'Summary Sheet - June 2026'!AM6 -> 0 | AO6: ='Summary Sheet - April 2026'!AO6 + 'Summary Sheet - May 2026'!AO6 + 'Summary Sheet - June 2026'!AO6 -> 0 | AQ6: ='Summary Sheet - April 2026'!AQ6 + 'Summary Sheet - May 2026'!AQ6 + 'Summary Sheet - June 2026'!AQ6 -> 8503017.5 | AS6: ='Summary Sheet - April 2026'!AS6 + 'Summary Sheet - May 2026'!AS6 + 'Summary Sheet - June 2026'!AS6 -> 0 | AU6: ='Summary Sheet - April 2026'!AU6 + 'Summary Sheet - May 2026'!AU6 + 'Summary Sheet - June 2026'!AU6 -> 0 | AW6: ='Summary Sheet - April 2026'!AW6 + 'Summary Sheet - May 2026'!AW6 + 'Summary Sheet - June 2026'!AW6 -> 0 | AY6: ='Summary Sheet - April 2026'!AY6 + 'Summary Sheet - May 2026'!AY6 + 'Summary Sheet - June 2026'!AY6 -> 0 | BA6: ='Summary Sheet - April 2026'!BA6 + 'Summary Sheet - May 2026'!BA6 + 'Summary Sheet - June 2026'!BA6 -> 0 | BC6: ='Summary Sheet - April 2026'!BC6 + 'Summary Sheet - May 2026'!BC6 + 'Summary Sheet - June 2026'!BC6 -> 0 | BE6: ='Summary Sheet - April 2026'!BE6 + 'Summary Sheet - May 2026'!BE6 + 'Summary Sheet - June 2026'!BE6 -> 0 | BG6: ='Summary Sheet - April 2026'!BG6 + 'Summary Sheet - May 2026'!BG6 + 'Summary Sheet - June 2026'!BG6 -> 0 | BI6: ='Summary Sheet - April 2026'!BI6 + 'Summary Sheet - May 2026'!BI6 + 'Summary Sheet - June 2026'!BI6 -> 0
B7: Food | C7: =G7+K7 -> 108260254 | D7: =C7/$C$10 -> 0.72746255 | E7: =I7+M7 -> 0 | F7: =E7/$E$10 -> #DIV/0! | G7: ='Summary Sheet - April 2026'!G7 + 'Summary Sheet - May 2026'!G7 + 'Summary Sheet - June 2026'!G7 -> 0 | I7: ='Summary Sheet - April 2026'!I7 + 'Summary Sheet - May 2026'!I7 + 'Summary Sheet - June 2026'!I7 -> 0 | K7: =O7+S7+W7+AA7+AE7+AI7+AM7+AQ7+AU7+AY7+BC7+BG7 -> 108260254 | M7: =Q7+U7+Y7+AC7+AG7+AK7+AO7 -> 0 | O7: ='Summary Sheet - April 2026'!O7 + 'Summary Sheet - May 2026'!O7 + 'Summary Sheet - June 2026'!O7 -> 26989559 | Q7: ='Summary Sheet - April 2026'!Q7 + 'Summary Sheet - May 2026'!Q7 + 'Summary Sheet - June 2026'!Q7 -> 0 | S7: ='Summary Sheet - April 2026'!S7 + 'Summary Sheet - May 2026'!S7 + 'Summary Sheet - June 2026'!S7 -> 1667248 | U7: ='Summary Sheet - April 2026'!U7 + 'Summary Sheet - May 2026'!U7 + 'Summary Sheet - June 2026'!U7 -> 0 | W7: ='Summary Sheet - April 2026'!W7+'Summary Sheet - May 2026'!W7 + 'Summary Sheet - June 2026'!W7 -> 20658266 | Y7: ='Summary Sheet - April 2026'!Y7+'Summary Sheet - May 2026'!Y7 + 'Summary Sheet - June 2026'!Y7 -> 0 | AA7: ='Summary Sheet - April 2026'!AA7 + 'Summary Sheet - May 2026'!AA7 + 'Summary Sheet - June 2026'!AA7 -> 16390588 | AC7: ='Summary Sheet - April 2026'!AC7 + 'Summary Sheet - May 2026'!AC7 + 'Summary Sheet - June 2026'!AC7 -> 0 | AE7: ='Summary Sheet - April 2026'!AE7 + 'Summary Sheet - May 2026'!AE7 + 'Summary Sheet - June 2026'!AE7 -> 25758068 | AG7: ='Summary Sheet - April 2026'!AG7 + 'Summary Sheet - May 2026'!AG7 + 'Summary Sheet - June 2026'!AG7 -> 0 | AI7: ='Summary Sheet - April 2026'!AI7 + 'Summary Sheet - May 2026'!AI7 + 'Summary Sheet - June 2026'!AI7 -> 0 | AK7: ='Summary Sheet - April 2026'!AK7 + 'Summary Sheet - May 2026'!AK7 + 'Summary Sheet - June 2026'!AK7 -> 0 | AM7: ='Summary Sheet - April 2026'!AM7 + 'Summary Sheet - May 2026'!AM7 + 'Summary Sheet - June 2026'!AM7 -> 970993.82 | AO7: ='Summary Sheet - April 2026'!AO7 + 'Summary Sheet - May 2026'!AO7 + 'Summary Sheet - June 2026'!AO7 -> 0 | AQ7: ='Summary Sheet - April 2026'!AQ7 + 'Summary Sheet - May 2026'!AQ7 + 'Summary Sheet - June 2026'!AQ7 -> 13386680 | AS7: ='Summary Sheet - April 2026'!AS7 + 'Summary Sheet - May 2026'!AS7 + 'Summary Sheet - June 2026'!AS7 -> 0 | AU7: ='Summary Sheet - April 2026'!AU7 + 'Summary Sheet - May 2026'!AU7 + 'Summary Sheet - June 2026'!AU7 -> 666826.99 | AW7: ='Summary Sheet - April 2026'!AW7 + 'Summary Sheet - May 2026'!AW7 + 'Summary Sheet - June 2026'!AW7 -> 0 | AY7: ='Summary Sheet - April 2026'!AY7 + 'Summary Sheet - May 2026'!AY7 + 'Summary Sheet - June 2026'!AY7 -> 228077.89 | BA7: ='Summary Sheet - April 2026'!BA7 + 'Summary Sheet - May 2026'!BA7 + 'Summary Sheet - June 2026'!BA7 -> 0 | BC7: ='Summary Sheet - April 2026'!BC7 + 'Summary Sheet - May 2026'!BC7 + 'Summary Sheet - June 2026'!BC7 -> 306961.08 | BE7: ='Summary Sheet - April 2026'!BE7 + 'Summary Sheet - May 2026'!BE7 + 'Summary Sheet - June 2026'!BE7 -> 0 | BG7: ='Summary Sheet - April 2026'!BG7 + 'Summary Sheet - May 2026'!BG7 + 'Summary Sheet - June 2026'!BG7 -> 1236985 | BI7: ='Summary Sheet - April 2026'!BI7 + 'Summary Sheet - May 2026'!BI7 + 'Summary Sheet - June 2026'!BI7 -> 0
B8: Service Charge | C8: =G8+K8 -> 4894605 | D8: =C8/$C$10 -> 0.03288965 | E8: =I8+M8 -> 0 | F8: =E8/$E$10 -> #DIV/0! | G8: ='Summary Sheet - April 2026'!G8 + 'Summary Sheet - May 2026'!G8 + 'Summary Sheet - June 2026'!G8 -> 0 | I8: ='Summary Sheet - April 2026'!I8 + 'Summary Sheet - May 2026'!I8 + 'Summary Sheet - June 2026'!I8 -> 0 | K8: =O8+S8+W8+AA8+AE8+AI8+AM8+AQ8+AU8+AY8+BC8+BG8 -> 4894605 | M8: =Q8+U8+Y8+AC8+AG8+AK8+AO8 -> 0 | O8: ='Summary Sheet - April 2026'!O8 + 'Summary Sheet - May 2026'!O8 + 'Summary Sheet - June 2026'!O8 -> 1719138 | Q8: ='Summary Sheet - April 2026'!Q8 + 'Summary Sheet - May 2026'!Q8 + 'Summary Sheet - June 2026'!Q8 -> 0 | S8: ='Summary Sheet - April 2026'!S8 + 'Summary Sheet - May 2026'!S8 + 'Summary Sheet - June 2026'!S8 -> 0 | U8: ='Summary Sheet - April 2026'!U8 + 'Summary Sheet - May 2026'!U8 + 'Summary Sheet - June 2026'!U8 -> 0 | W8: ='Summary Sheet - April 2026'!W8+'Summary Sheet - May 2026'!W8 + 'Summary Sheet - June 2026'!W8 -> 721626 | Y8: ='Summary Sheet - April 2026'!Y8+'Summary Sheet - May 2026'!Y8 + 'Summary Sheet - June 2026'!Y8 -> 0 | AA8: ='Summary Sheet - April 2026'!AA8 + 'Summary Sheet - May 2026'!AA8 + 'Summary Sheet - June 2026'!AA8 -> 356972.05 | AC8: ='Summary Sheet - April 2026'!AC8 + 'Summary Sheet - May 2026'!AC8 + 'Summary Sheet - June 2026'!AC8 -> 0 | AE8: ='Summary Sheet - April 2026'!AE8 + 'Summary Sheet - May 2026'!AE8 + 'Summary Sheet - June 2026'!AE8 -> 1028709 | AG8: ='Summary Sheet - April 2026'!AG8 + 'Summary Sheet - May 2026'!AG8 + 'Summary Sheet - June 2026'!AG8 -> 0 | AI8: ='Summary Sheet - April 2026'!AI8 + 'Summary Sheet - May 2026'!AI8 + 'Summary Sheet - June 2026'!AI8 -> 0 | AK8: ='Summary Sheet - April 2026'!AK8 + 'Summary Sheet - May 2026'!AK8 + 'Summary Sheet - June 2026'!AK8 -> 0 | AM8: ='Summary Sheet - April 2026'!AM8 + 'Summary Sheet - May 2026'!AM8 + 'Summary Sheet - June 2026'!AM8 -> 0 | AO8: ='Summary Sheet - April 2026'!AO8 + 'Summary Sheet - May 2026'!AO8 + 'Summary Sheet - June 2026'!AO8 -> 0 | AQ8: ='Summary Sheet - April 2026'!AQ8 + 'Summary Sheet - May 2026'!AQ8 + 'Summary Sheet - June 2026'!AQ8 -> 1068160 | AS8: ='Summary Sheet - April 2026'!AS8 + 'Summary Sheet - May 2026'!AS8 + 'Summary Sheet - June 2026'!AS8 -> 0 | AU8: ='Summary Sheet - April 2026'!AU8 + 'Summary Sheet - May 2026'!AU8 + 'Summary Sheet - June 2026'!AU8 -> 0 | AW8: ='Summary Sheet - April 2026'!AW8 + 'Summary Sheet - May 2026'!AW8 + 'Summary Sheet - June 2026'!AW8 -> 0 | AY8: ='Summary Sheet - April 2026'!AY8 + 'Summary Sheet - May 2026'!AY8 + 'Summary Sheet - June 2026'!AY8 -> 0 | BA8: ='Summary Sheet - April 2026'!BA8 + 'Summary Sheet - May 2026'!BA8 + 'Summary Sheet - June 2026'!BA8 -> 0 | BC8: ='Summary Sheet - April 2026'!BC8 + 'Summary Sheet - May 2026'!BC8 + 'Summary Sheet - June 2026'!BC8 -> 0 | BE8: ='Summary Sheet - April 2026'!BE8 + 'Summary Sheet - May 2026'!BE8 + 'Summary Sheet - June 2026'!BE8 -> 0 | BG8: ='Summary Sheet - April 2026'!BG8 + 'Summary Sheet - May 2026'!BG8 + 'Summary Sheet - June 2026'!BG8 -> 0 | BI8: ='Summary Sheet - April 2026'!BI8 + 'Summary Sheet - May 2026'!BI8 + 'Summary Sheet - June 2026'!BI8 -> 0
B9: Scrap Sales | C9: =G9+K9 -> 35231 | D9: =C9/$C$10 -> 0.00023673724 | E9: =I9+M9 -> 0 | F9: =E9/$E$10 -> #DIV/0! | G9: ='Summary Sheet - April 2026'!G9 + 'Summary Sheet - May 2026'!G9 + 'Summary Sheet - June 2026'!G9 -> 0 | I9: ='Summary Sheet - April 2026'!I9 + 'Summary Sheet - May 2026'!I9 + 'Summary Sheet - June 2026'!I9 -> 0 | K9: =O9+S9+W9+AA9+AE9+AI9+AM9+AQ9+AU9+AY9+BC9+BG9 -> 35231 | M9: =Q9+U9+Y9+AC9+AG9+AK9+AO9 -> 0 | O9: ='Summary Sheet - April 2026'!O9 + 'Summary Sheet - May 2026'!O9 + 'Summary Sheet - June 2026'!O9 -> 0 | Q9: ='Summary Sheet - April 2026'!Q9 + 'Summary Sheet - May 2026'!Q9 + 'Summary Sheet - June 2026'!Q9 -> 0 | S9: ='Summary Sheet - April 2026'!S9 + 'Summary Sheet - May 2026'!S9 + 'Summary Sheet - June 2026'!S9 -> 0 | U9: ='Summary Sheet - April 2026'!U9 + 'Summary Sheet - May 2026'!U9 + 'Summary Sheet - June 2026'!U9 -> 0 | W9: ='Summary Sheet - April 2026'!W9+'Summary Sheet - May 2026'!W9 + 'Summary Sheet - June 2026'!W9 -> 0 | Y9: ='Summary Sheet - April 2026'!Y9+'Summary Sheet - May 2026'!Y9 + 'Summary Sheet - June 2026'!Y9 -> 0 | AA9: ='Summary Sheet - April 2026'!AA9 + 'Summary Sheet - May 2026'!AA9 + 'Summary Sheet - June 2026'!AA9 -> 8000 | AC9: ='Summary Sheet - April 2026'!AC9 + 'Summary Sheet - May 2026'!AC9 + 'Summary Sheet - June 2026'!AC9 -> 0 | AE9: ='Summary Sheet - April 2026'!AE9 + 'Summary Sheet - May 2026'!AE9 + 'Summary Sheet - June 2026'!AE9 -> 13731 | AG9: ='Summary Sheet - April 2026'!AG9 + 'Summary Sheet - May 2026'!AG9 + 'Summary Sheet - June 2026'!AG9 -> 0 | AI9: ='Summary Sheet - April 2026'!AI9 + 'Summary Sheet - May 2026'!AI9 + 'Summary Sheet - June 2026'!AI9 -> 0 | AK9: ='Summary Sheet - April 2026'!AK9 + 'Summary Sheet - May 2026'!AK9 + 'Summary Sheet - June 2026'!AK9 -> 0 | AM9: ='Summary Sheet - April 2026'!AM9 + 'Summary Sheet - May 2026'!AM9 + 'Summary Sheet - June 2026'!AM9 -> 0 | AO9: ='Summary Sheet - April 2026'!AO9 + 'Summary Sheet - May 2026'!AO9 + 'Summary Sheet - June 2026'!AO9 -> 0 | AQ9: ='Summary Sheet - April 2026'!AQ9 + 'Summary Sheet - May 2026'!AQ9 + 'Summary Sheet - June 2026'!AQ9 -> 13500 | AS9: ='Summary Sheet - April 2026'!AS9 + 'Summary Sheet - May 2026'!AS9 + 'Summary Sheet - June 2026'!AS9 -> 0 | AU9: ='Summary Sheet - April 2026'!AU9 + 'Summary Sheet - May 2026'!AU9 + 'Summary Sheet - June 2026'!AU9 -> 0 | AW9: ='Summary Sheet - April 2026'!AW9 + 'Summary Sheet - May 2026'!AW9 + 'Summary Sheet - June 2026'!AW9 -> 0 | AY9: ='Summary Sheet - April 2026'!AY9 + 'Summary Sheet - May 2026'!AY9 + 'Summary Sheet - June 2026'!AY9 -> 0 | BA9: ='Summary Sheet - April 2026'!BA9 + 'Summary Sheet - May 2026'!BA9 + 'Summary Sheet - June 2026'!BA9 -> 0 | BC9: ='Summary Sheet - April 2026'!BC9 + 'Summary Sheet - May 2026'!BC9 + 'Summary Sheet - June 2026'!BC9 -> 0 | BE9: ='Summary Sheet - April 2026'!BE9 + 'Summary Sheet - May 2026'!BE9 + 'Summary Sheet - June 2026'!BE9 -> 0 | BG9: ='Summary Sheet - April 2026'!BG9 + 'Summary Sheet - May 2026'!BG9 + 'Summary Sheet - June 2026'!BG9 -> 0 | BI9: ='Summary Sheet - April 2026'!BI9 + 'Summary Sheet - May 2026'!BI9 + 'Summary Sheet - June 2026'!BI9 -> 0
B10: Total Sales Revenue | C10: =SUM(C5:C9) -> 1.4881901e+08 | D10: =C10/C10 -> 1 | E10: =SUM(E5:E9) -> 0 | F10: =E10/E10 -> #DIV/0! | G10: =SUM(G5:G9) -> 0 | I10: =SUM(I5:I8) -> 0 | K10: =SUM(K5:K9) -> 1.4881901e+08 | M10: =SUM(M5:M9) -> 0 | O10: =SUM(O5:O9) -> 40934293 | Q10: =SUM(Q5:Q9) -> 0 | S10: =SUM(S5:S9) -> 1667248 | U10: =SUM(U5:U9) -> 0 | W10: =SUM(W5:W9) -> 25283076 | Y10: =SUM(Y5:Y9) -> 0 | AA10: =SUM(AA5:AA9) -> 19145660 | AC10: =SUM(AC5:AC9) -> 0 | AE10: =SUM(AE5:AE9) -> 34232739 | AG10: =SUM(AG5:AG9) -> 0 | AI10: =SUM(AI5:AI9) -> 0 | AK10: =SUM(AK5:AK9) -> 0 | AM10: =SUM(AM5:AM9) -> 970993.82 | AO10: =SUM(AO5:AO9) -> 0 | AQ10: =SUM(AQ5:AQ9) -> 24146144 | AS10: =SUM(AS5:AS9) -> 0 | AU10: =SUM(AU5:AU9) -> 666826.99 | AW10: =SUM(AW5:AW9) -> 0 | AY10: =SUM(AY5:AY9) -> 228077.89 | BA10: =SUM(BA5:BA9) -> 0 | BC10: =SUM(BC5:BC8) -> 306961.08 | BE10: =SUM(BE5:BE8) -> 0 | BG10: =SUM(BG5:BG8) -> 1236985 | BI10: =SUM(BI5:BI8) -> 0
B12: COGS | C12: =G12+K12 -> 55832434 | D12: =C12/$C$10 -> 0.37517005 | E12: =I12+M12 -> 0 | G12: ='Summary Sheet - April 2026'!G12 + 'Summary Sheet - May 2026'!G12 + 'Summary Sheet - June 2026'!G12 -> 0 | I12: ='Summary Sheet - April 2026'!I12 + 'Summary Sheet - May 2026'!I12 + 'Summary Sheet - June 2026'!I12 -> 0 | K12: =O12+S12+W12+AA12+AE12+AI12+AM12+AQ12+AU12+AY12+BC12+BG12 -> 55832434 | M12: =Q12+U12+Y12+AC12+AG12+AK12+AO12 -> 0 | O12: ='Summary Sheet - April 2026'!O12 +'Summary Sheet - May 2026'!O12 + 'Summary Sheet - June 2026'!O12 -> 14259873 | Q12: ='Summary Sheet - April 2026'!Q12 +'Summary Sheet - May 2026'!Q12 + 'Summary Sheet - June 2026'!Q12 -> 0 | S12: ='Summary Sheet - April 2026'!S12 + 'Summary Sheet - May 2026'!S12 + 'Summary Sheet - June 2026'!S12 -> 573413.45 | U12: ='Summary Sheet - April 2026'!U12 + 'Summary Sheet - May 2026'!U12 + 'Summary Sheet - June 2026'!U12 -> 0 | W12: ='Summary Sheet - April 2026'!W12 + 'Summary Sheet - May 2026'!W12 -> 9869489.7 | Y12: ='Summary Sheet - April 2026'!Y12 + 'Summary Sheet - May 2026'!Y12 -> 0 | AA12: ='Summary Sheet - April 2026'!AA12 + 'Summary Sheet - May 2026'!AA12 + 'Summary Sheet - June 2026'!AA12 -> 6943290.1 | AC12: ='Summary Sheet - April 2026'!AC12 + 'Summary Sheet - May 2026'!AC12 + 'Summary Sheet - June 2026'!AC12 -> 0 | AE12: ='Summary Sheet - April 2026'!AE12 + 'Summary Sheet - May 2026'!AE12 + 'Summary Sheet - June 2026'!AE12 -> 11423138 | AG12: ='Summary Sheet - April 2026'!AG12 + 'Summary Sheet - May 2026'!AG12 + 'Summary Sheet - June 2026'!AG12 -> 0 | AI12: ='Summary Sheet - April 2026'!AI12 + 'Summary Sheet - May 2026'!AI12 + 'Summary Sheet - June 2026'!AI12 -> 0 | AK12: ='Summary Sheet - April 2026'!AK12 + 'Summary Sheet - May 2026'!AK12 + 'Summary Sheet - June 2026'!AK12 -> 0 | AM12: ='Summary Sheet - April 2026'!AM12 + 'Summary Sheet - May 2026'!AM12 + 'Summary Sheet - June 2026'!AM12 -> 1697483.5 | AO12: ='Summary Sheet - April 2026'!AO12 + 'Summary Sheet - May 2026'!AO12 + 'Summary Sheet - June 2026'!AO12 -> 0 | AQ12: ='Summary Sheet - April 2026'!AQ12 + 'Summary Sheet - May 2026'!AQ12 +'Summary Sheet - June 2026'!AQ12 -> 9435973 | AS12: ='Summary Sheet - April 2026'!AS12 + 'Summary Sheet - May 2026'!AS12 +'Summary Sheet - June 2026'!AS12 -> 0 | AU12: ='Summary Sheet - April 2026'!AU12 + 'Summary Sheet - May 2026'!AU12 + 'Summary Sheet - June 2026'!AU12 -> 438745.12 | AW12: ='Summary Sheet - April 2026'!AW12 + 'Summary Sheet - May 2026'!AW12 + 'Summary Sheet - June 2026'!AW12 -> 0 | AY12: ='Summary Sheet - April 2026'!AY12 + 'Summary Sheet - May 2026'!AY12 + 'Summary Sheet - June 2026'!AY12 -> 339203.01 | BA12: ='Summary Sheet - April 2026'!BA12 + 'Summary Sheet - May 2026'!BA12 + 'Summary Sheet - June 2026'!BA12 -> 0 | BC12: ='Summary Sheet - April 2026'!BC12 + 'Summary Sheet - May 2026'!BC12 + 'Summary Sheet - June 2026'!BC12 -> 495419.73 | BE12: ='Summary Sheet - April 2026'!BE12 + 'Summary Sheet - May 2026'!BE12 + 'Summary Sheet - June 2026'!BE12 -> 0 | BG12: ='Summary Sheet - April 2026'!BG12 + 'Summary Sheet - May 2026'!BG12 + 'Summary Sheet - June 2026'!BG12 -> 356406.24 | BI12: ='Summary Sheet - April 2026'!BI12 + 'Summary Sheet - May 2026'!BI12 + 'Summary Sheet - June 2026'!BI12 -> 0
B13: Packaging Cost | C13: =G13+K13 -> 1899950.2 | D13: =C13/$C$10 -> 0.012766852 | E13: =I13+M13 -> 0 | G13: ='Summary Sheet - April 2026'!G13 + 'Summary Sheet - May 2026'!G13 + 'Summary Sheet - June 2026'!G13 -> 0 | I13: ='Summary Sheet - April 2026'!I13 + 'Summary Sheet - May 2026'!I13 + 'Summary Sheet - June 2026'!I13 -> 0 | K13: =O13+S13+W13+AA13+AE13+AI13+AM13+AQ13+AU13+AY13+BC13+BG13 -> 1899950.2 | M13: =Q13+U13+Y13+AC13+AG13+AK13+AO13 -> 0 | O13: ='Summary Sheet - April 2026'!O13 +'Summary Sheet - May 2026'!O13 + 'Summary Sheet - June 2026'!O13 -> 106548 | Q13: ='Summary Sheet - April 2026'!Q13 +'Summary Sheet - May 2026'!Q13 + 'Summary Sheet - June 2026'!Q13 -> 0 | S13: ='Summary Sheet - April 2026'!S13 + 'Summary Sheet - May 2026'!S13 + 'Summary Sheet - June 2026'!S13 -> 73214 | U13: ='Summary Sheet - April 2026'!U13 + 'Summary Sheet - May 2026'!U13 + 'Summary Sheet - June 2026'!U13 -> 0 | W13: ='Summary Sheet - April 2026'!W13 + 'Summary Sheet - May 2026'!W13 -> 366401.4 | Y13: ='Summary Sheet - April 2026'!Y13 + 'Summary Sheet - May 2026'!Y13 -> 0 | AA13: ='Summary Sheet - April 2026'!AA13 + 'Summary Sheet - May 2026'!AA13 + 'Summary Sheet - June 2026'!AA13 -> 442124 | AC13: ='Summary Sheet - April 2026'!AC13 + 'Summary Sheet - May 2026'!AC13 + 'Summary Sheet - June 2026'!AC13 -> 0 | AE13: ='Summary Sheet - April 2026'!AE13 + 'Summary Sheet - May 2026'!AE13 + 'Summary Sheet - June 2026'!AE13 -> 512245.02 | AG13: ='Summary Sheet - April 2026'!AG13 + 'Summary Sheet - May 2026'!AG13 + 'Summary Sheet - June 2026'!AG13 -> 0 | AI13: ='Summary Sheet - April 2026'!AI13 + 'Summary Sheet - May 2026'!AI13 + 'Summary Sheet - June 2026'!AI13 -> 1030 | AK13: ='Summary Sheet - April 2026'!AK13 + 'Summary Sheet - May 2026'!AK13 + 'Summary Sheet - June 2026'!AK13 -> 0 | AM13: ='Summary Sheet - April 2026'!AM13 + 'Summary Sheet - May 2026'!AM13 + 'Summary Sheet - June 2026'!AM13 -> 203076.5 | AO13: ='Summary Sheet - April 2026'!AO13 + 'Summary Sheet - May 2026'!AO13 + 'Summary Sheet - June 2026'!AO13 -> 0 | AQ13: ='Summary Sheet - April 2026'!AQ13 + 'Summary Sheet - May 2026'!AQ13 +'Summary Sheet - June 2026'!AQ13 -> 85375.3 | AS13: ='Summary Sheet - April 2026'!AS13 + 'Summary Sheet - May 2026'!AS13 +'Summary Sheet - June 2026'!AS13 -> 0 | AU13: ='Summary Sheet - April 2026'!AU13 + 'Summary Sheet - May 2026'!AU13 + 'Summary Sheet - June 2026'!AU13 -> 8383 | AW13: ='Summary Sheet - April 2026'!AW13 + 'Summary Sheet - May 2026'!AW13 + 'Summary Sheet - June 2026'!AW13 -> 0 | AY13: ='Summary Sheet - April 2026'!AY13 + 'Summary Sheet - May 2026'!AY13 + 'Summary Sheet - June 2026'!AY13 -> 9422 | BA13: ='Summary Sheet - April 2026'!BA13 + 'Summary Sheet - May 2026'!BA13 + 'Summary Sheet - June 2026'!BA13 -> 0 | BC13: ='Summary Sheet - April 2026'!BC13 + 'Summary Sheet - May 2026'!BC13 + 'Summary Sheet - June 2026'!BC13 -> 5647 | BE13: ='Summary Sheet - April 2026'!BE13 + 'Summary Sheet - May 2026'!BE13 + 'Summary Sheet - June 2026'!BE13 -> 0 | BG13: ='Summary Sheet - April 2026'!BG13 + 'Summary Sheet - May 2026'!BG13 + 'Summary Sheet - June 2026'!BG13 -> 86484 | BI13: ='Summary Sheet - April 2026'!BI13 + 'Summary Sheet - May 2026'!BI13 + 'Summary Sheet - June 2026'!BI13 -> 0
B14: Total COGS & Packaging | C14: =SUM(C12:C13) -> 57732384 | D14: =C14/C10 -> 0.3879369 | E14: =E12+E13 -> 0 | G14: =G12+G13 -> 0 | I14: =I12+I13 -> 0 | K14: =SUM(K12:K13) -> 57732384 | M14: =Q14+U14+Y14+AC14+AG14+AK14+AO14 -> 0 | O14: =O12+O13 -> 14366421 | Q14: =Q12+Q13 -> 0 | S14: =S12+S13 -> 646627.45 | U14: =U12+U13 -> 0 | W14: =W12+W13 -> 10235891 | Y14: =Y12+Y13 -> 0 | AA14: =AA12+AA13 -> 7385414.1 | AC14: =AC12+AC13 -> 0 | AE14: =AE12+AE13 -> 11935383 | AG14: =AG12+AG13 -> 0 | AI14: =AI12+AI13 -> 1030 | AK14: =AK12+AK13 -> 0 | AM14: =AM12+AM13 -> 1900560 | AO14: =AO12+AO13 -> 0 | AQ14: =AQ12+AQ13 -> 9521348.3 | AS14: =AS12+AS13 -> 0 | AU14: =AU12+AU13 -> 447128.12 | AW14: =AW12+AW13 -> 0 | AY14: =AY12+AY13 -> 348625.01 | BA14: =BA12+BA13 -> 0 | BC14: =BC12+BC13 -> 501066.73 | BE14: =BE12+BE13 -> 0 | BG14: =BG12+BG13 -> 442890.24 | BI14: =BI12+BI13 -> 0
B15: DEQ
B16: Gross Margin | C16: =C10-C14 -> 91086622 | D16: =C16/C10 -> 0.6120631 | E16: =E10-E14 -> 0 | G16: =G10-G14 -> 0 | I16: =I10-I14 -> 0 | K16: =K10-K14 -> 91086622 | M16: =M10-M14 -> 0 | O16: =O10-O14-O15 -> 26567872 | Q16: =Q10-Q14-Q15 -> 0 | S16: =S10-S14-S15 -> 1020620.5 | U16: =U10-U14-U15 -> 0 | W16: =W10-W14-W15 -> 15047185 | Y16: =Y10-Y14-Y15 -> 0 | AA16: =AA10-AA14-AA15 -> 11760246 | AC16: =AC10-AC14-AC15 -> 0 | AE16: =AE10-AE14-AE15 -> 22297357 | AG16: =AG10-AG14-AG15 -> 0 | AI16: =AI10-AI14-AI15 -> -1030 | AK16: ='Summary Sheet - April 2026'!AK17 -> 0 | AM16: =AM10-AM14-AM15 -> -929566.16 | AO16: ='Summary Sheet - April 2026'!AO17 -> 0 | AQ16: =AQ10-AQ14-AQ15 -> 14624796 | AS16: =AS10-AS14-AS15 -> 0 | AU16: =AU10-AU14-AU15 -> 219698.87 | AW16: =AW10-AW14 -> 0 | AY16: =AY10-AY14-AY15 -> -120547.12 | BA16: =BA10-BA14 -> 0 | BC16: =BC10-BC14-BC15 -> -194105.65 | BE16: =BE10-BE14 -> 0 | BG16: =BG10-BG14-BG15 -> 794094.76 | BI16: =BI10-BI14 -> 0
B18: Other Direct Expenses | C18: =G18+K18 -> 3971287.5 | D18: =C18/$C$10 -> 0.026685352 | E18: =I18+M18 -> 0 | G18: ='Summary Sheet - April 2026'!G19 + 'Summary Sheet - May 2026'!G19 + 'Summary Sheet - June 2026'!G19 -> 128002.51 | I18: ='Summary Sheet - April 2026'!I19 + 'Summary Sheet - May 2026'!I19 + 'Summary Sheet - June 2026'!I19 -> 0 | K18: =O18+S18+W18+AA18+AE18+AI18+AM18+AQ18+AU18+AY18+BC18+BG18 -> 3843285 | M18: =Q18+U18+Y18+AC18+AG18+AK18+AO18 -> 0 | O18: ='Summary Sheet - April 2026'!O19 + 'Summary Sheet - May 2026'!O19 + 'Summary Sheet - June 2026'!O19 -> 949580.56 | Q18: ='Summary Sheet - April 2026'!Q19 + 'Summary Sheet - May 2026'!Q19 + 'Summary Sheet - June 2026'!Q19 -> 0 | S18: ='Summary Sheet - April 2026'!S19 +'Summary Sheet - May 2026'!S19 + 'Summary Sheet - June 2026'!S19 -> 91280.29 | U18: ='Summary Sheet - April 2026'!U19 +'Summary Sheet - May 2026'!U19 + 'Summary Sheet - June 2026'!U19 -> 0 | W18: ='Summary Sheet - April 2026'!W19 + 'Summary Sheet - May 2026'!W19 + 'Summary Sheet - June 2026'!W19 -> 750009.87 | Y18: ='Summary Sheet - April 2026'!Y19 + 'Summary Sheet - May 2026'!Y19 + 'Summary Sheet - June 2026'!Y19 -> 0 | AA18: ='Summary Sheet - April 2026'!AA19 + 'Summary Sheet - May 2026'!AA19 + 'Summary Sheet - June 2026'!AA19 -> 483204.82 | AC18: ='Summary Sheet - April 2026'!AC19 + 'Summary Sheet - May 2026'!AC19 + 'Summary Sheet - June 2026'!AC19 -> 0 | AE18: ='Summary Sheet - April 2026'!AE19 + 'Summary Sheet - May 2026'!AE19 + 'Summary Sheet - June 2026'!AE19 -> 989178.45 | AG18: ='Summary Sheet - April 2026'!AG19 + 'Summary Sheet - May 2026'!AG19 + 'Summary Sheet - June 2026'!AG19 -> 0 | AI18: ='Summary Sheet - April 2026'!AI19 + 'Summary Sheet - May 2026'!AI19 + 'Summary Sheet - June 2026'!AI19 -> 35514 | AK18: ='Summary Sheet - April 2026'!AK19 + 'Summary Sheet - May 2026'!AK19 + 'Summary Sheet - June 2026'!AK19 -> 0 | AM18: ='Summary Sheet - April 2026'!AM19 + 'Summary Sheet - May 2026'!AM19 + 'Summary Sheet - June 2026'!AM19 -> 71198.86 | AO18: ='Summary Sheet - April 2026'!AO19 + 'Summary Sheet - May 2026'!AO19 + 'Summary Sheet - June 2026'!AO19 -> 0 | AQ18: ='Summary Sheet - April 2026'!AQ19 + 'Summary Sheet - May 2026'!AQ19 + 'Summary Sheet - June 2026'!AQ19 -> 467605.13 | AS18: ='Summary Sheet - April 2026'!AS19 + 'Summary Sheet - May 2026'!AS19 + 'Summary Sheet - June 2026'!AS19 -> 0 | AU18: ='Summary Sheet - April 2026'!AU19 + 'Summary Sheet - May 2026'!AU19 + 'Summary Sheet - June 2026'!AU19 -> 0 | AW18: ='Summary Sheet - April 2026'!AW19 + 'Summary Sheet - May 2026'!AW19 + 'Summary Sheet - June 2026'!AW19 -> 0 | AY18: ='Summary Sheet - April 2026'!AY19 + 'Summary Sheet - May 2026'!AY19 + 'Summary Sheet - June 2026'!AY19 -> 0 | BA18: ='Summary Sheet - April 2026'!BA19 + 'Summary Sheet - May 2026'!BA19 + 'Summary Sheet - June 2026'!BA19 -> 0 | BC18: ='Summary Sheet - April 2026'!BC19 + 'Summary Sheet - May 2026'!BC19 + 'Summary Sheet - June 2026'!BC19 -> 0 | BE18: ='Summary Sheet - April 2026'!BE19 + 'Summary Sheet - May 2026'!BE19 + 'Summary Sheet - June 2026'!BE19 -> 0 | BG18: ='Summary Sheet - April 2026'!BG19 + 'Summary Sheet - May 2026'!BG19 + 'Summary Sheet - June 2026'!BG19 -> 5713 | BI18: ='Summary Sheet - April 2026'!BI19 + 'Summary Sheet - May 2026'!BI19 + 'Summary Sheet - June 2026'!BI19 -> 0
B19: Marketing Expenses | C19: =G19+K19 -> 1618158.4 | D19: =C19/$C$10 -> 0.010873332 | E19: =I19+M19 -> 53100 | G19: ='Summary Sheet - April 2026'!G20 + 'Summary Sheet - May 2026'!G20 + 'Summary Sheet - June 2026'!G20 -> 106200 | I19: ='Summary Sheet - April 2026'!I20 + 'Summary Sheet - May 2026'!I20 + 'Summary Sheet - June 2026'!I20 -> 53100 | K19: =O19+S19+W19+AA19+AE19+AI19+AM19+AQ19+AU19+AY19+BC19+BG19 -> 1511958.4 | M19: =Q19+U19+Y19+AC19+AG19+AK19+AO19 -> 0 | O19: ='Summary Sheet - April 2026'!O20 + 'Summary Sheet - May 2026'!O20 + 'Summary Sheet - June 2026'!O20 -> 72049 | Q19: ='Summary Sheet - April 2026'!Q20 + 'Summary Sheet - May 2026'!Q20 + 'Summary Sheet - June 2026'!Q20 -> 0 | S19: ='Summary Sheet - April 2026'!S20 +'Summary Sheet - May 2026'!S20 + 'Summary Sheet - June 2026'!S20 -> 179253.69 | U19: ='Summary Sheet - April 2026'!U20 +'Summary Sheet - May 2026'!U20 + 'Summary Sheet - June 2026'!U20 -> 0 | W19: ='Summary Sheet - April 2026'!W20 + 'Summary Sheet - May 2026'!W20 + 'Summary Sheet - June 2026'!W20 -> 406787.44 | Y19: ='Summary Sheet - April 2026'!Y20 + 'Summary Sheet - May 2026'!Y20 + 'Summary Sheet - June 2026'!Y20 -> 0 | AA19: ='Summary Sheet - April 2026'!AA20 + 'Summary Sheet - May 2026'!AA20 + 'Summary Sheet - June 2026'!AA20 -> 215071.5 | AC19: ='Summary Sheet - April 2026'!AC20 + 'Summary Sheet - May 2026'!AC20 + 'Summary Sheet - June 2026'!AC20 -> 0 | AE19: ='Summary Sheet - April 2026'!AE20 + 'Summary Sheet - May 2026'!AE20 + 'Summary Sheet - June 2026'!AE20 -> 187484 | AG19: ='Summary Sheet - April 2026'!AG20 + 'Summary Sheet - May 2026'!AG20 + 'Summary Sheet - June 2026'!AG20 -> 0 | AI19: ='Summary Sheet - April 2026'!AI20 + 'Summary Sheet - May 2026'!AI20 + 'Summary Sheet - June 2026'!AI20 -> 80000 | AK19: ='Summary Sheet - April 2026'!AK20 + 'Summary Sheet - May 2026'!AK20 + 'Summary Sheet - June 2026'!AK20 -> 0 | AM19: ='Summary Sheet - April 2026'!AM20 + 'Summary Sheet - May 2026'!AM20 + 'Summary Sheet - June 2026'!AM20 -> 103790.78 | AO19: ='Summary Sheet - April 2026'!AO20 + 'Summary Sheet - May 2026'!AO20 + 'Summary Sheet - June 2026'!AO20 -> 0 | AQ19: ='Summary Sheet - April 2026'!AQ20 + 'Summary Sheet - May 2026'!AQ20 + 'Summary Sheet - June 2026'!AQ20 -> 52063.98 | AS19: ='Summary Sheet - April 2026'!AS20 + 'Summary Sheet - May 2026'!AS20 + 'Summary Sheet - June 2026'!AS20 -> 35000 | AU19: ='Summary Sheet - April 2026'!AU20 + 'Summary Sheet - May 2026'!AU20 + 'Summary Sheet - June 2026'!AU20 -> 113959.52 | AW19: ='Summary Sheet - April 2026'!AW20 + 'Summary Sheet - May 2026'!AW20 + 'Summary Sheet - June 2026'!AW20 -> 0 | AY19: ='Summary Sheet - April 2026'!AY20 + 'Summary Sheet - May 2026'!AY20 + 'Summary Sheet - June 2026'!AY20 -> 43183.46 | BA19: ='Summary Sheet - April 2026'!BA20 + 'Summary Sheet - May 2026'!BA20 + 'Summary Sheet - June 2026'!BA20 -> 0 | BC19: ='Summary Sheet - April 2026'!BC20 + 'Summary Sheet - May 2026'!BC20 + 'Summary Sheet - June 2026'!BC20 -> 43467.03 | BE19: ='Summary Sheet - April 2026'!BE20 + 'Summary Sheet - May 2026'!BE20 + 'Summary Sheet - June 2026'!BE20 -> 0 | BG19: ='Summary Sheet - April 2026'!BG20 + 'Summary Sheet - May 2026'!BG20 + 'Summary Sheet - June 2026'!BG20 -> 14848 | BI19: ='Summary Sheet - April 2026'!BI20 + 'Summary Sheet - May 2026'!BI20 + 'Summary Sheet - June 2026'!BI20 -> 0
B20: Sales Commission | C20: =G20+K20 -> 4609465.1 | D20: =C20/$C$10 -> 0.030973632 | E20: =I20+M20 -> #REF! | G20: ='Summary Sheet - April 2026'!G21 + 'Summary Sheet - May 2026'!G21 + 'Summary Sheet - June 2026'!G21 -> 0 | I20: ='Summary Sheet - April 2026'!I21 + 'Summary Sheet - May 2026'!I21 + 'Summary Sheet - June 2026'!I21 -> 0 | K20: =O20+S20+W20+AA20+AE20+AI20+AM20+AQ20+AU20+AY20+BC20+BG20 -> 4609465.1 | M20: =Q20+U20+Y20+AC20+AG20+AK20+AO20 -> #REF! | O20: ='Summary Sheet - April 2026'!O21 + 'Summary Sheet - May 2026'!O21 + 'Summary Sheet - June 2026'!O21 -> 173480.51 | Q20: ='Summary Sheet - April 2026'!Q21 + 'Summary Sheet - May 2026'!Q21 + 'Summary Sheet - June 2026'!Q21 -> 0 | S20: ='Summary Sheet - April 2026'!S21 +'Summary Sheet - May 2026'!S21 + 'Summary Sheet - June 2026'!S21 -> 228974.03 | U20: ='Summary Sheet - April 2026'!U21 +'Summary Sheet - May 2026'!U21 + 'Summary Sheet - June 2026'!U21 -> 0 | W20: ='Summary Sheet - April 2026'!W21 + 'Summary Sheet - May 2026'!W21 + 'Summary Sheet - June 2026'!W21 -> 960909.79 | Y20: ='Summary Sheet - April 2026'!Y21 + 'Summary Sheet - May 2026'!Y21 + 'Summary Sheet - June 2026'!Y21 -> #REF! | AA20: ='Summary Sheet - April 2026'!AA21 + 'Summary Sheet - May 2026'!AA21 + 'Summary Sheet - June 2026'!AA21 -> 1396555.2 | AC20: ='Summary Sheet - April 2026'!AC21 + 'Summary Sheet - May 2026'!AC21 + 'Summary Sheet - June 2026'!AC21 -> 0 | AE20: ='Summary Sheet - April 2026'!AE21 + 'Summary Sheet - May 2026'!AE21 + 'Summary Sheet - June 2026'!AE21 -> 1307943 | AG20: ='Summary Sheet - April 2026'!AG21 + 'Summary Sheet - May 2026'!AG21 + 'Summary Sheet - June 2026'!AG21 -> 0 | AI20: ='Summary Sheet - April 2026'!AI21 + 'Summary Sheet - May 2026'!AI21 + 'Summary Sheet - June 2026'!AI21 -> 0 | AK20: ='Summary Sheet - April 2026'!AK21 + 'Summary Sheet - May 2026'!AK21 + 'Summary Sheet - June 2026'!AK21 -> 0 | AM20: ='Summary Sheet - April 2026'!AM21 + 'Summary Sheet - May 2026'!AM21 + 'Summary Sheet - June 2026'!AM21 -> 78387.37 | AO20: ='Summary Sheet - April 2026'!AO21 + 'Summary Sheet - May 2026'!AO21 + 'Summary Sheet - June 2026'!AO21 -> 0 | AQ20: ='Summary Sheet - April 2026'!AQ21 + 'Summary Sheet - May 2026'!AQ21 + 'Summary Sheet - June 2026'!AQ21 -> 0 | AS20: ='Summary Sheet - April 2026'!AS21 + 'Summary Sheet - May 2026'!AS21 + 'Summary Sheet - June 2026'!AS21 -> 0 | AU20: ='Summary Sheet - April 2026'!AU21 + 'Summary Sheet - May 2026'!AU21 + 'Summary Sheet - June 2026'!AU21 -> 162351.79 | AW20: ='Summary Sheet - April 2026'!AW21 + 'Summary Sheet - May 2026'!AW21 + 'Summary Sheet - June 2026'!AW21 -> 0 | AY20: ='Summary Sheet - April 2026'!AY21 + 'Summary Sheet - May 2026'!AY21 + 'Summary Sheet - June 2026'!AY21 -> 69035.85 | BA20: ='Summary Sheet - April 2026'!BA21 + 'Summary Sheet - May 2026'!BA21 + 'Summary Sheet - June 2026'!BA21 -> 0 | BC20: ='Summary Sheet - April 2026'!BC21 + 'Summary Sheet - May 2026'!BC21 + 'Summary Sheet - June 2026'!BC21 -> 85672.94 | BE20: ='Summary Sheet - April 2026'!BE21 + 'Summary Sheet - May 2026'!BE21 + 'Summary Sheet - June 2026'!BE21 -> 0 | BG20: ='Summary Sheet - April 2026'!BG21 + 'Summary Sheet - May 2026'!BG21 + 'Summary Sheet - June 2026'!BG21 -> 146154.56 | BI20: ='Summary Sheet - April 2026'!BI21 + 'Summary Sheet - May 2026'!BI21 + 'Summary Sheet - June 2026'!BI21 -> 0
B21: Rental & Utility Expenses | C21: =G21+K21 -> 16374761 | D21: =C21/$C$10 -> 0.11003138 | E21: =I21+M21 -> 3057546 | G21: ='Summary Sheet - April 2026'!G22 + 'Summary Sheet - May 2026'!G22 + 'Summary Sheet - June 2026'!G22 -> 1627794.7 | I21: ='Summary Sheet - April 2026'!I22 + 'Summary Sheet - May 2026'!I22 + 'Summary Sheet - June 2026'!I22 -> 0 | K21: =O21+S21+W21+AA21+AE21+AI21+AM21+AQ21+AU21+AY21+BC21+BG21 -> 14746966 | M21: =Q21+U21+Y21+AC21+AG21+AK21+AO21 -> 3057546 | O21: ='Summary Sheet - April 2026'!O22 + 'Summary Sheet - May 2026'!O22 + 'Summary Sheet - June 2026'!O22 -> 3665933.8 | Q21: ='Summary Sheet - April 2026'!Q22 + 'Summary Sheet - May 2026'!Q22 + 'Summary Sheet - June 2026'!Q22 -> 1419717 | S21: ='Summary Sheet - April 2026'!S22 +'Summary Sheet - May 2026'!S22 + 'Summary Sheet - June 2026'!S22 -> 213175 | U21: ='Summary Sheet - April 2026'!U22 +'Summary Sheet - May 2026'!U22 + 'Summary Sheet - June 2026'!U22 -> 76212 | W21: ='Summary Sheet - April 2026'!W22 + 'Summary Sheet - May 2026'!W22 + 'Summary Sheet - June 2026'!W22 -> 3480038.3 | Y21: ='Summary Sheet - April 2026'!Y22 + 'Summary Sheet - May 2026'!Y22 + 'Summary Sheet - June 2026'!Y22 -> 1314963 | AA21: ='Summary Sheet - April 2026'!AA22 + 'Summary Sheet - May 2026'!AA22 + 'Summary Sheet - June 2026'!AA22 -> 2210248 | AC21: ='Summary Sheet - April 2026'!AC22 + 'Summary Sheet - May 2026'!AC22 + 'Summary Sheet - June 2026'!AC22 -> 0 | AE21: ='Summary Sheet - April 2026'!AE22 + 'Summary Sheet - May 2026'!AE22 + 'Summary Sheet - June 2026'!AE22 -> 2351243 | AG21: ='Summary Sheet - April 2026'!AG22 + 'Summary Sheet - May 2026'!AG22 + 'Summary Sheet - June 2026'!AG22 -> 0 | AI21: ='Summary Sheet - April 2026'!AI22 + 'Summary Sheet - May 2026'!AI22 + 'Summary Sheet - June 2026'!AI22 -> 370741 | AK21: ='Summary Sheet - April 2026'!AK22 + 'Summary Sheet - May 2026'!AK22 + 'Summary Sheet - June 2026'!AK22 -> 90931 | AM21: ='Summary Sheet - April 2026'!AM22 + 'Summary Sheet - May 2026'!AM22 + 'Summary Sheet - June 2026'!AM22 -> 489829 | AO21: ='Summary Sheet - April 2026'!AO22 + 'Summary Sheet - May 2026'!AO22 + 'Summary Sheet - June 2026'!AO22 -> 155723 | AQ21: ='Summary Sheet - April 2026'!AQ22 + 'Summary Sheet - May 2026'!AQ22 + 'Summary Sheet - June 2026'!AQ22 -> 1965758 | AS21: ='Summary Sheet - April 2026'!AS22 + 'Summary Sheet - May 2026'!AS22 + 'Summary Sheet - June 2026'!AS22 -> 2419 | AU21: ='Summary Sheet - April 2026'!AU22 + 'Summary Sheet - May 2026'!AU22 + 'Summary Sheet - June 2026'!AU22 -> 0 | AW21: ='Summary Sheet - April 2026'!AW22 + 'Summary Sheet - May 2026'!AW22 + 'Summary Sheet - June 2026'!AW22 -> 0 | AY21: ='Summary Sheet - April 2026'!AY22 + 'Summary Sheet - May 2026'!AY22 + 'Summary Sheet - June 2026'!AY22 -> 0 | BA21: ='Summary Sheet - April 2026'!BA22 + 'Summary Sheet - May 2026'!BA22 + 'Summary Sheet - June 2026'!BA22 -> 0 | BC21: ='Summary Sheet - April 2026'!BC22 + 'Summary Sheet - May 2026'!BC22 + 'Summary Sheet - June 2026'!BC22 -> 0 | BE21: ='Summary Sheet - April 2026'!BE22 + 'Summary Sheet - May 2026'!BE22 + 'Summary Sheet - June 2026'!BE22 -> 0 | BG21: ='Summary Sheet - April 2026'!BG22 + 'Summary Sheet - May 2026'!BG22 + 'Summary Sheet - June 2026'!BG22 -> 0 | BI21: ='Summary Sheet - April 2026'!BI22 + 'Summary Sheet - May 2026'!BI22 + 'Summary Sheet - June 2026'!BI22 -> 0
B22: Salary & Staff Expenses | C22: =G22+K22 -> 48806327 | D22: =C22/$C$10 -> 0.32795762 | E22: =I22+M22 -> 758150 | G22: ='Summary Sheet - April 2026'!G23 + 'Summary Sheet - May 2026'!G23 + 'Summary Sheet - June 2026'!G23 -> 7747821.5 | I22: ='Summary Sheet - April 2026'!I23 + 'Summary Sheet - May 2026'!I23 + 'Summary Sheet - June 2026'!I23 -> 0 | K22: =O22+S22+W22+AA22+AE22+AI22+AM22+AQ22+AU22+AY22+BC22+BG22 -> 41058506 | M22: =Q22+U22+Y22+AC22+AG22+AK22+AO22 -> 758150 | O22: ='Summary Sheet - April 2026'!O23 + 'Summary Sheet - May 2026'!O23 + 'Summary Sheet - June 2026'!O23 -> 10602073 | Q22: ='Summary Sheet - April 2026'!Q23 + 'Summary Sheet - May 2026'!Q23 + 'Summary Sheet - June 2026'!Q23 -> 663750 | S22: ='Summary Sheet - April 2026'!S23 +'Summary Sheet - May 2026'!S23 + 'Summary Sheet - June 2026'!S23 -> 679710.73 | U22: ='Summary Sheet - April 2026'!U23 +'Summary Sheet - May 2026'!U23 + 'Summary Sheet - June 2026'!U23 -> 0 | W22: ='Summary Sheet - April 2026'!W23 + 'Summary Sheet - May 2026'!W23 + 'Summary Sheet - June 2026'!W23 -> 6422135 | Y22: ='Summary Sheet - April 2026'!Y23 + 'Summary Sheet - May 2026'!Y23 + 'Summary Sheet - June 2026'!Y23 -> 0 | AA22: ='Summary Sheet - April 2026'!AA23 + 'Summary Sheet - May 2026'!AA23 + 'Summary Sheet - June 2026'!AA23 -> 3537149.7 | AC22: ='Summary Sheet - April 2026'!AC23 + 'Summary Sheet - May 2026'!AC23 + 'Summary Sheet - June 2026'!AC23 -> 0 | AE22: ='Summary Sheet - April 2026'!AE23 + 'Summary Sheet - May 2026'!AE23 + 'Summary Sheet - June 2026'!AE23 -> 7545416 | AG22: ='Summary Sheet - April 2026'!AG23 + 'Summary Sheet - May 2026'!AG23 + 'Summary Sheet - June 2026'!AG23 -> 0 | AI22: ='Summary Sheet - April 2026'!AI23 + 'Summary Sheet - May 2026'!AI23 + 'Summary Sheet - June 2026'!AI23 -> 460392 | AK22: ='Summary Sheet - April 2026'!AK23 + 'Summary Sheet - May 2026'!AK23 + 'Summary Sheet - June 2026'!AK23 -> 0 | AM22: ='Summary Sheet - April 2026'!AM23 + 'Summary Sheet - May 2026'!AM23 + 'Summary Sheet - June 2026'!AM23 -> 3028630.6 | AO22: ='Summary Sheet - April 2026'!AO23 + 'Summary Sheet - May 2026'!AO23 + 'Summary Sheet - June 2026'!AO23 -> 94400 | AQ22: ='Summary Sheet - April 2026'!AQ23 + 'Summary Sheet - May 2026'!AQ23 + 'Summary Sheet - June 2026'!AQ23 -> 7579231.5 | AS22: ='Summary Sheet - April 2026'!AS23 + 'Summary Sheet - May 2026'!AS23 + 'Summary Sheet - June 2026'!AS23 -> 0 | AU22: ='Summary Sheet - April 2026'!AU23 + 'Summary Sheet - May 2026'!AU23 + 'Summary Sheet - June 2026'!AU23 -> 0 | AW22: ='Summary Sheet - April 2026'!AW23 + 'Summary Sheet - May 2026'!AW23 + 'Summary Sheet - June 2026'!AW23 -> 0 | AY22: ='Summary Sheet - April 2026'!AY23 + 'Summary Sheet - May 2026'!AY23 + 'Summary Sheet - June 2026'!AY23 -> 0 | BA22: ='Summary Sheet - April 2026'!BA23 + 'Summary Sheet - May 2026'!BA23 + 'Summary Sheet - June 2026'!BA23 -> 0 | BC22: ='Summary Sheet - April 2026'!BC23 + 'Summary Sheet - May 2026'!BC23 + 'Summary Sheet - June 2026'!BC23 -> 0 | BE22: ='Summary Sheet - April 2026'!BE23 + 'Summary Sheet - May 2026'!BE23 + 'Summary Sheet - June 2026'!BE23 -> 0 | BG22: ='Summary Sheet - April 2026'!BG23 + 'Summary Sheet - May 2026'!BG23 + 'Summary Sheet - June 2026'!BG23 -> 1203766.5 | BI22: ='Summary Sheet - April 2026'!BI23 + 'Summary Sheet - May 2026'!BI23 + 'Summary Sheet - June 2026'!BI23 -> 0
B23: Bank and Finance Charges | C23: =G23+K23 -> 1958841 | D23: =C23/$C$10 -> 0.013162573 | E23: =I23+M23 -> 0 | G23: ='Summary Sheet - April 2026'!G24 + 'Summary Sheet - May 2026'!G24 + 'Summary Sheet - June 2026'!G24 -> 813941 | I23: ='Summary Sheet - April 2026'!I24 + 'Summary Sheet - May 2026'!I24 + 'Summary Sheet - June 2026'!I24 -> 0 | K23: =O23+S23+W23+AA23+AE23+AI23+AM23+AQ23+AU23+AY23+BC23+BG23 -> 1144900 | M23: =Q23+U23+Y23+AC23+AG23+AK23+AO23 -> 0 | O23: ='Summary Sheet - April 2026'!O24 + 'Summary Sheet - May 2026'!O24 + 'Summary Sheet - June 2026'!O24 -> 947509.88 | Q23: ='Summary Sheet - April 2026'!Q24 + 'Summary Sheet - May 2026'!Q24 + 'Summary Sheet - June 2026'!Q24 -> 0 | S23: ='Summary Sheet - April 2026'!S24 +'Summary Sheet - May 2026'!S24 + 'Summary Sheet - June 2026'!S24 -> 0 | U23: ='Summary Sheet - April 2026'!U24 +'Summary Sheet - May 2026'!U24 + 'Summary Sheet - June 2026'!U24 -> 0 | W23: ='Summary Sheet - April 2026'!W24 + 'Summary Sheet - May 2026'!W24 + 'Summary Sheet - June 2026'!W24 -> 46560.5 | Y23: ='Summary Sheet - April 2026'!Y24 + 'Summary Sheet - May 2026'!Y24 + 'Summary Sheet - June 2026'!Y24 -> 0 | AA23: ='Summary Sheet - April 2026'!AA24 + 'Summary Sheet - May 2026'!AA24 + 'Summary Sheet - June 2026'!AA24 -> 55147.82 | AC23: ='Summary Sheet - April 2026'!AC24 + 'Summary Sheet - May 2026'!AC24 + 'Summary Sheet - June 2026'!AC24 -> 0 | AE23: ='Summary Sheet - April 2026'!AE24 + 'Summary Sheet - May 2026'!AE24 + 'Summary Sheet - June 2026'!AE24 -> 47677.73 | AG23: ='Summary Sheet - April 2026'!AG24 + 'Summary Sheet - May 2026'!AG24 + 'Summary Sheet - June 2026'!AG24 -> 0 | AI23: ='Summary Sheet - April 2026'!AI24 + 'Summary Sheet - May 2026'!AI24 + 'Summary Sheet - June 2026'!AI24 -> 0 | AK23: ='Summary Sheet - April 2026'!AK24 + 'Summary Sheet - May 2026'!AK24 + 'Summary Sheet - June 2026'!AK24 -> 0 | AM23: ='Summary Sheet - April 2026'!AM24 + 'Summary Sheet - May 2026'!AM24 + 'Summary Sheet - June 2026'!AM24 -> 11118.42 | AO23: ='Summary Sheet - April 2026'!AO24 + 'Summary Sheet - May 2026'!AO24 + 'Summary Sheet - June 2026'!AO24 -> 0 | AQ23: ='Summary Sheet - April 2026'!AQ24 + 'Summary Sheet - May 2026'!AQ24 + 'Summary Sheet - June 2026'!AQ24 -> 36885.62 | AS23: ='Summary Sheet - April 2026'!AS24 + 'Summary Sheet - May 2026'!AS24 + 'Summary Sheet - June 2026'!AS24 -> 0 | AU23: ='Summary Sheet - April 2026'!AU24 + 'Summary Sheet - May 2026'!AU24 + 'Summary Sheet - June 2026'!AU24 -> 0 | AW23: ='Summary Sheet - April 2026'!AW24 + 'Summary Sheet - May 2026'!AW24 + 'Summary Sheet - June 2026'!AW24 -> 0 | AY23: ='Summary Sheet - April 2026'!AY24 + 'Summary Sheet - May 2026'!AY24 + 'Summary Sheet - June 2026'!AY24 -> 0 | BA23: ='Summary Sheet - April 2026'!BA24 + 'Summary Sheet - May 2026'!BA24 + 'Summary Sheet - June 2026'!BA24 -> 0 | BC23: ='Summary Sheet - April 2026'!BC24 + 'Summary Sheet - May 2026'!BC24 + 'Summary Sheet - June 2026'!BC24 -> 0 | BE23: ='Summary Sheet - April 2026'!BE24 + 'Summary Sheet - May 2026'!BE24 + 'Summary Sheet - June 2026'!BE24 -> 0 | BG23: ='Summary Sheet - April 2026'!BG24 + 'Summary Sheet - May 2026'!BG24 + 'Summary Sheet - June 2026'!BG24 -> 0 | BI23: ='Summary Sheet - April 2026'!BI24 + 'Summary Sheet - May 2026'!BI24 + 'Summary Sheet - June 2026'!BI24 -> 0
B24: Software and Subscription | C24: =G24+K24 -> 964259.07 | D24: =C24/$C$10 -> 0.0064794081 | E24: =I24+M24 -> 134471.92 | G24: ='Summary Sheet - April 2026'!G25 + 'Summary Sheet - May 2026'!G25 + 'Summary Sheet - June 2026'!G25 -> 241237.57 | I24: ='Summary Sheet - April 2026'!I25 + 'Summary Sheet - May 2026'!I25 + 'Summary Sheet - June 2026'!I25 -> 0 | K24: =O24+S24+W24+AA24+AE24+AI24+AM24+AQ24+AU24+AY24+BC24+BG24 -> 723021.5 | M24: =Q24+U24+Y24+AC24+AG24+AK24+AO24 -> 134471.92 | O24: ='Summary Sheet - April 2026'!O25 + 'Summary Sheet - May 2026'!O25 + 'Summary Sheet - June 2026'!O25 -> 48494.333 | Q24: ='Summary Sheet - April 2026'!Q25 + 'Summary Sheet - May 2026'!Q25 + 'Summary Sheet - June 2026'!Q25 -> 0 | S24: ='Summary Sheet - April 2026'!S25 +'Summary Sheet - May 2026'!S25 + 'Summary Sheet - June 2026'!S25 -> 46181 | U24: ='Summary Sheet - April 2026'!U25 +'Summary Sheet - May 2026'!U25 + 'Summary Sheet - June 2026'!U25 -> 0 | W24: ='Summary Sheet - April 2026'!W25 + 'Summary Sheet - May 2026'!W25 + 'Summary Sheet - June 2026'!W25 -> 127370.67 | Y24: ='Summary Sheet - April 2026'!Y25 + 'Summary Sheet - May 2026'!Y25 + 'Summary Sheet - June 2026'!Y25 -> 0 | AA24: ='Summary Sheet - April 2026'!AA25 + 'Summary Sheet - May 2026'!AA25 + 'Summary Sheet - June 2026'!AA25 -> 99640.667 | AC24: ='Summary Sheet - April 2026'!AC25 + 'Summary Sheet - May 2026'!AC25 + 'Summary Sheet - June 2026'!AC25 -> 49820.333 | AE24: ='Summary Sheet - April 2026'!AE25 + 'Summary Sheet - May 2026'!AE25 + 'Summary Sheet - June 2026'!AE25 -> 155690.67 | AG24: ='Summary Sheet - April 2026'!AG25 + 'Summary Sheet - May 2026'!AG25 + 'Summary Sheet - June 2026'!AG25 -> 77845.333 | AI24: ='Summary Sheet - April 2026'!AI25 + 'Summary Sheet - May 2026'!AI25 + 'Summary Sheet - June 2026'!AI25 -> 13612.5 | AK24: ='Summary Sheet - April 2026'!AK25 + 'Summary Sheet - May 2026'!AK25 + 'Summary Sheet - June 2026'!AK25 -> 6806.25 | AM24: ='Summary Sheet - April 2026'!AM25 + 'Summary Sheet - May 2026'!AM25 + 'Summary Sheet - June 2026'!AM25 -> 72561.333 | AO24: ='Summary Sheet - April 2026'!AO25 + 'Summary Sheet - May 2026'!AO25 + 'Summary Sheet - June 2026'!AO25 -> 0 | AQ24: ='Summary Sheet - April 2026'!AQ25 + 'Summary Sheet - May 2026'!AQ25 + 'Summary Sheet - June 2026'!AQ25 -> 6293.3333 | AS24: ='Summary Sheet - April 2026'!AS25 + 'Summary Sheet - May 2026'!AS25 + 'Summary Sheet - June 2026'!AS25 -> 3146.6667 | AU24: ='Summary Sheet - April 2026'!AU25 + 'Summary Sheet - May 2026'!AU25 + 'Summary Sheet - June 2026'!AU25 -> 58819 | AW24: ='Summary Sheet - April 2026'!AW25 + 'Summary Sheet - May 2026'!AW25 + 'Summary Sheet - June 2026'!AW25 -> 0 | AY24: ='Summary Sheet - April 2026'!AY25 + 'Summary Sheet - May 2026'!AY25 + 'Summary Sheet - June 2026'!AY25 -> 46182 | BA24: ='Summary Sheet - April 2026'!BA25 + 'Summary Sheet - May 2026'!BA25 + 'Summary Sheet - June 2026'!BA25 -> 0 | BC24: ='Summary Sheet - April 2026'!BC25 + 'Summary Sheet - May 2026'!BC25 + 'Summary Sheet - June 2026'!BC25 -> 46182 | BE24: ='Summary Sheet - April 2026'!BE25 + 'Summary Sheet - May 2026'!BE25 + 'Summary Sheet - June 2026'!BE25 -> 0 | BG24: ='Summary Sheet - April 2026'!BG25 + 'Summary Sheet - May 2026'!BG25 + 'Summary Sheet - June 2026'!BG25 -> 1994 | BI24: ='Summary Sheet - April 2026'!BI25 + 'Summary Sheet - May 2026'!BI25 + 'Summary Sheet - June 2026'!BI25 -> 0
B25: Other Outlet Costs | C25: =G25+K25 -> 9882304.1 | D25: =C25/$C$10 -> 0.066404852 | E25: =I25+M25 -> 356555.58 | G25: ='Summary Sheet - April 2026'!G26 + 'Summary Sheet - May 2026'!G26 + 'Summary Sheet - June 2026'!G26 -> 2184064 | I25: ='Summary Sheet - April 2026'!I26 + 'Summary Sheet - May 2026'!I26 + 'Summary Sheet - June 2026'!I26 -> 737.5 | K25: =O25+S25+W25+AA25+AE25+AI25+AM25+AQ25+AU25+AY25+BC25+BG25 -> 7698240.1 | M25: =Q25+U25+Y25+AC25+AG25+AK25+AO25 -> 355818.08 | O25: ='Summary Sheet - April 2026'!O26 + 'Summary Sheet - May 2026'!O26 + 'Summary Sheet - June 2026'!O26 -> 2374341.3 | Q25: ='Summary Sheet - April 2026'!Q26 + 'Summary Sheet - May 2026'!Q26 + 'Summary Sheet - June 2026'!Q26 -> 184154.58 | S25: ='Summary Sheet - April 2026'!S26 +'Summary Sheet - May 2026'!S26 + 'Summary Sheet - June 2026'!S26 -> 155919 | U25: ='Summary Sheet - April 2026'!U26 +'Summary Sheet - May 2026'!U26 + 'Summary Sheet - June 2026'!U26 -> 0 | W25: ='Summary Sheet - April 2026'!W26 + 'Summary Sheet - May 2026'!W26 + 'Summary Sheet - June 2026'!W26 -> 1114412.7 | Y25: ='Summary Sheet - April 2026'!Y26 + 'Summary Sheet - May 2026'!Y26 + 'Summary Sheet - June 2026'!Y26 -> 0 | AA25: ='Summary Sheet - April 2026'!AA26 + 'Summary Sheet - May 2026'!AA26 + 'Summary Sheet - June 2026'!AA26 -> 468887.5 | AC25: ='Summary Sheet - April 2026'!AC26 + 'Summary Sheet - May 2026'!AC26 + 'Summary Sheet - June 2026'!AC26 -> 15522.25 | AE25: ='Summary Sheet - April 2026'!AE26 + 'Summary Sheet - May 2026'!AE26 + 'Summary Sheet - June 2026'!AE26 -> 922235.09 | AG25: ='Summary Sheet - April 2026'!AG26 + 'Summary Sheet - May 2026'!AG26 + 'Summary Sheet - June 2026'!AG26 -> 133043 | AI25: ='Summary Sheet - April 2026'!AI26 + 'Summary Sheet - May 2026'!AI26 + 'Summary Sheet - June 2026'!AI26 -> 1414742.5 | AK25: ='Summary Sheet - April 2026'!AK26 + 'Summary Sheet - May 2026'!AK26 + 'Summary Sheet - June 2026'!AK26 -> 5934.9167 | AM25: ='Summary Sheet - April 2026'!AM26 + 'Summary Sheet - May 2026'!AM26 + 'Summary Sheet - June 2026'!AM26 -> 161457.6 | AO25: ='Summary Sheet - April 2026'!AO26 + 'Summary Sheet - May 2026'!AO26 + 'Summary Sheet - June 2026'!AO26 -> 17163.333 | AQ25: ='Summary Sheet - April 2026'!AQ26 + 'Summary Sheet - May 2026'!AQ26 + 'Summary Sheet - June 2026'!AQ26 -> 994208.45 | AS25: ='Summary Sheet - April 2026'!AS26 + 'Summary Sheet - May 2026'!AS26 + 'Summary Sheet - June 2026'!AS26 -> 212632.08 | AU25: ='Summary Sheet - April 2026'!AU26 + 'Summary Sheet - May 2026'!AU26 + 'Summary Sheet - June 2026'!AU26 -> 8100 | AW25: ='Summary Sheet - April 2026'!AW26 + 'Summary Sheet - May 2026'!AW26 + 'Summary Sheet - June 2026'!AW26 -> 0 | AY25: ='Summary Sheet - April 2026'!AY26 + 'Summary Sheet - May 2026'!AY26 + 'Summary Sheet - June 2026'!AY26 -> 8100 | BA25: ='Summary Sheet - April 2026'!BA26 + 'Summary Sheet - May 2026'!BA26 + 'Summary Sheet - June 2026'!BA26 -> 0 | BC25: ='Summary Sheet - April 2026'!BC26 + 'Summary Sheet - May 2026'!BC26 + 'Summary Sheet - June 2026'!BC26 -> 0 | BE25: ='Summary Sheet - April 2026'!BE26 + 'Summary Sheet - May 2026'!BE26 + 'Summary Sheet - June 2026'!BE26 -> 0 | BG25: ='Summary Sheet - April 2026'!BG26 + 'Summary Sheet - May 2026'!BG26 + 'Summary Sheet - June 2026'!BG26 -> 75836 | BI25: ='Summary Sheet - April 2026'!BI26 + 'Summary Sheet - May 2026'!BI26 + 'Summary Sheet - June 2026'!BI26 -> 0
B26: Other Professional Fees | C26: =G26+K26 -> 925817 | D26: =C26/$C$10 -> 0.0062210938 | E26: =I26+M26 -> 10010 | G26: ='Summary Sheet - April 2026'!G27 + 'Summary Sheet - May 2026'!G27 + 'Summary Sheet - June 2026'!G27 -> 828298 | I26: ='Summary Sheet - April 2026'!I27 + 'Summary Sheet - May 2026'!I27 + 'Summary Sheet - June 2026'!I27 -> 0 | K26: =O26+S26+W26+AA26+AE26+AI26+AM26+AQ26+AU26+AY26+BC26+BG26 -> 97519 | M26: =Q26+U26+Y26+AC26+AG26+AK26+AO26 -> 10010 | O26: ='Summary Sheet - April 2026'!O27 + 'Summary Sheet - May 2026'!O27 + 'Summary Sheet - June 2026'!O27 -> 40644 | Q26: ='Summary Sheet - April 2026'!Q27 + 'Summary Sheet - May 2026'!Q27 + 'Summary Sheet - June 2026'!Q27 -> 0 | S26: ='Summary Sheet - April 2026'!S27 +'Summary Sheet - May 2026'!S27 + 'Summary Sheet - June 2026'!S27 -> 0 | U26: ='Summary Sheet - April 2026'!U27 +'Summary Sheet - May 2026'!U27 + 'Summary Sheet - June 2026'!U27 -> 0 | W26: ='Summary Sheet - April 2026'!W27 + 'Summary Sheet - May 2026'!W27 + 'Summary Sheet - June 2026'!W27 -> 20335 | Y26: ='Summary Sheet - April 2026'!Y27 + 'Summary Sheet - May 2026'!Y27 + 'Summary Sheet - June 2026'!Y27 -> 0 | AA26: ='Summary Sheet - April 2026'!AA27 + 'Summary Sheet - May 2026'!AA27 + 'Summary Sheet - June 2026'!AA27 -> 0 | AC26: ='Summary Sheet - April 2026'!AC27 + 'Summary Sheet - May 2026'!AC27 + 'Summary Sheet - June 2026'!AC27 -> 0 | AE26: ='Summary Sheet - April 2026'!AE27 + 'Summary Sheet - May 2026'!AE27 + 'Summary Sheet - June 2026'!AE27 -> 20020 | AG26: ='Summary Sheet - April 2026'!AG27 + 'Summary Sheet - May 2026'!AG27 + 'Summary Sheet - June 2026'!AG27 -> 10010 | AI26: ='Summary Sheet - April 2026'!AI27 + 'Summary Sheet - May 2026'!AI27 + 'Summary Sheet - June 2026'!AI27 -> 0 | AK26: ='Summary Sheet - April 2026'!AK27 + 'Summary Sheet - May 2026'!AK27 + 'Summary Sheet - June 2026'!AK27 -> 0 | AM26: ='Summary Sheet - April 2026'!AM27 + 'Summary Sheet - May 2026'!AM27 + 'Summary Sheet - June 2026'!AM27 -> 0 | AO26: ='Summary Sheet - April 2026'!AO27 + 'Summary Sheet - May 2026'!AO27 + 'Summary Sheet - June 2026'!AO27 -> 0 | AQ26: ='Summary Sheet - April 2026'!AQ27 + 'Summary Sheet - May 2026'!AQ27 + 'Summary Sheet - June 2026'!AQ27 -> 16520 | AS26: ='Summary Sheet - April 2026'!AS27 + 'Summary Sheet - May 2026'!AS27 + 'Summary Sheet - June 2026'!AS27 -> 8260 | AU26: ='Summary Sheet - April 2026'!AU27 + 'Summary Sheet - May 2026'!AU27 + 'Summary Sheet - June 2026'!AU27 -> 0 | AW26: ='Summary Sheet - April 2026'!AW27 + 'Summary Sheet - May 2026'!AW27 + 'Summary Sheet - June 2026'!AW27 -> 0 | AY26: ='Summary Sheet - April 2026'!AY27 + 'Summary Sheet - May 2026'!AY27 + 'Summary Sheet - June 2026'!AY27 -> 0 | BA26: ='Summary Sheet - April 2026'!BA27 + 'Summary Sheet - May 2026'!BA27 + 'Summary Sheet - June 2026'!BA27 -> 0 | BC26: ='Summary Sheet - April 2026'!BC27 + 'Summary Sheet - May 2026'!BC27 + 'Summary Sheet - June 2026'!BC27 -> 0 | BE26: ='Summary Sheet - April 2026'!BE27 + 'Summary Sheet - May 2026'!BE27 + 'Summary Sheet - June 2026'!BE27 -> 0 | BG26: ='Summary Sheet - April 2026'!BG27 + 'Summary Sheet - May 2026'!BG27 + 'Summary Sheet - June 2026'!BG27 -> 0 | BI26: ='Summary Sheet - April 2026'!BI27 + 'Summary Sheet - May 2026'!BI27 + 'Summary Sheet - June 2026'!BI27 -> 0
B27: Other Expenses | C27: =G27+K27 -> -3582848.6 | D27: =C27/$C$10 -> -0.024075208 | E27: =I27+M27 -> 0 | G27: ='Summary Sheet - April 2026'!G28 + 'Summary Sheet - May 2026'!G28 + 'Summary Sheet - June 2026'!G28 -> 423825.41 | I27: ='Summary Sheet - April 2026'!I28 + 'Summary Sheet - May 2026'!I28 + 'Summary Sheet - June 2026'!I28 -> 0 | K27: =O27+S27+W27+AA27+AE27+AI27+AM27+AQ27+AU27+AY27+BC27+BG27 -> -4006674 | M27: =Q27+U27+Y27+AC27+AG27+AK27+AO27 -> 0 | O27: ='Summary Sheet - April 2026'!O28 + 'Summary Sheet - May 2026'!O28 + 'Summary Sheet - June 2026'!O28 -> 0 | Q27: ='Summary Sheet - April 2026'!Q28 + 'Summary Sheet - May 2026'!Q28 + 'Summary Sheet - June 2026'!Q28 -> 0 | S27: ='Summary Sheet - April 2026'!S28 +'Summary Sheet - May 2026'!S28 + 'Summary Sheet - June 2026'!S28 -> 0 | U27: ='Summary Sheet - April 2026'!U28 +'Summary Sheet - May 2026'!U28 + 'Summary Sheet - June 2026'!U28 -> 0 | W27: ='Summary Sheet - April 2026'!W28 + 'Summary Sheet - May 2026'!W28 + 'Summary Sheet - June 2026'!W28 -> 0 | Y27: ='Summary Sheet - April 2026'!Y28 + 'Summary Sheet - May 2026'!Y28 + 'Summary Sheet - June 2026'!Y28 -> 0 | AA27: ='Summary Sheet - April 2026'!AA28 + 'Summary Sheet - May 2026'!AA28 + 'Summary Sheet - June 2026'!AA28 -> 0 | AC27: ='Summary Sheet - April 2026'!AC28 + 'Summary Sheet - May 2026'!AC28 + 'Summary Sheet - June 2026'!AC28 -> 0 | AE27: ='Summary Sheet - April 2026'!AE28 + 'Summary Sheet - May 2026'!AE28 + 'Summary Sheet - June 2026'!AE28 -> 0 | AG27: ='Summary Sheet - April 2026'!AG28 + 'Summary Sheet - May 2026'!AG28 + 'Summary Sheet - June 2026'!AG28 -> 0 | AI27: ='Summary Sheet - April 2026'!AI28 + 'Summary Sheet - May 2026'!AI28 + 'Summary Sheet - June 2026'!AI28 -> 0 | AK27: ='Summary Sheet - April 2026'!AK28 + 'Summary Sheet - May 2026'!AK28 + 'Summary Sheet - June 2026'!AK28 -> 0 | AM27: ='Summary Sheet - April 2026'!AM28 + 'Summary Sheet - May 2026'!AM28 + 'Summary Sheet - June 2026'!AM28 -> -4016974 | AO27: ='Summary Sheet - April 2026'!AO28 + 'Summary Sheet - May 2026'!AO28 + 'Summary Sheet - June 2026'!AO28 -> 0 | AQ27: ='Summary Sheet - April 2026'!AQ28 + 'Summary Sheet - May 2026'!AQ28 + 'Summary Sheet - June 2026'!AQ28 -> 0 | AS27: ='Summary Sheet - April 2026'!AS28 + 'Summary Sheet - May 2026'!AS28 + 'Summary Sheet - June 2026'!AS28 -> 0 | AU27: ='Summary Sheet - April 2026'!AU28 + 'Summary Sheet - May 2026'!AU28 + 'Summary Sheet - June 2026'!AU28 -> 0 | AW27: ='Summary Sheet - April 2026'!AW28 + 'Summary Sheet - May 2026'!AW28 + 'Summary Sheet - June 2026'!AW28 -> 0 | AY27: ='Summary Sheet - April 2026'!AY28 + 'Summary Sheet - May 2026'!AY28 + 'Summary Sheet - June 2026'!AY28 -> 0 | BA27: ='Summary Sheet - April 2026'!BA28 + 'Summary Sheet - May 2026'!BA28 + 'Summary Sheet - June 2026'!BA28 -> 0 | BC27: ='Summary Sheet - April 2026'!BC28 + 'Summary Sheet - May 2026'!BC28 + 'Summary Sheet - June 2026'!BC28 -> 0 | BE27: ='Summary Sheet - April 2026'!BE28 + 'Summary Sheet - May 2026'!BE28 + 'Summary Sheet - June 2026'!BE28 -> 0 | BG27: ='Summary Sheet - April 2026'!BG28 + 'Summary Sheet - May 2026'!BG28 + 'Summary Sheet - June 2026'!BG28 -> 10300 | BI27: ='Summary Sheet - April 2026'!BI28 + 'Summary Sheet - May 2026'!BI28 + 'Summary Sheet - June 2026'!BI28 -> 0
B28: Total Other Expenses | C28: =SUM(C18:C27) -> 85528372 | D28: =C28/C10 -> 0.57471404 | E28: =I28+M28 -> #REF! | G28: =SUM(G18:G27) -> 14101185 | I28: =SUM(I18:I27) -> 53837.5 | K28: =SUM(K18:K27) -> 71427187 | M28: =SUM(M18:M27) -> #REF! | O28: =SUM(O18:O27) -> 18874107 | Q28: =SUM(Q18:Q27) -> 2267621.6 | S28: =SUM(S18:S27) -> 1594493.7 | U28: =SUM(U18:U27) -> 76212 | W28: =SUM(W18:W27) -> 13328559 | Y28: =SUM(Y18:Y27) -> #REF! | AA28: =SUM(AA18:AA27) -> 8465905.3 | AC28: =SUM(AC18:AC27) -> 65342.583 | AE28: =SUM(AE18:AE27) -> 13526888 | AG28: =SUM(AG18:AG27) -> 220898.33 | AI28: =SUM(AI18:AI27) -> 2375002 | AK28: =SUM(AK18:AK27) -> 103672.17 | AM28: =SUM(AM18:AM27) -> -0.06 | AO28: =SUM(AO18:AO27) -> 267286.33 | AQ28: =SUM(AQ18:AQ27) -> 11118566 | AS28: =SUM(AS18:AS27) -> 261457.75 | AU28: =SUM(AU18:AU27) -> 343230.31 | AW28: =SUM(AW18:AW27) -> 0 | AY28: =SUM(AY18:AY27) -> 166501.31 | BA28: =SUM(BA18:BA27) -> 0 | BC28: =SUM(BC18:BC27) -> 175321.97 | BE28: =SUM(BE18:BE27) -> 0 | BG28: =SUM(BG18:BG27) -> 1458612.1 | BI28: =SUM(BI18:BI27) -> 0
B30: EBIDTA | C30: =C16-C28 -> 5558250.2 | E30: =E16-E28 -> #REF! | G30: =G16-G28 -> -14101185 | I30: =I16-I28 -> -53837.5 | K30: =K16-K28 -> 19659435 | M30: =M16-M28 -> #REF! | O30: =O16-O28 -> 7693765.5 | Q30: =Q16-Q28 -> -2267621.6 | S30: =S16-S28 -> -573873.19 | U30: =U16-U28 -> -76212 | W30: =W16-W28 -> 1718626.1 | Y30: =Y16-Y28 -> #REF! | AA30: =AA16-AA28 -> 3294340.5 | AC30: =AC16-AC28 -> -65342.583 | AE30: =AE16-AE28 -> 8770468.7 | AG30: =AG16-AG28 -> -220898.33 | AI30: =AI16-AI28 -> -2376032 | AK30: =AK16-AK28 -> -103672.17 | AM30: =AM16-AM28 -> -929566.1 | AO30: =AO16-AO28 -> -267286.33 | AQ30: =AQ16-AQ28 -> 3506230.1 | AS30: =AS16-AS28 -> -261457.75 | AU30: =AU16-AU28 -> -123531.44 | AW30: =AW16-AW28 -> 0 | AY30: =AY16-AY28 -> -287048.43 | BA30: =BA16-BA28 -> 0 | BC30: =BC16-BC28 -> -369427.62 | BE30: =BE16-BE28 -> 0 | BG30: =BG16-BG28 -> -664517.3 | BI30: =BI16-BI28 -> 0
B31: EBIDTA Margin | C31: =C30/C10 -> 0.037349061 | E31: =E30/E10 -> #REF! | K31: =K30/K10 -> 0.13210299 | M31: =M30/M10 -> #REF! | O31: =O30/O10 -> 0.18795404 | Q31: =Q30/Q10 -> #DIV/0! | S31: =S30/S10 -> -0.34420386 | U31: =U30/U10 -> #DIV/0! | W31: =W30/W10 -> 0.067975355 | Y31: =Y30/Y10 -> #REF! | AA31: =AA30/AA10 -> 0.17206722 | AC31: =AC30/AC10 -> #DIV/0! | AE31: =AE30/AE10 -> 0.2562012 | AG31: =AG30/AG10 -> #DIV/0! | AI31: =AI30/AI10 -> #DIV/0! | AK31: =AK30/AK10 -> #DIV/0! | AM31: =AM30/AM10 -> -0.95733473 | AO31: =AO30/AO10 -> #DIV/0!
C33: =G33+K33 -> 5558250.2 | G33: ='Summary Sheet - April 2026'!G31+'Summary Sheet - May 2026'!G31 -> -14101185 | K33: =SUM(O33:BJ33) -> 19659435 | O33: ='Summary Sheet - April 2026'!O31+'Summary Sheet - May 2026'!O31 -> 7693765.5 | S33: ='Summary Sheet - April 2026'!S31+'Summary Sheet - May 2026'!S31 -> -573873.19 | W33: ='Summary Sheet - April 2026'!W31+'Summary Sheet - May 2026'!W31 -> 1718626.1 | AA33: ='Summary Sheet - April 2026'!AA31+'Summary Sheet - May 2026'!AA31 -> 3294340.5 | AE33: ='Summary Sheet - April 2026'!AE31+'Summary Sheet - May 2026'!AE31 -> 8770468.7 | AI33: ='Summary Sheet - April 2026'!AI31+'Summary Sheet - May 2026'!AI31 -> -2376032 | AM33: ='Summary Sheet - April 2026'!AM31+'Summary Sheet - May 2026'!AM31 -> -929566.1 | AQ33: ='Summary Sheet - April 2026'!AQ31+'Summary Sheet - May 2026'!AQ31 -> 3506230.1 | AU33: ='Summary Sheet - April 2026'!AU31+'Summary Sheet - May 2026'!AU31 -> -123531.44 | AY33: ='Summary Sheet - April 2026'!AY31+'Summary Sheet - May 2026'!AY31 -> -287048.43 | BC33: ='Summary Sheet - April 2026'!BC31+'Summary Sheet - May 2026'!BC31 -> -369427.62 | BG33: ='Summary Sheet - April 2026'!BG31+'Summary Sheet - May 2026'!BG31 -> -664517.3
C34: =+C30-C33 -> -3.7252903e-09 | G34: =+G30-G33 -> -1.8626451e-09 | K34: =+K30-K33 -> -1.8626451e-08 | O34: =+O30-O33 -> -3.7252903e-09 | S34: =+S30-S33 -> 0 | W34: =+W30-W33 -> 2.7939677e-09 | AA34: =+AA30-AA33 -> -1.8626451e-09 | AE34: =+AE30-AE33 -> -5.5879354e-09 | AI34: =+AI30-AI33 -> 0 | AM34: =+AM30-AM33 -> 0 | AQ34: =+AQ30-AQ33 -> -1.8626451e-09 | AU34: =+AU30-AU33 -> 0 | AY34: =+AY30-AY33 -> 0 | BC34: =+BC30-BC33 -> 0 | BG34: =+BG30-BG33 -> 0

Sheet Mg St Colaba Comparison
A1: Mg St Colaba Comparison
C3: 45748 | D3: 45778 | E3: 45809 | F3: 45839 | G3: 45870 | H3: 45901
B4: Beverage | C4: ='Summary Sheet - April 2026'!W5 -> 1181100 | D4: =#REF! -> #REF! | E4: =#REF! -> #REF! | F4: =#REF! -> #REF! | G4: =#REF! -> #REF! | H4: ='Mg St Colaba'!#REF! -> #ERROR!
B5: Liquor | C5: ='Summary Sheet - April 2026'!W6 -> 769660 | D5: =#REF! -> #REF! | E5: =#REF! -> #REF! | F5: =#REF! -> #REF! | G5: =#REF! -> #REF! | H5: ='Mg St Colaba'!#REF! -> #ERROR!
B6: Food | C6: ='Summary Sheet - April 2026'!W7 -> 10177814 | D6: =#REF! -> #REF! | E6: =#REF! -> #REF! | F6: =#REF! -> #REF! | G6: =#REF! -> #REF! | H6: ='Mg St Colaba'!#REF! -> #ERROR!
B7: Service Charge | C7: ='Summary Sheet - April 2026'!W8 -> 721626 | D7: =#REF! -> #REF! | E7: =#REF! -> #REF! | F7: =#REF! -> #REF! | G7: =#REF! -> #REF! | H7: ='Mg St Colaba'!#REF! -> #ERROR!
B8: Total Sales Revenue | C8: =SUM(C4:C7) -> 12850200 | D8: =SUM(D4:D7) -> #REF! | E8: =SUM(E4:E7) -> #REF! | F8: =SUM(F4:F7) -> #REF! | G8: =SUM(G4:G7) -> #REF! | H8: =SUM(H4:H7) -> #ERROR!
C9: ='Summary Sheet - April 2026'!O11 | D9: =#REF! -> #REF! | E9: =#REF! -> #REF! | F9: =#REF! -> #REF!
B10: COGS | C10: ='Summary Sheet - April 2026'!W12 -> 4857214.2 | D10: =#REF! -> #REF! | E10: =#REF! -> #REF! | F10: =#REF! -> #REF! | G10: =#REF! -> #REF! | H10: ='Mg St Colaba'!#REF! -> #ERROR!
B11: Packaging Cost | C11: ='Summary Sheet - April 2026'!W13 -> 187031.4 | D11: =#REF! -> #REF! | E11: =#REF! -> #REF! | F11: =#REF! -> #REF! | G11: =#REF! -> #REF! | H11: ='Mg St Colaba'!#REF! -> #ERROR!
B12: Total COGS & Packaging | C12: =C10+C11 -> 5044245.6 | D12: =D10+D11 -> #REF! | E12: =E10+E11 -> #REF! | F12: =F10+F11 -> #REF! | G12: =G10+G11 -> #REF! | H12: =H10+H11 -> #ERROR!
B13: DEQ | C13: =#REF! -> #REF! | D13: ='Mg St Colaba'!#REF! -> #ERROR! | E13: ='Mg St Colaba'!#REF! -> #ERROR! | F13: ='Mg St Colaba'!#REF! -> #ERROR! | G13: ='Mg St Colaba'!#REF! -> #ERROR! | H13: ='Mg St Colaba'!#REF! -> #ERROR!
E14: =#REF! -> #REF! | F14: =#REF! -> #REF!
B15: Gross Margin | C15: =C8-C12-C13 -> #REF! | D15: =D8-D12-D13 -> #REF! | E15: =E8-E12-E13 -> #REF! | F15: =F8-F12-F13 -> #REF! | G15: =G8-G12-G13 -> #REF! | H15: =H8-H12-H13 -> #ERROR!
B16: Gross Margin %age | C16: =C15/C8 -> #REF! | D16: =D15/D8 -> #REF! | E16: =E15/E8 -> #REF! | F16: =F15/F8 -> #REF! | G16: =G15/G8 -> #REF! | H16: =H15/H8 -> #ERROR!
C17: ='Summary Sheet - April 2026'!O16 | D17: =#REF! -> #REF! | E17: =#REF! -> #REF! | F17: =#REF! -> #REF!
B18: Other Direct Expenses | C18: ='Summary Sheet - April 2026'!W19 -> 393268.87 | D18: =#REF! -> #REF! | E18: =#REF! -> #REF! | F18: =#REF! -> #REF! | G18: =#REF! -> #REF! | H18: ='Mg St Colaba'!#REF! -> #ERROR!
B19: Marketing Expenses | C19: ='Summary Sheet - April 2026'!W20 -> 196105.44 | D19: =#REF! -> #REF! | E19: =#REF! -> #REF! | F19: =#REF! -> #REF! | G19: =#REF! -> #REF! | H19: ='Mg St Colaba'!#REF! -> #ERROR!
B20: Sales Commission | C20: ='Summary Sheet - April 2026'!W21 -> 480580.79 | D20: =#REF! -> #REF! | E20: =#REF! -> #REF! | F20: =#REF! -> #REF! | G20: =#REF! -> #REF! | H20: ='Mg St Colaba'!#REF! -> #ERROR!
B21: Rental & Utility Expenses | C21: ='Summary Sheet - April 2026'!W22 -> 1695349.3 | D21: =#REF! -> #REF! | E21: =#REF! -> #REF! | F21: =#REF! -> #REF! | G21: =#REF! -> #REF! | H21: ='Mg St Colaba'!#REF! -> #ERROR!
B22: Salary & Staff Expenses | C22: ='Summary Sheet - April 2026'!W23 -> 3187826.8 | D22: =#REF! -> #REF! | E22: =#REF! -> #REF! | F22: =#REF! -> #REF! | G22: =#REF! -> #REF! | H22: ='Mg St Colaba'!#REF! -> #ERROR!
B23: Bank and Finance Charges | C23: ='Summary Sheet - April 2026'!W24 -> 24118.9 | D23: =#REF! -> #REF! | E23: =#REF! -> #REF! | F23: =#REF! -> #REF! | G23: ='Mg St Colaba'!#REF! -> #ERROR! | H23: ='Mg St Colaba'!#REF! -> #ERROR!
B24: Software and Subscription | C24: ='Summary Sheet - April 2026'!W25 -> 63685.333 | D24: =#REF! -> #REF! | E24: =#REF! -> #REF! | F24: =#REF! -> #REF! | G24: ='Mg St Colaba'!#REF! -> #ERROR! | H24: ='Mg St Colaba'!#REF! -> #ERROR!
B25: Other Outlet Costs | C25: ='Summary Sheet - April 2026'!W26 -> 667797.92 | D25: =#REF! -> #REF! | E25: =#REF! -> #REF! | F25: =#REF! -> #REF! | G25: ='Mg St Colaba'!#REF! -> #ERROR! | H25: ='Mg St Colaba'!#REF! -> #ERROR!
B26: Other Professional Fees | C26: ='Summary Sheet - April 2026'!W27 -> 10325 | D26: =#REF! -> #REF! | E26: =#REF! -> #REF! | F26: =#REF! -> #REF!
B27: Other Expenses | C27: ='Summary Sheet - April 2026'!W28 -> 0 | D27: =#REF! -> #REF! | E27: =#REF! -> #REF! | F27: =#REF! -> #REF!
B28: Total Other Expenses | C28: =SUM(C18:C27) -> 6719058.4 | D28: =SUM(D18:D27) -> #REF! | E28: =SUM(E18:E27) -> #REF! | F28: =SUM(F18:F27) -> #REF! | G28: =SUM(G18:G27) -> #REF! | H28: =SUM(H18:H27) -> #ERROR!
E29: =#REF! -> #REF! | F29: =#REF! -> #REF!
B30: EBIDTA | C30: =C15-C28 -> #REF! | D30: =D15-D28 -> #REF! | E30: =E15-E28 -> #REF! | F30: =F15-F28 -> #REF! | G30: =G15-G28 -> #REF! | H30: =H15-H28 -> #ERROR!
B31: EBITDA %age | C31: =C30/C8 -> #REF! | D31: =D30/D8 -> #REF! | E31: =E30/E8 -> #REF! | F31: =F30/F8 -> #REF! | G31: =G30/G8 -> #REF! | H31: =H30/H8 -> #ERROR!

Sheet AOV
A1: Restaurant Summary Data
X2: Brand Name | Y2: Overall | AH2: Mag St. Bandra | AR2: Mag St. Colaba | BB2: Mag St. Lower Parel | BL2: Mag St. Bread Co. Bandra | BU2: Mag St. Bread Co. Byculla | CE2: Mag St. Bread Co. Colaba | CO2: Mag St. Bread Co. Lower Parel | CY2: Mag St. Bread Co. Andheri | DH2: The Table Colaba | DR2: Iktara
B3: Mg St Cafe - Colaba | C3: 45444 | D3: 45474 | E3: 45505 | F3: Sept 2024 | G3: 45566 | H3: 45597 | I3: 45627 | J3: 45658 | K3: 45689 | L3: 45717 | M3: 45748 | N3: 45778 | X3: Category | Y3: Total Sales | Z3: Dining Sales | AA3: Delivery Sales | AB3: Others | AC3: Covers | AD3: APC | AE3: Orders | AF3: AOV | AH3: Total Sales | AI3: Dining Sales | AJ3: Delivery Sales | AK3: Others | AL3: Dine in Working | AM3: Covers | AN3: APC | AO3: Orders | AP3: AOV | AR3: Total Sales | AS3: Dining Sales | AT3: Delivery Sales | AU3: Others | AV3: Dine in Working | AW3: Covers | AX3: APC | AY3: Orders | AZ3: AOV | BB3: Total Sales | BC3: Dining Sales | BD3: Delivery Sales | BE3: Others | BF3: Dine in Working | BG3: Covers | BH3: APC | BI3: Orders | BJ3: AOV | BL3: Total Sales | BM3: Dining Sales | BN3: Delivery Sales | BO3: Others | BP3: Covers | BQ3: APC | BR3: Orders | BS3: AOV | BU3: Total Sales | BV3: Dining Sales | BW3: Delivery Sales | BX3: Others | BY3: Dine in Working | BZ3: Covers | CA3: APC | CB3: Orders | CC3: AOV | CE3: Total Sales | CF3: Dining Sales | CG3: Delivery Sales | CH3: Others | CI3: Dine in Working | CJ3: Covers | CK3: APC | CL3: Orders | CM3: AOV | CO3: Total Sales | CP3: Dining Sales | CQ3: Delivery Sales | CR3: Others | CS3: Dine in Working | CT3: Covers | CU3: APC | CV3: Orders | CW3: AOV | CY3: Total Sales | CZ3: Dining Sales | DA3: Delivery Sales | DB3: Others | DC3: Covers | DD3: APC | DE3: Orders | DF3: AOV | DH3: Total Sales | DI3: Dining Sales | DJ3: Delivery Sales | DK3: Others | DL3: Dine in Working | DM3: Covers | DN3: APC | DO3: Orders | DP3: AOV | DR3: Total Sales | DS3: Dining Sales | DT3: Delivery Sales | DU3: Others | DV3: Dine in Working | DW3: Covers | DX3: APC | DY3: Orders | DZ3: AOV
B4: Total Covers (Dine-in) | M4: ='Mg St Colaba'!D6 -> 5434 | N4: ='Mg St Colaba'!#REF! -> #ERROR! | X4: 45444 | Y4: 40610452 | Z4: 32612158 | AA4: 6289412.4 | AB4: 1708882.1 | AC4: 20552 | AD4: 1587.81 | AE4: 7595 | AF4: 1110.22 | AH4: 12780050.75 | AI4: 11218384.75 | AJ4: 1314270.00 | AK4: 247396.00 | AL4: 11465781 | AM4: 7526.00 | AN4: 1491.62 | AO4: 1229 | AP4: 1376.2 | AR4: 10252039 | AS4: 8727909 | AT4: 1207380 | AU4: 316749.75 | AV4: 9044658.8 | AW4: 5928 | AX4: 1473.32 | AY4: 1135 | AZ4: 1427.16 | BB4: 5954008.5 | BC4: 3474309 | BD4: 2001483 | BE4: 478216.5 | BF4: 3952525.5 | BG4: 3802 | BH4: 914.81 | BI4: 2046 | BJ4: 1477.11 | BL4: 206749.36 | BM4: 0 | BN4: 206749.36 | BO4: 0 | BP4: 0 | BQ4: 0 | BR4: 394 | BS4: 524.74 | BU4: 334731.54 | BV4: 0 | BW4: 181825.04 | BX4: 152906.5 | BY4: 152906.5 | BZ4: 0 | CA4: 0 | CB4: 334 | CC4: 629.15 | CE4: 725851.86 | CF4: 0 | CG4: 351691 | CH4: 374160.86 | CI4: 374160.86 | CJ4: 0 | CK4: 0 | CL4: 1174 | CM4: 575.6 | CO4: 445738 | CP4: 0 | CQ4: 442013 | CR4: 3725 | CS4: 3725 | CT4: 0 | CU4: 0 | CV4: 806 | CW4: 550.45 | DH4: 9707698.5 | DI4: 9191555 | DJ4: 408771 | DK4: 107372.5 | DL4: 9298927.5 | DM4: 3296 | DN4: 2789.7 | DO4: 322 | DP4: 1497.33 | DR4: 203585 | DS4: 0 | DT4: 175230 | DU4: 28355 | DV4: 28355 | DW4: 0 | DX4: 0 | DY4: 155 | DZ4: 1260.65
B5: Total Delivery Orders (Swiggy, Zomato +) | M5: ='Mg St Colaba'!D7 -> 1706 | N5: ='Mg St Colaba'!#REF! -> #ERROR! | X5: 45474 | Y5: 42036088 | Z5: 33369905 | AA5: 6715473.7 | AB5: 1936843.8 | AC5: 20849 | AD5: 1601.55 | AE5: 8085 | AF5: 1132.46 | AH5: 12280674.50 | AI5: 10610962.00 | AJ5: 1431076.00 | AK5: 238636.50 | AL5: 10849598 | AM5: 7144.00 | AN5: 1486.30 | AO5: 1332 | AP5: 1385.36 | AR5: 10720273 | AS5: 8903963.8 | AT5: 1458400 | AU5: 357909 | AV5: 9261872.8 | AW5: 6066 | AX5: 1468.85 | AY5: 1305 | AZ5: 1438.26 | BB5: 6271416 | BC5: 3649913.5 | BD5: 1984457 | BE5: 637045.5 | BF5: 4286959 | BG5: 4112 | BH5: 888.62 | BI5: 2162 | BJ5: 1513.7 | BL5: 214714.22 | BM5: 0 | BN5: 214714.22 | BO5: 0 | BP5: 0 | BQ5: 0 | BR5: 390 | BS5: 550.55 | BU5: 389232 | BV5: 0 | BW5: 230855.5 | BX5: 158376.5 | BY5: 158376.5 | BZ5: 0 | CA5: 0 | CB5: 373 | CC5: 708.15 | CE5: 762792.28 | CF5: 0 | CG5: 389437 | CH5: 373355.28 | CI5: 373355.28 | CJ5: 0 | CK5: 0 | CL5: 1265 | CM5: 569.35 | CO5: 399988 | CP5: 0 | CQ5: 398588 | CR5: 1400 | CS5: 1400 | CT5: 0 | CU5: 0 | CV5: 766 | CW5: 521.03 | DH5: 10795638 | DI5: 10205066 | DJ5: 427246 | DK5: 149461 | DL5: 10354527 | DM5: 3527 | DN5: 2894.41 | DO5: 324 | DP5: 1702.18 | DR5: 201360 | DS5: 0 | DT5: 180700 | DU5: 20660 | DV5: 20660 | DW5: 0 | DX5: 0 | DY5: 168 | DZ5: 1158.33
B6: Total Revenue - (Dine-in +Takeaway) | M6: ='Mg St Colaba'!D8 -> 8713619.2 | N6: ='Mg St Colaba'!#REF! -> #ERROR! | X6: 45505 | Y6: 46777133 | Z6: 37054634 | AA6: 7413990.4 | AB6: 2296488.8 | AC6: 22678 | AD6: 1634.95 | AE6: 8551 | AF6: 1177.2 | AH6: 13966088.25 | AI6: 11894934.75 | AJ6: 1645414.00 | AK6: 425739.50 | AL6: 12320674 | AM6: 7634.00 | AN6: 1559.15 | AO6: 1601 | AP6: 1367.76 | AR6: 12132881 | AS6: 10168225 | AT6: 1517171 | AU6: 447485 | AV6: 10615710 | AW6: 6698 | AX6: 1519.1 | AY6: 1372 | AZ6: 1436.71 | BB6: 6848079.2 | BC6: 3841861.8 | BD6: 2334118 | BE6: 672099.5 | BF6: 4513961.2 | BG6: 4354 | BH6: 883.38 | BI6: 2328 | BJ6: 1543.73 | BL6: 218895.16 | BM6: 0 | BN6: 218895.16 | BO6: 0 | BP6: 0 | BQ6: 0 | BR6: 366 | BS6: 598.07 | BU6: 401656 | BV6: 0 | BW6: 221497.25 | BX6: 180158.75 | BY6: 180158.75 | BZ6: 0 | CA6: 0 | CB6: 372 | CC6: 721.49 | CE6: 795599.5 | CF6: 0 | CG6: 378039 | CH6: 417560.5 | CI6: 417560.5 | CJ6: 0 | CK6: 0 | CL6: 1237 | CM6: 584.3 | CO6: 421281 | CP6: 0 | CQ6: 420681 | CR6: 600 | CS6: 600 | CT6: 0 | CU6: 0 | CV6: 763 | CW6: 552.8 | DH6: 11738218 | DI6: 11149613 | DJ6: 457315 | DK6: 119270.5 | DL6: 11268883 | DM6: 3992 | DN6: 2793.99 | DO6: 321 | DP6: 1719.23 | DR6: 254435 | DS6: 0 | DT6: 220860 | DU6: 33575 | DV6: 33575 | DW6: 0 | DX6: 0 | DY6: 191 | DZ6: 1227
B7: Total Revenue - (Delivery) | M7: ='Mg St Colaba'!D9 -> 4136581.2 | N7: ='Mg St Colaba'!#REF! -> #ERROR! | X7: 45536 | Y7: 43460885 | Z7: 33552103 | AA7: 7701230.4 | AB7: 2199476.8 | AC7: 19717 | AD7: 1702.68 | AE7: 8928 | AF7: 1160.17 | AH7: 13429240.00 | AI7: 11164169.00 | AJ7: 1977000.00 | AK7: 288071.00 | AL7: 11452240 | AM7: 6608.00 | AN7: 1690.49 | AO7: 1772 | AP7: 1365.33 | AR7: 10133146 | AS7: 8189301.8 | AT7: 1619433 | AU7: 324411.25 | AV7: 8513713 | AW7: 5533 | AX7: 1481.08 | AY7: 1461 | AZ7: 1403.32 | BB7: 6474856 | BC7: 3479957.8 | BD7: 2290823 | BE7: 704075.25 | BF7: 4184033 | BG7: 3855 | BH7: 903.71 | BI7: 2426 | BJ7: 1473.2 | BL7: 182875 | BM7: 0 | BN7: 182875 | BO7: 0 | BP7: 0 | BQ7: 0 | BR7: 325 | BS7: 562.69 | BU7: 440123.5 | BV7: 200 | BW7: 139654 | BX7: 300269.5 | BY7: 300469.5 | BZ7: 0 | CA7: 0 | CB7: 433 | CC7: 623.46 | CE7: 703701.7 | CF7: 0 | CG7: 373227.42 | CH7: 330474.28 | CI7: 330474.28 | CJ7: 0 | CK7: 0 | CL7: 1182 | CM7: 544.86 | CO7: 412044.98 | CP7: 0 | CQ7: 410094.98 | CR7: 1950 | CS7: 1950 | CT7: 0 | CU7: 0 | CV7: 765 | CW7: 537.48 | DH7: 11306908 | DI7: 10718475 | DJ7: 426088 | DK7: 154270.5 | DL7: 10872745 | DM7: 3721 | DN7: 2881.54 | DO7: 341 | DP7: 1505.61 | DR7: 377990 | DS7: 0 | DT7: 282035 | DU7: 95955 | DV7: 95955 | DW7: 0 | DX7: 0 | DY7: 223 | DZ7: 1403.16
B8: Total Check | M8: ='Mg St Colaba'!D10 -> 0 | N8: ='Mg St Colaba'!#REF! -> #ERROR! | X8: 45566 | Y8: 46397490 | Z8: 35659771 | AA8: 8250709.8 | AB8: 2475063.9 | AC8: 20654 | AD8: 1727.53 | AE8: 9745 | AF8: 1100.24 | AH8: 13496728.62 | AI8: 11228215.50 | AJ8: 1984707.12 | AK8: 283806.00 | AL8: 11512022 | AM8: 6633.00 | AN8: 1693.78 | AO8: 1837 | AP8: 1308.31 | AR8: 10575305 | AS8: 8537077 | AT8: 1654242.6 | AU8: 383985 | AV8: 8921062 | AW8: 5658 | AX8: 1509.85 | AY8: 1589 | AZ8: 1288.35 | BB8: 7186494.2 | BC8: 3907337.8 | BD8: 2474846.5 | BE8: 804310 | BF8: 4711647.8 | BG8: 4251 | BH8: 920.16 | BI8: 2755 | BJ8: 1408.56 | BL8: 219060 | BM8: 0 | BN8: 219060 | BO8: 0 | BP8: 0 | BQ8: 0 | BR8: 388 | BS8: 564.59 | BU8: 457678.25 | BV8: 0 | BW8: 116902 | BX8: 340776.25 | BY8: 340776.25 | BZ8: 0 | CA8: 0 | CB8: 273 | CC8: 524.22 | CE8: 678692.11 | CF8: 0 | CG8: 367754 | CH8: 310938.11 | CI8: 310938.11 | CJ8: 0 | CK8: 0 | CL8: 1158 | CM8: 537.65 | CO8: 504642 | CP8: 0 | CQ8: 500942 | CR8: 3700 | CS8: 3700 | CT8: 0 | CU8: 0 | CV8: 944 | CW8: 531.22 | DH8: 12605985 | DI8: 11987141 | DJ8: 470347 | DK8: 136552 | DL8: 12123693 | DM8: 4112 | DN8: 2916.16 | DO8: 386 | DP8: 1451.69 | DR8: 672905.1 | DS8: 0 | DT8: 461908.6 | DU8: 210996.5 | DV8: 210996.5 | DW8: 0 | DX8: 0 | DY8: 415 | DZ8: 1218.76
B9: AOV (Dine-in) | M9: ='Mg St Colaba'!D11 -> 1603.5369 | N9: ='Mg St Colaba'!#REF! -> #ERROR! | X9: 45597 | Y9: 48633034 | Z9: 37563824 | AA9: 8692990 | AB9: 2285460 | AC9: 21027 | AD9: 1787.46 | AE9: 10086 | AF9: 1098.57 | AH9: 13061755.45 | AI9: 10720005.50 | AJ9: 2039306.95 | AK9: 302443.00 | AL9: 11022448 | AM9: 6458.00 | AN9: 1660.96 | AO9: 1962 | AP9: 1251.11 | AR9: 10518155 | AS9: 8476917 | AT9: 1751339.9 | AU9: 289898.25 | AV9: 8766815.2 | AW9: 5680 | AX9: 1493.41 | AY9: 1498 | AZ9: 1399.95 | BB9: 6803685.6 | BC9: 3364524.5 | BD9: 2672539.6 | BE9: 766621.5 | BF9: 4131146 | BG9: 3669 | BH9: 918.01 | BI9: 2872 | BJ9: 1394.13 | BL9: 223299.14 | BM9: 0 | BN9: 223299.14 | BO9: 0 | BP9: 0 | BQ9: 0 | BR9: 428 | BS9: 521.73 | BU9: 429357.52 | BV9: 0 | BW9: 100377.02 | BX9: 328980.5 | BY9: 328980.5 | BZ9: 0 | CA9: 0 | CB9: 216 | CC9: 563.92 | CE9: 793248.87 | CF9: 0 | CG9: 409549.65 | CH9: 383699.22 | CI9: 383699.22 | CJ9: 0 | CK9: 0 | CL9: 1260 | CM9: 557.21 | CO9: 601704.75 | CP9: 0 | CQ9: 598654.75 | CR9: 3050 | CS9: 3050 | CT9: 0 | CU9: 0 | CV9: 1104 | CW9: 543.24 | DH9: 15706930 | DI9: 15002377 | DJ9: 482688 | DK9: 131105 | DL9: 15133482 | DM9: 5220 | DN9: 2875.02 | DO9: 356 | DP9: 1587.79 | DR9: 494897.46 | DS9: 0 | DT9: 415234.96 | DU9: 79662.5 | DV9: 79662.5 | DW9: 0 | DX9: 0 | DY9: 390 | DZ9: 1128.36
B10: AOV (Delivery) | M10: ='Mg St Colaba'!D12 -> 2424.7252 | N10: ='Mg St Colaba'!#REF! -> #ERROR! | X10: 45627 | Y10: 56858970 | Z10: 45119367 | AA10: 9313600 | AB10: 2414308.5 | AC10: 24520 | AD10: 1841.1 | AE10: 10856 | AF10: 1081.09 | AH10: 15024612.69 | AI10: 12552164.50 | AJ10: 2151840.69 | AK10: 320607.50 | AL10: 12872772 | AM10: 7370.00 | AN10: 1704.14 | AO10: 2057 | AP10: 1264.3 | AR10: 13379585 | AS10: 11118964 | AT10: 1938796.7 | AU10: 321824.5 | AV10: 11440788 | AW10: 7200 | AX10: 1545.3 | AY10: 1732 | AZ10: 1348.26 | BB10: 7225322.6 | BC10: 3710635.5 | BD10: 2787430.6 | BE10: 727256.5 | BF10: 4437892 | BG10: 4010 | BH10: 926.35 | BI10: 2887 | BJ10: 1359.72 | BL10: 312053.11 | BM10: 0 | BN10: 312053.11 | BO10: 0 | BP10: 0 | BQ10: 0 | BR10: 599 | BS10: 520.96 | BU10: 452140.06 | BV10: 0 | BW10: 83230.56 | BX10: 368909.5 | BY10: 368909.5 | BZ10: 0 | CA10: 0 | CB10: 201 | CC10: 547.57 | CE10: 932418.4 | CF10: 0 | CG10: 478284.42 | CH10: 454133.98 | CI10: 454133.98 | CJ10: 0 | CK10: 0 | CL10: 1437 | CM10: 593.4 | CO10: 653261.79 | CP10: 0 | CQ10: 647911.79 | CR10: 5350 | CS10: 5350 | CT10: 0 | CU10: 0 | CV10: 1193 | CW10: 544.01 | DH10: 18336850 | DI10: 17737603 | DJ10: 442208 | DK10: 145344 | DL10: 17882947 | DM10: 5940 | DN10: 2987.13 | DO10: 321 | DP10: 1625.76 | DR10: 542726.6 | DS10: 0 | DT10: 471844.1 | DU10: 70882.5 | DV10: 70882.5 | DW10: 0 | DX10: 0 | DY10: 429 | DZ10: 1165.05
X11: 45658 | Y11: 52803038 | Z11: 41940528 | AA11: 8779763.2 | AB11: 2082747.2 | AC11: 23354 | AD11: 1796.86 | AE11: 10495 | AF11: 1053.87 | AH11: 13499912.08 | AI11: 11173286.50 | AJ11: 2056592.58 | AK11: 270033.00 | AL11: 11443320 | AM11: 6551.00 | AN11: 1706.58 | AO11: 1952 | AP11: 1273.43 | AR11: 12767801 | AS11: 10593907 | AT11: 1837355.3 | AU11: 336539.25 | AV11: 10930446 | AW11: 6947 | AX11: 1525.96 | AY11: 1667 | AZ11: 1318.05 | BB11: 7176728.9 | BC11: 3850240.5 | BD11: 2649011.4 | BE11: 677477 | BF11: 4527717.5 | BG11: 4392 | BH11: 877.65 | BI11: 2934 | BJ11: 1328.49 | BL11: 272329.93 | BM11: 0 | BN11: 272329.93 | BO11: 0 | BP11: 0 | BQ11: 0 | BR11: 524 | BS11: 519.71 | BU11: 426947.01 | BV11: 0 | BW11: 92114.13 | BX11: 334832.88 | BY11: 334832.88 | BZ11: 0 | CA11: 0 | CB11: 199 | CC11: 561.67 | CE11: 724488.44 | CF11: 0 | CG11: 397378.38 | CH11: 327110.06 | CI11: 327110.06 | CJ11: 0 | CK11: 0 | CL11: 1233 | CM11: 542.87 | CO11: 632911.21 | CP11: 0 | CQ11: 632911.21 | CR11: 0 | CS11: 0 | CT11: 0 | CU11: 0 | CV11: 1223 | CW11: 517.51 | DH11: 16900310 | DI11: 16323094 | DJ11: 463151 | DK11: 114065 | DL11: 16437159 | DM11: 5464 | DN11: 2988.39 | DO11: 361 | DP11: 1538.71 | DR11: 401609.25 | DS11: 0 | DT11: 378919.25 | DU11: 22690 | DV11: 22690 | DW11: 0 | DX11: 0 | DY11: 402 | DZ11: 986.77
B12: Mg St Cafe - LP | M12: 45748 | N12: 45778 | X12: 45689 | Y12: 46867379 | Z12: 36154066 | AA12: 8878440.8 | AB12: 1834872.2 | AC12: 20011 | AD12: 1807.71 | AE12: 10204 | AF12: 1064.82 | AH12: 12042585.21 | AI12: 9547877.50 | AJ12: 2163821.21 | AK12: 330886.50 | AL12: 9878764 | AM12: 5823.00 | AN12: 1640.68 | AO12: 2116 | AP12: 1207.49 | AR12: 10589751 | AS12: 8554300 | AT12: 1836480.5 | AU12: 198971 | AV12: 8753271 | AW12: 5556 | AX12: 1540.65 | AY12: 1615 | AZ12: 1307.1 | BB12: 6592019.9 | BC12: 3214963.8 | BD12: 2758945.2 | BE12: 618111 | BF12: 3833074.8 | BG12: 3752 | BH12: 857.87 | BI12: 2934 | BJ12: 1313.16 | BL12: 269505.12 | BM12: 0 | BN12: 269505.12 | BO12: 0 | BP12: 0 | BQ12: 0 | BR12: 512 | BS12: 526.38 | BU12: 331673.28 | BV12: 875 | BW12: 99092.53 | BX12: 231705.75 | BY12: 232580.75 | BZ12: 0 | CA12: 0 | CB12: 172 | CC12: 647.66 | CE12: 639315.59 | CF12: 0 | CG12: 362322.67 | CH12: 276992.92 | CI12: 276992.92 | CJ12: 0 | CK12: 0 | CL12: 1054 | CM12: 557.42 | CO12: 574735.73 | CP12: 0 | CQ12: 574735.73 | CR12: 0 | CS12: 0 | CT12: 0 | CU12: 0 | CV12: 1065 | CW12: 539.66 | DH12: 15413399 | DI12: 14836050 | DJ12: 432879 | DK12: 144470 | DL12: 14980520 | DM12: 4880 | DN12: 3041.17 | DO12: 328 | DP12: 1621.27 | DR12: 414393.84 | DS12: 0 | DT12: 380658.84 | DU12: 33735 | DV12: 33735 | DW12: 0 | DX12: 0 | DY12: 408 | DZ12: 968.6
B13: Total Covers (Dine-in) | M13: ='Mg St LP'!D6 -> 4432 | N13: ='Mg St LP'!#REF! -> #ERROR! | X13: 45717 | Y13: 52065361 | Z13: 39668071 | AA13: 10366867 | AB13: 2030423.3 | AC13: 22339 | AD13: 1776.73 | AE13: 11503 | AF13: 1089.99 | AH13: 13828343.92 | AI13: 10913157.50 | AJ13: 2652789.92 | AK13: 262396.50 | AL13: 11175554 | AM13: 6514.00 | AN13: 1676.34 | AO13: 2436 | AP13: 1243.69 | AR13: 11527193 | AS13: 9107859.5 | AT13: 2136801.3 | AU13: 282532 | AV13: 9390391.5 | AW13: 5839 | AX13: 1560.83 | AY13: 1862 | AZ13: 1313.34 | BB13: 8007527.5 | BC13: 4084209.5 | BD13: 3200802.5 | BE13: 722515.5 | BF13: 4806725 | BG13: 4566 | BH13: 895.48 | BI13: 3335 | BJ13: 1329.79 | BL13: 236942.03 | BM13: 0 | BN13: 236942.03 | BO13: 0 | BP13: 0 | BQ13: 0 | BR13: 466 | BS13: 508.46 | BU13: 349931.53 | BV13: 0 | BW13: 71962.53 | BX13: 277969 | BY13: 277969 | BZ13: 0 | CA13: 0 | CB13: 166 | CC13: 525.27 | CE13: 640732.34 | CF13: 0 | CG13: 335894.56 | CH13: 304837.78 | CI13: 304837.78 | CJ13: 0 | CK13: 0 | CL13: 1074 | CM13: 515.18 | CO13: 629526.63 | CP13: 0 | CQ13: 629526.63 | CR13: 0 | CS13: 0 | CT13: 0 | CU13: 0 | CV13: 1194 | CW13: 527.24 | DH13: 16141898 | DI13: 15562844 | DJ13: 461254 | DK13: 117800 | DL13: 15680644 | DM13: 5420 | DN13: 2872.37 | DO13: 338 | DP13: 1574.25 | DR13: 703266.32 | DS13: 0 | DT13: 640893.82 | DU13: 62372.5 | DV13: 62372.5 | DW13: 0 | DX13: 0 | DY13: 632 | DZ13: 1064.61
B14: Total Delivery Orders (Swiggy, Zomato +) | M14: ='Mg St LP'!D7 -> 2983 | N14: ='Mg St LP'!#REF! -> #ERROR! | X14: 45748 | Y14: 52095941 | Z14: 40631145 | AA14: 9610200.5 | AB14: 1854596.1 | AC14: 21929 | AD14: 1853.85 | AE14: 10600 | AF14: 1108.19 | AH14: 15361003.06 | AI14: 12580908.00 | AJ14: 2496683.06 | AK14: 283412.00 | AL14: 12864320 | AM14: 7363.00 | AN14: 1709.67 | AO14: 2241 | AP14: 1284.96 | AR14: 11274555 | AS14: 9021174.2 | AT14: 2026403.3 | AU14: 226977 | AV14: 9248151.2 | AW14: 5434 | AX14: 1661.14 | AY14: 1706 | AZ14: 1323.58 | BB14: 7799625.9 | BC14: 4119225 | BD14: 3003393.4 | BE14: 677007.5 | BF14: 4796232.5 | BG14: 4432 | BH14: 930.43 | BI14: 2983 | BJ14: 1408.06 | BL14: 210736.64 | BM14: 0 | BN14: 210736.64 | BO14: 0 | BP14: 0 | BQ14: 0 | BR14: 419 | BS14: 502.95 | BU14: 285064.01 | BV14: 0 | BW14: 68163.01 | BX14: 216901 | BY14: 216901 | BZ14: 0 | CA14: 0 | CB14: 159 | CC14: 532.52 | CE14: 671198.18 | CF14: 0 | CG14: 343309.62 | CH14: 327888.56 | CI14: 327888.56 | CJ14: 0 | CK14: 0 | CL14: 1147 | CM14: 533.92 | CO14: 521785.14 | CP14: 0 | CQ14: 521785.14 | CR14: 0 | CS14: 0 | CT14: 0 | CU14: 0 | CV14: 1015 | CW14: 514.07 | CY14: 44479.59 | CZ14: 0 | DA14: 44479.59 | DB14: 0 | DC14: 0 | DD14: 0 | DE14: 83 | DF14: 535.9 | DH14: 15494880 | DI14: 14909837 | DJ14: 486848 | DK14: 98195 | DL14: 15008032 | DM14: 4700 | DN14: 3173.31 | DO14: 348 | DP14: 1606.76 | DR14: 432613.72 | DS14: 0 | DT14: 408398.72 | DU14: 24215 | DV14: 24215 | DW14: 0 | DX14: 0 | DY14: 499 | DZ14: 861.6
B15: Total Revenue - (Dine-in +Takeaway) | M15: ='Mg St LP'!D8 -> 4144195 | N15: ='Mg St LP'!#REF! -> #ERROR! | X15: 45778 | Y15: 54872940 | Z15: 41502148 | AA15: 11552515 | AB15: 1818276.6 | AC15: 22639 | AD15: 1834.21 | AE15: 13029 | AF15: 1030.46 | AH15: 16059929.84 | AI15: 12748872.00 | AJ15: 2990357.84 | AK15: 320700.00 | AL15: 13069572 | AM15: 7332.00 | AN15: 1739.80 | AO15: 2613 | AP15: 1303.56 | AR15: 11931117 | AS15: 9415520.2 | AT15: 2359371 | AU15: 156226 | AV15: 9571746.2 | AW15: 5738 | AX15: 1641.91 | AY15: 1956 | AZ15: 1297.07 | BB15: 8814733.8 | BC15: 4677508 | BD15: 3496559.8 | BE15: 640666 | BF15: 5318174 | BG15: 4850 | BH15: 965.43 | BI15: 3547 | BJ15: 1303.71 | BL15: 269945.41 | BM15: 0 | BN15: 269945.41 | BO15: 0 | BP15: 0 | BQ15: 0 | BR15: 599 | BS15: 450.66 | BU15: 333501.82 | BV15: 0 | BW15: 103864.57 | BX15: 229637.25 | BY15: 229637.25 | BZ15: 0 | CA15: 0 | CB15: 248 | CC15: 487.63 | CE15: 670011.57 | CF15: 0 | CG15: 401899.2 | CH15: 268112.37 | CI15: 268112.37 | CJ15: 0 | CK15: 0 | CL15: 1154 | CM15: 521.27 | CO15: 610855.05 | CP15: 0 | CQ15: 610855.05 | CR15: 0 | CS15: 0 | CT15: 0 | CU15: 0 | CV15: 1203 | CW15: 507.78 | CY15: 404859.4 | CZ15: 0 | DA15: 404859.4 | DB15: 0 | DC15: 0 | DD15: 0 | DE15: 859 | DF15: 471.31 | DH15: 15236383 | DI15: 14660248 | DJ15: 444905 | DK15: 131230 | DL15: 14791478 | DM15: 4719 | DN15: 3107.64 | DO15: 349 | DP15: 1508.15 | DR15: 541603.11 | DS15: 0 | DT15: 469898.11 | DU15: 71705 | DV15: 71705 | DW15: 0 | DX15: 0 | DY15: 501 | DZ15: 987.18
B16: Total Revenue - (Delivery) | M16: ='Mg St LP'!D9 -> 5688107.9 | N16: ='Mg St LP'!#REF! -> #ERROR!
B17: Total Check | M17: ='Mg St LP'!D10 -> -1.8626451e-09 | N17: ='Mg St LP'!#REF! -> #ERROR! | AN17: =(AN15-AN4)/AN4 -> 0.16638286 | AP17: =(AP15-AP4)/AP4 -> -0.052783026 | AX17: =(AX15-AX4)/AX4 -> 0.11442864 | AZ17: =(AZ15-AZ4)/AZ4 -> -0.091153059 | BH17: =(BH15-BH4)/BH4 -> 0.055333894 | BJ17: =(BJ15-BJ4)/BJ4 -> -0.11739139
B18: AOV (Dine-in) | M18: ='Mg St LP'!D11 -> 935.06206 | N18: ='Mg St LP'!#REF! -> #ERROR!
B19: AOV (Delivery) | M19: ='Mg St LP'!D12 -> 1906.8414 | N19: ='Mg St LP'!#REF! -> #ERROR!
B21: Mg St Cafe - Bandra | C21: 45444 | D21: 45474 | E21: 45505 | F21: Sept 2024 | G21: 45566 | H21: 45597 | I21: 45627 | J21: 45658 | K21: 45689 | L21: 45717 | M21: 45748 | N21: 45778
B22: Total Covers (Dine-in) | C22: 7526 | D22: 7144 | E22: 7634 | F22: 6608 | G22: 6633 | H22: 6458 | I22: 7370 | J22: 6551 | K22: 5823 | L22: 6514 | M22: ='Mg St Bandra'!D6 -> 7363 | N22: ='Mg St Bandra'!#REF! -> #ERROR!
B23: Total Delivery Orders (Swiggy, Zomato +) | C23: 1229 | D23: 1332 | E23: 1601 | F23: 1772 | G23: 1837 | H23: 1962 | I23: 2057 | J23: 1952 | K23: 2116 | L23: 2436 | M23: ='Mg St Bandra'!D7 -> 2241 | N23: ='Mg St Bandra'!#REF! -> #ERROR!
B24: Total Revenue - (Dine-in +Takeaway) | C24: 11465781 | D24: 10849598 | E24: 12320674 | F24: 11452240 | G24: 11512022 | H24: 11022448 | I24: 12872772 | J24: 11443320 | K24: 9878764 | L24: 11175554 | M24: 12864320 | N24: 13069572
B25: Total Revenue - (Delivery) | C25: 1314270 | D25: 1431076 | E25: 1645414 | F25: 1977000 | G25: 1984707.1 | H25: 2039306.9 | I25: 2151840.7 | J25: 2056592.6 | K25: 2163821.2 | L25: 2652789.9 | M25: 2496683.1 | N25: 2990357.8
B26: Total Check | M26: ='Mg St Bandra'!D10 -> 0 | N26: ='Mg St Bandra'!#REF! -> #ERROR!
B27: AOV (Dine-in) | C27: =C24/C22 -> 1523.4893 | D27: =D24/D22 -> 1518.7008 | E27: =E24/E22 -> 1613.9212 | F27: =F24/F22 -> 1733.0872 | G27: =G24/G22 -> 1735.5678 | H27: =H24/H22 -> 1706.7898 | I27: =I24/I22 -> 1746.6448 | J27: =J24/J22 -> 1746.805 | ... L27: =L24/L22 -> 1715.6208 | M27: ='Mg St Bandra'!D11 -> 1689.7525 | N27: ='Mg St Bandra'!#REF! -> #ERROR!
B28: AOV (Delivery) | C28: =C25/C23 -> 1069.3816 | D28: =D25/D23 -> 1074.3814 | E28: =E25/E23 -> 1027.7414 | F28: =F25/F23 -> 1115.6885 | G28: =G25/G23 -> 1080.4067 | H28: =H25/H23 -> 1039.4021 | I28: =I25/I23 -> 1046.1063 | J28: =J25/J23 -> 1053.5823 | ... L28: =L25/L23 -> 1088.9942 | M28: ='Mg St Bandra'!D12 -> 2188.5378 | N28: ='Mg St Bandra'!#REF! -> #ERROR!
B30: The Table | M30: 45748 | N30: 45778
B31: Total Covers (Dine-in) | M31: ='The Table'!D6 -> 4700 | N31: ='The Table'!#REF! -> #ERROR!
B32: Total Delivery Orders (Swiggy, Zomato +) | M32: ='The Table'!D7 -> 348 | N32: ='The Table'!#REF! -> #ERROR!
B33: Total Revenue - (Dine-in +Takeaway) | M33: ='The Table'!D8 -> 19734168 | N33: ='The Table'!#REF! -> #ERROR!
B34: Total Revenue - (Delivery) | M34: ='The Table'!D9 -> 792545.26 | N34: ='The Table'!#REF! -> #ERROR!
B35: Total Check | M35: ='The Table'!D10 -> 3.7252903e-09 | N35: ='The Table'!#REF! -> #ERROR!
B36: APC (Dine-in) | M36: ='The Table'!D11 -> 4198.7591 | N36: ='The Table'!#REF! -> #ERROR!
B37: AOV (Delivery) | M37: ='The Table'!D12 -> 2277.4289 | N37: ='The Table'!#REF! -> #ERROR!
N40: =6%*(N33+N34) -> #ERROR!

Sheet Summary Sheet - June 2026
A1: FY26-27 Budgeted vs Actual MIS | AE1: =AE12/$K$12 -> #DIV/0! | BC1: c | BG1: c
A2: Food Matters Group
C3: Total with HO | G3: HO | K3: Outlets Total | O3: Table Total | S3: Iktara | W3: Mg St Colaba | AA3: Mg St LP | AE3: Mg St Bandra | AI3: MSK Events | AM3: MSBC | AQ3: Kaspers | AU3: MSBC Andheri | AY3: MSBC Dahisar | BC3: MSBC Juhu / Goregaon | BG3: Loud Mouth
C4: Actual | D4: %age | E4: Budgeted | F4: %age | G4: Actual | H4: %age | I4: Budgeted | J4: %age | K4: Actual | L4: %age | M4: Budgeted | N4: %age | O4: Actual | P4: %age | Q4: Budgeted | R4: %age | S4: Actual | T4: %age | U4: Budgeted | V4: %age | W4: Actual | X4: %age | Y4: Budgeted | Z4: %age | AA4: Actual | AB4: %age | AC4: Budgeted | AD4: %age | AE4: Actual | AF4: %age | AG4: Budgeted | AH4: %age | AI4: Actual | AJ4: %age | AK4: Budgeted | AL4: %age | AM4: Actual | AN4: %age | AO4: Budgeted | AP4: %age | AQ4: Actual | AR4: %age | AS4: Budgeted | AT4: %age | AU4: Amount | AV4: %age | AW4: Budgeted | AX4: %age | AY4: Amount | AZ4: %age | BA4: Budgeted | BB4: %age | BC4: Amount | BD4: %age | BE4: Budgeted | BF4: %age | BG4: Amount | BH4: %age | BI4: Budgeted | BJ4: %age
B5: Beverage | C5: =G5+K5 -> 0 | D5: =C5/C$10 -> #DIV/0! | E5: =I5+M5 -> 0 | F5: =E5/E$10 -> #DIV/0! | G5: =HO!P14 -> 0 | I5: =HO!R14 | K5: =O5+S5+W5+AA5+AE5+AI5+AM5+AQ5+AU5+AY5+BC5+BG5 -> 0 | L5: =K5/K$10 -> #DIV/0! | M5: =Q5+U5+Y5+AC5+AG5+AK5+AO5+AS5+AW5+BA5+BE5+BI5 -> 0 | N5: =M5/M$10 -> #DIV/0! | O5: ='The Table'!P24 | P5: =O5/O$10 -> #DIV/0! | Q5: ='The Table'!R24 | R5: =Q5/Q$10 -> #DIV/0! | S5: =Iktara!P24 | T5: =S5/S$10 -> #DIV/0! | U5: =Iktara!R24 | V5: =U5/U$10 -> #DIV/0! | W5: ='Mg St Colaba'!P24 | X5: =W5/W$10 -> #DIV/0! | Y5: ='Mg St Colaba'!R24 | Z5: =Y5/Y$10 -> #DIV/0! | AA5: ='Mg St LP'!P24 | AB5: =AA5/AA$10 -> #DIV/0! | AC5: ='Mg St LP'!R24 | AD5: =AC5/AC$10 -> #DIV/0! | AE5: ='Mg St Bandra'!P24 | AF5: =AE5/AE$10 -> #DIV/0! | AG5: ='Mg St Bandra'!R24 | AH5: =AG5/AG$10 -> #DIV/0! | AI5: ='MSK Events'!P24 | AJ5: =AI5/AI$10 -> #DIV/0! | AK5: ='MSK Events'!R24 | AM5: =MSBC!P24 | AN5: =AM5/AM$10 -> #DIV/0! | AO5: =MSBC!R24 -> 0 | AP5: =AO5/AO$10 -> #DIV/0! | AQ5: =Kaspers!P24 | AS5: =Kaspers!R24 | AU5: ='MSBC Andheri'!P24 -> 0 | AW5: ='MSBC Andheri'!R24 | AY5: ='MSBC Dahisar'!P22 | BA5: ='MSBC Dahisar'!R22 | BC5: ='MSBC Juhu Goregoan'!P22 | BE5: ='MSBC Juhu Goregoan'!R22 -> 0 | BG5: ='LOUD MOUTH'!P24 | BI5: ='LOUD MOUTH'!R24
B6: Liquor | C6: =G6+K6 -> 0 | D6: =C6/C$10 -> #DIV/0! | E6: =I6+M6 -> 0 | F6: =E6/E$10 -> #DIV/0! | G6: =HO!P15 -> 0 | I6: =HO!R15 | K6: =O6+S6+W6+AA6+AE6+AI6+AM6+AQ6+AU6+AY6+BC6+BG6 -> 0 | L6: =K6/K$10 -> #DIV/0! | M6: =Q6+U6+Y6+AC6+AG6+AK6+AO6+AS6+AW6+BA6+BE6+BI6 -> 0 | N6: =M6/M$10 -> #DIV/0! | O6: ='The Table'!P25 | P6: =O6/O$10 -> #DIV/0! | Q6: ='The Table'!R25 | R6: =Q6/Q$10 -> #DIV/0! | S6: =Iktara!P25 | T6: =S6/S$10 -> #DIV/0! | U6: =Iktara!R25 | V6: =U6/U$10 -> #DIV/0! | W6: ='Mg St Colaba'!P25 | X6: =W6/W$10 -> #DIV/0! | Y6: ='Mg St Colaba'!R25 | Z6: =Y6/Y$10 -> #DIV/0! | AA6: ='Mg St LP'!P25 | AB6: =AA6/AA$10 -> #DIV/0! | AC6: ='Mg St LP'!R25 | AD6: =AC6/AC$10 -> #DIV/0! | AE6: ='Mg St Bandra'!P25 | AF6: =AE6/AE$10 -> #DIV/0! | AG6: ='Mg St Bandra'!R25 | AH6: =AG6/AG$10 -> #DIV/0! | AI6: ='MSK Events'!P25 | AJ6: =AI6/AI$10 -> #DIV/0! | AK6: ='MSK Events'!R25 | AM6: =MSBC!P25 | AN6: =AM6/AM$10 -> #DIV/0! | AO6: =MSBC!R25 -> 0 | AP6: =AO6/AO$10 -> #DIV/0! | AQ6: =Kaspers!P25 | AS6: =Kaspers!R25 | AU6: ='MSBC Andheri'!P25 -> 0 | AW6: ='MSBC Andheri'!R25 | AY6: ='MSBC Dahisar'!P23 | BA6: ='MSBC Dahisar'!R23 | BC6: ='MSBC Juhu Goregoan'!P23 | BE6: ='MSBC Juhu Goregoan'!R23 -> 0 | BG6: ='LOUD MOUTH'!P25 | BI6: ='LOUD MOUTH'!R25
B7: Food | C7: =G7+K7 -> 0 | D7: =C7/C$10 -> #DIV/0! | E7: =I7+M7 -> 0 | F7: =E7/E$10 -> #DIV/0! | G7: =HO!P16 -> 0 | I7: =HO!R16 | K7: =O7+S7+W7+AA7+AE7+AI7+AM7+AQ7+AU7+AY7+BC7+BG7 -> 0 | L7: =K7/K$10 -> #DIV/0! | M7: =Q7+U7+Y7+AC7+AG7+AK7+AO7+AS7+AW7+BA7+BE7+BI7 -> 0 | N7: =M7/M$10 -> #DIV/0! | O7: ='The Table'!P26 | P7: =O7/O$10 -> #DIV/0! | Q7: ='The Table'!R26 | R7: =Q7/Q$10 -> #DIV/0! | S7: =Iktara!P26 | T7: =S7/S$10 -> #DIV/0! | U7: =Iktara!R26 | V7: =U7/U$10 -> #DIV/0! | W7: ='Mg St Colaba'!P26 | X7: =W7/W$10 -> #DIV/0! | Y7: ='Mg St Colaba'!R26 | Z7: =Y7/Y$10 -> #DIV/0! | AA7: ='Mg St LP'!P26 | AB7: =AA7/AA$10 -> #DIV/0! | AC7: ='Mg St LP'!R26 | AD7: =AC7/AC$10 -> #DIV/0! | AE7: ='Mg St Bandra'!P26 | AF7: =AE7/AE$10 -> #DIV/0! | AG7: ='Mg St Bandra'!R26 | AH7: =AG7/AG$10 -> #DIV/0! | AI7: ='MSK Events'!P26 | AJ7: =AI7/AI$10 -> #DIV/0! | AK7: ='MSK Events'!R26 | AM7: =MSBC!P26 | AN7: =AM7/AM$10 -> #DIV/0! | AO7: =MSBC!R26 -> 0 | AP7: =AO7/AO$10 -> #DIV/0! | AQ7: =Kaspers!P26 | AS7: =Kaspers!R26 -> 0 | AU7: ='MSBC Andheri'!P26 -> 0 | AW7: ='MSBC Andheri'!R26 | AY7: ='MSBC Dahisar'!P24 | BA7: ='MSBC Dahisar'!R24 | BC7: ='MSBC Juhu Goregoan'!P24 | BE7: ='MSBC Juhu Goregoan'!R24 -> 0 | BG7: ='LOUD MOUTH'!P26 -> 0 | BI7: ='LOUD MOUTH'!R26
B8: Service Charge | C8: =G8+K8 -> 0 | D8: =C8/C$10 -> #DIV/0! | E8: =I8+M8 -> 0 | F8: =E8/E$10 -> #DIV/0! | G8: =HO!P18 -> 0 | I8: =HO!R18 | K8: =O8+S8+W8+AA8+AE8+AI8+AM8+AQ8+AU8+AY8+BC8+BG8 -> 0 | L8: =K8/K$10 -> #DIV/0! | M8: =Q8+U8+Y8+AC8+AG8+AK8+AO8+AS8+AW8+BA8+BE8+BI8 -> 0 | N8: =M8/M$10 -> #DIV/0! | O8: ='The Table'!P28 | P8: =O8/O$10 -> #DIV/0! | Q8: ='The Table'!R28 | R8: =Q8/Q$10 -> #DIV/0! | S8: =Iktara!P28 | T8: =S8/S$10 -> #DIV/0! | U8: =Iktara!R28 -> 0 | V8: =U8/U$10 -> #DIV/0! | W8: ='Mg St Colaba'!P27 | X8: =W8/W$10 -> #DIV/0! | Y8: ='Mg St Colaba'!R27 | Z8: =Y8/Y$10 -> #DIV/0! | AA8: ='Mg St LP'!P28 | AB8: =AA8/AA$10 -> #DIV/0! | AC8: ='Mg St LP'!R28 | AD8: =AC8/AC$10 -> #DIV/0! | AE8: ='Mg St Bandra'!P28 | AF8: =AE8/AE$10 -> #DIV/0! | AG8: ='Mg St Bandra'!R28 -> 0 | AH8: =AG8/AG$10 -> #DIV/0! | AI8: ='MSK Events'!P28 | AJ8: =AI8/AI$10 -> #DIV/0! | AK8: ='MSK Events'!R28 | AM8: =MSBC!P28 | AN8: =AM8/AM$10 -> #DIV/0! | AO8: =MSBC!R28 | AP8: =AO8/AO$10 -> #DIV/0! | AQ8: =Kaspers!P28 | AS8: =Kaspers!R28 | AU8: ='MSBC Andheri'!P28 | AW8: ='MSBC Andheri'!R28 | AY8: ='MSBC Dahisar'!P25 | BG8: ='LOUD MOUTH'!P28 | BI8: ='LOUD MOUTH'!R28
B9: Other revenue | C9: =G9+K9 -> 0 | D9: =C9/C$10 -> #DIV/0! | E9: =I9+M9 -> 0 | F9: =E9/E$10 -> #DIV/0! | K9: =O9+S9+W9+AA9+AE9+AI9+AM9+AQ9+AU9+AY9+BC9+BG9 -> 0 | L9: =K9/K$10 -> #DIV/0! | M9: =Q9+U9+Y9+AC9+AG9+AK9+AO9+AS9+AW9+BA9+BE9+BI9 -> 0 | N9: =M9/M$10 -> #DIV/0! | O9: ='The Table'!P22 | Q9: ='The Table'!R22 | S9: =Iktara!P22 | U9: =Iktara!R22 | W9: ='Mg St Colaba'!P22 | Y9: ='Mg St Colaba'!R22 | AA9: ='Mg St LP'!P22 | AC9: ='Mg St LP'!R22 | AE9: ='Mg St Bandra'!P22 | AG9: ='Mg St Bandra'!R22 | AI9: ='MSK Events'!P22 | AK9: ='MSK Events'!R22 | AM9: =MSBC!P22 | AO9: =MSBC!R22 | AQ9: =Kaspers!P22 | AS9: =Kaspers!R22 | AU9: ='MSBC Andheri'!P22 | AW9: ='MSBC Andheri'!R22 | AY9: ='MSBC Dahisar'!P20 | BA9: ='MSBC Dahisar'!R20 | BC9: ='MSBC Juhu Goregoan'!P20 | BE9: ='MSBC Juhu Goregoan'!R20 | BG9: ='LOUD MOUTH'!P22 | BI9: ='LOUD MOUTH'!R22
B10: Total Sales Revenue | C10: =SUM(C5:C9) -> 0 | D10: =C10/C$10 -> #DIV/0! | E10: =SUM(E5:E9) -> 0 | F10: =E10/E$10 -> #DIV/0! | G10: =SUM(G5:G9) -> 0 | I10: =SUM(I5:I9) -> 0 | K10: =SUM(K5:K9) -> 0 | L10: =K10/K$10 -> #DIV/0! | M10: =SUM(M5:M9) -> 0 | N10: =M10/M$10 -> #DIV/0! | O10: =SUM(O5:O9) -> 0 | Q10: =SUM(Q5:Q9) -> 0 | S10: =SUM(S5:S9) -> 0 | U10: =SUM(U5:U9) -> 0 | W10: =SUM(W5:W9) -> 0 | Y10: =SUM(Y5:Y9) -> 0 | AA10: =SUM(AA5:AA9) -> 0 | AC10: =SUM(AC5:AC9) -> 0 | AE10: =SUM(AE5:AE9) -> 0 | AG10: =SUM(AG5:AG9) -> 0 | AI10: =SUM(AI5:AI9) -> 0 | AK10: =SUM(AK5:AK9) -> 0 | AM10: =SUM(AM5:AM9) -> 0 | AO10: =SUM(AO5:AO9) -> 0 | AQ10: =SUM(AQ5:AQ9) -> 0 | AS10: =SUM(AS5:AS9) -> 0 | AU10: =SUM(AU5:AU9) -> 0 | AW10: =SUM(AW5:AW9) -> 0 | AY10: =SUM(AY5:AY9) -> 0 | BA10: =SUM(BA5:BA9) -> 0 | BC10: =SUM(BC5:BC9) -> 0 | BE10: =SUM(BE5:BE9) -> 0 | BG10: =SUM(BG5:BG9) -> 0 | BI10: =SUM(BI5:BI9) -> 0
B12: COGS | C12: =G12+K12 -> 0 | D12: =C12/C$10 -> #DIV/0! | E12: =I12+M12 -> 0 | F12: =E12/E$10 -> #DIV/0! | G12: =HO!P32 -> 0 | I12: =HO!R32 | K12: =O12+S12+W12+AA12+AE12+AI12+AM12+AQ12+AU12+AY12+BC12+BG12 -> 0 | L12: =K12/K$10 -> #DIV/0! | M12: =Q12+U12+Y12+AC12+AG12+AK12+AO12+AS12+AW12+BA12+BE12+BI12 -> 0 | N12: =M12/M$10 -> #DIV/0! | O12: ='The Table'!P39 -> 0 | P12: =O12/O$10 -> #DIV/0! | Q12: ='The Table'!R39 -> 0 | R12: =Q12/Q$10 -> #DIV/0! | S12: =Iktara!P40 -> 0 | T12: =S12/S$10 -> #DIV/0! | U12: =Iktara!R40 -> 0 | V12: =U12/U$10 -> #DIV/0! | W12: ='Mg St Colaba'!P47 -> 0 | X12: =W12/W$10 -> #DIV/0! | Y12: ='Mg St Colaba'!R47 | Z12: =Y12/Y$10 -> #DIV/0! | AA12: ='Mg St LP'!P49 -> 0 | AB12: =AA12/AA$10 -> #DIV/0! | AC12: ='Mg St LP'!R49 | AD12: =AC12/AC$10 -> #DIV/0! | AE12: ='Mg St Bandra'!P47 -> 0 | AF12: =AE12/AE$10 -> #DIV/0! | AG12: ='Mg St Bandra'!R47 -> 0 | AH12: =AG12/AG$10 -> #DIV/0! | AI12: ='MSK Events'!P47 -> 0 | AJ12: =AI12/AI$10 -> #DIV/0! | AK12: ='MSK Events'!R47 -> 0 | AM12: =MSBC!P47 -> 0 | AO12: =MSBC!R47 -> 0 | AQ12: =Kaspers!P47 -> 0 | AS12: =Kaspers!R47 -> 0 | AU12: ='MSBC Andheri'!P46 | AW12: ='MSBC Andheri'!R46 -> 0 | AY12: ='MSBC Dahisar'!P44 | BA12: ='MSBC Dahisar'!R44 -> 0 | BC12: ='MSBC Juhu Goregoan'!P37 | BE12: ='MSBC Juhu Goregoan'!R37 -> 0 | BG12: ='LOUD MOUTH'!P39 -> 0 | BI12: ='LOUD MOUTH'!R39
B13: Packaging Cost | C13: =G13+K13 -> 0 | D13: =C13/C$10 -> #DIV/0! | E13: =I13+M13 -> 0 | F13: =E13/E$10 -> #DIV/0! | G13: =HO!P33 | I13: =HO!R33 | K13: =O13+S13+W13+AA13+AE13+AI13+AM13+AQ13+AU13+AY13+BC13+BG13 -> 0 | L13: =K13/K$10 -> #DIV/0! | M13: =Q13+U13+Y13+AC13+AG13+AK13+AO13+AS13+AW13+BA13+BE13+BI13 -> 0 | N13: =M13/M$10 -> #DIV/0! | O13: ='The Table'!P40 | P13: =O13/O$10 -> #DIV/0! | Q13: ='The Table'!R40 -> 0 | R13: =Q13/Q$10 -> #DIV/0! | S13: =Iktara!P41 | T13: =S13/S$10 -> #DIV/0! | U13: =Iktara!R41 | V13: =U13/U$10 -> #DIV/0! | W13: ='Mg St Colaba'!P48 | X13: =W13/W$10 -> #DIV/0! | Y13: ='Mg St Colaba'!R48 | Z13: =Y13/Y$10 -> #DIV/0! | AA13: ='Mg St LP'!P50 | AB13: =AA13/AA$10 -> #DIV/0! | AC13: ='Mg St LP'!R50 | AD13: =AC13/AC$10 -> #DIV/0! | AE13: ='Mg St Bandra'!P48 | AF13: =AE13/AE$10 -> #DIV/0! | AG13: ='Mg St Bandra'!R48 | AH13: =AG13/AG$10 -> #DIV/0! | AI13: ='MSK Events'!P48 | AK13: ='MSK Events'!R48 | AM13: =MSBC!P48 | AO13: =MSBC!R48 | AQ13: =Kaspers!P48 | AS13: =Kaspers!R48 -> 0 | AU13: ='MSBC Andheri'!P47 | AW13: ='MSBC Andheri'!R47 | AY13: ='MSBC Dahisar'!P45 | BA13: ='MSBC Dahisar'!R45 | BC13: ='MSBC Juhu Goregoan'!P38 | BE13: ='MSBC Juhu Goregoan'!R38 | BG13: ='LOUD MOUTH'!P40 | BI13: ='LOUD MOUTH'!R40
B14: NC & DQ | C14: =G14+K14 -> 0 | D14: =C14/C$10 -> #DIV/0! | K14: =O14+S14+W14+AA14+AE14+AI14+AM14+AQ14+AU14+AY14+BC14+BG14 -> 0 | M14: =Q14+U14+Y14+AC14+AG14+AK14+AO14+AS14+AW14+BA14+BE14+BI14 -> 0
B15: Total COGS & Packaging | C15: =SUM(C12:C14) -> 0 | D15: =SUM(D12:D14) -> #DIV/0! | E15: =SUM(E12:E14) -> 0 | F15: =SUM(F12:F14) -> #DIV/0! | G15: =SUM(G12:G14) -> 0 | H15: =SUM(H12:H14) -> 0 | I15: =SUM(I12:I14) -> 0 | J15: =SUM(J12:J14) -> 0 | ... AM15: =SUM(AM12:AM14) -> 0 | AO15: =SUM(AO12:AO14) -> 0 | AQ15: =SUM(AQ12:AQ13) -> 0 | AS15: =SUM(AS12:AS14) -> 0 | AU15: =SUM(AU12:AU14) -> 0 | AV15: =SUM(AV12:AV14) -> 0 | AW15: =SUM(AW12:AW14) -> 0 | AX15: =SUM(AX12:AX14) -> 0 | AY15: =SUM(AY12:AY14) -> 0 | AZ15: =SUM(AZ12:AZ14) -> 0 | BA15: =SUM(BA12:BA14) -> 0 | BB15: =SUM(BB12:BB14) -> 0 | ... BJ15: =SUM(BJ12:BJ14) -> 0
B17: Gross Margin | C17: =C10-C15 -> 0 | D17: =C17/C$10 -> #DIV/0! | E17: =E10-E15 -> 0 | F17: =E17/E$10 -> #DIV/0! | G17: =G10-G15 -> 0 | I17: =I10-I15 -> 0 | K17: =K10-K15 -> 0 | L17: =K17/K$10 -> #DIV/0! | M17: =Q17+U17+Y17+AC17+AG17+AK17+AO17+AS17+AW17+BA17+BE17+BI17 -> 0 | N17: =M17/M$10 -> #DIV/0! | O17: =O10-O15 -> 0 | P17: =O17/O$10 -> #DIV/0! | Q17: =Q10-Q15 -> 0 | R17: =Q17/Q$10 -> #DIV/0! | S17: =S10-S15 -> 0 | T17: =S17/S$10 -> #DIV/0! | U17: =U10-U15 -> 0 | V17: =U17/U$10 -> #DIV/0! | W17: =W10-W15 -> 0 | X17: =W17/W$10 -> #DIV/0! | Y17: =Y10-Y15 -> 0 | Z17: =Y17/Y$10 -> #DIV/0! | AA17: =AA10-AA15 -> 0 | AB17: =AA17/AA$10 -> #DIV/0! | AC17: =AC10-AC15 -> 0 | AD17: =AC17/AC$10 -> #DIV/0! | AE17: =AE10-AE15 -> 0 | AF17: =AE17/AE$10 -> #DIV/0! | AG17: =AG10-AG15 -> 0 | AH17: =AG17/AG$10 -> #DIV/0! | AI17: =AI10-AI15 -> 0 | AJ17: =AI17/AI$10 -> #DIV/0! | AK17: =AK10-AK15 -> 0 | AM17: =AM10-AM15 -> 0 | AO17: =AO10-AO15 -> 0 | AQ17: =AQ10-AQ15 -> 0 | AS17: =AS10-AS15 -> 0 | AU17: =AU10-AU15 -> 0 | AV17: =AV10-AV15 -> 0 | AW17: =AW10-AW15 -> 0 | AX17: =AX10-AX15 -> 0 | AY17: =AY10-AY15 -> 0 | AZ17: =AZ10-AZ15 -> 0 | BA17: =BA10-BA15 -> 0 | BB17: =BB10-BB15 -> 0 | ... BJ17: =BJ10-BJ15 -> 0
B19: Other Direct Expenses | C19: =G19+K19 -> 0 | D19: =C19/C$10 -> #DIV/0! | E19: =I19+M19 -> 0 | F19: =E19/E$10 -> #DIV/0! | G19: =HO!P43 -> 0 | I19: =HO!R43 | K19: =O19+S19+W19+AA19+AE19+AI19+AM19+AQ19+AU19+AY19+BC19+BG19 -> 0 | L19: =K19/K$10 -> #DIV/0! | M19: =Q19+U19+Y19+AC19+AG19+AK19+AO19+AS19+AW19+BA19+BE19+BI19 -> 0 | N19: =M19/M$10 -> #DIV/0! | O19: ='The Table'!P51 -> 0 | P19: =O19/O$10 -> #DIV/0! | Q19: ='The Table'!R51 -> 0 | R19: =Q19/Q$10 -> #DIV/0! | S19: =Iktara!P52 -> 0 | T19: =S19/S$10 -> #DIV/0! | U19: =Iktara!R52 -> 0 | V19: =U19/U$10 -> #DIV/0! | W19: ='Mg St Colaba'!P60 -> 0 | X19: =W19/W$10 -> #DIV/0! | Y19: ='Mg St Colaba'!R60 -> 0 | Z19: =Y19/Y$10 -> #DIV/0! | AA19: ='Mg St LP'!P61 -> 0 | AB19: =AA19/AA$10 -> #DIV/0! | AC19: ='Mg St LP'!R61 -> 0 | AD19: =AC19/AC$10 -> #DIV/0! | AE19: ='Mg St Bandra'!P58 -> 0 | AF19: =AE19/AE$10 -> #DIV/0! | AG19: ='Mg St Bandra'!R58 -> 0 | AH19: =AG19/AG$10 -> #DIV/0! | AI19: ='MSK Events'!P59 -> 0 | AJ19: =AI19/AI$10 -> #DIV/0! | AK19: ='MSK Events'!R59 -> 0 | AL19: =AK19/AK$10 -> #DIV/0! | AM19: =MSBC!P59 -> 0 | AN19: =AM19/AM$10 -> #DIV/0! | AO19: =MSBC!R59 -> 0 | AP19: =AO19/AO$10 -> #DIV/0! | AQ19: =Kaspers!P62 -> 0 | AS19: =Kaspers!R62 -> 0 | AU19: ='MSBC Andheri'!P58 -> 0 | AW19: ='MSBC Andheri'!R58 -> 0 | AY19: ='MSBC Dahisar'!P55 -> 0 | BA19: ='MSBC Dahisar'!R55 -> 0 | BC19: ='MSBC Juhu Goregoan'!P60 -> 0 | BE19: ='MSBC Juhu Goregoan'!R60 -> 0 | BG19: ='LOUD MOUTH'!P51 -> 0 | BI19: ='LOUD MOUTH'!R51 -> 0
B20: Marketing Expenses | C20: =G20+K20 -> 0 | D20: =C20/C$10 -> #DIV/0! | E20: =I20+M20 -> 0 | F20: =E20/E$10 -> #DIV/0! | G20: =HO!P52 -> 0 | I20: =HO!R52 -> 0 | K20: =O20+S20+W20+AA20+AE20+AI20+AM20+AQ20+AU20+AY20+BC20+BG20 -> 0 | L20: =K20/K$10 -> #DIV/0! | M20: =Q20+U20+Y20+AC20+AG20+AK20+AO20+AS20+AW20+BA20+BE20+BI20 -> 0 | N20: =M20/M$10 -> #DIV/0! | O20: ='The Table'!P60 -> 0 | P20: =O20/O$10 -> #DIV/0! | Q20: ='The Table'!R60 -> 0 | R20: =Q20/Q$10 -> #DIV/0! | S20: =Iktara!P54 -> 0 | T20: =S20/S$10 -> #DIV/0! | U20: =Iktara!R54 -> 0 | V20: =U20/U$10 -> #DIV/0! | W20: ='Mg St Colaba'!P69 -> 0 | X20: =W20/W$10 -> #DIV/0! | Y20: ='Mg St Colaba'!R69 -> 0 | Z20: =Y20/Y$10 -> #DIV/0! | AA20: ='Mg St LP'!P70 -> 0 | AB20: =AA20/AA$10 -> #DIV/0! | AC20: ='Mg St LP'!R70 -> 0 | AD20: =AC20/AC$10 -> #DIV/0! | AE20: ='Mg St Bandra'!P70 -> 0 | AF20: =AE20/AE$10 -> #DIV/0! | AG20: ='Mg St Bandra'!R70 -> 0 | AH20: =AG20/AG$10 -> #DIV/0! | AI20: ='MSK Events'!P70 -> 0 | AJ20: =AI20/AI$10 -> #DIV/0! | AK20: ='MSK Events'!R70 -> 0 | AL20: =AK20/AK$10 -> #DIV/0! | AM20: =MSBC!P61 -> 0 | AN20: =AM20/AM$10 -> #DIV/0! | AO20: =MSBC!R61 -> 0 | AP20: =AO20/AO$10 -> #DIV/0! | AQ20: =Kaspers!P65 -> 0 | AS20: =Kaspers!R65 -> 0 | AU20: ='MSBC Andheri'!P70 -> 0 | AW20: ='MSBC Andheri'!R70 -> 0 | AY20: ='MSBC Dahisar'!P57 -> 0 | BA20: ='MSBC Dahisar'!R57 -> 0 | BC20: ='MSBC Juhu Goregoan'!P72 -> 0 | BE20: ='MSBC Juhu Goregoan'!R72 -> 0 | BG20: ='LOUD MOUTH'!P54 -> 0 | BI20: ='LOUD MOUTH'!R54 -> 0
B21: Sales Commission | C21: =G21+K21 -> 0 | D21: =C21/C$10 -> #DIV/0! | E21: =I21+M21 -> #REF! | F21: =E21/E$10 -> #REF! | G21: =HO!P63 -> 0 | I21: =HO!R63 -> 0 | K21: =O21+S21+W21+AA21+AE21+AI21+AM21+AQ21+AU21+AY21+BC21+BG21 -> 0 | L21: =K21/K$10 -> #DIV/0! | M21: =Q21+U21+Y21+AC21+AG21+AK21+AO21+AS21+AW21+BA21+BE21+BI21 -> #REF! | N21: =M21/M$10 -> #REF! | O21: ='The Table'!P69 -> 0 | P21: =O21/O$10 -> #DIV/0! | Q21: ='The Table'!R69 -> 0 | R21: =Q21/Q$10 -> #DIV/0! | S21: =Iktara!P64 -> 0 | T21: =S21/S$10 -> #DIV/0! | U21: =Iktara!R64 | V21: =U21/U$10 -> #DIV/0! | W21: ='Mg St Colaba'!P81 -> 0 | X21: =W21/W$10 -> #DIV/0! | Y21: ='Mg St Colaba'!R81 -> #REF! | Z21: =Y21/Y$10 -> #REF! | AA21: ='Mg St LP'!P83 -> 0 | AB21: =AA21/AA$10 -> #DIV/0! | AC21: ='Mg St LP'!R83 -> 0 | AD21: =AC21/AC$10 -> #DIV/0! | AE21: ='Mg St Bandra'!P81 -> 0 | AF21: =AE21/AE$10 -> #DIV/0! | AG21: ='Mg St Bandra'!R81 -> 0 | AH21: =AG21/AG$10 -> #DIV/0! | AI21: ='MSK Events'!P77 -> 0 | AJ21: =AI21/AI$10 -> #DIV/0! | AK21: ='MSK Events'!R77 -> 0 | AL21: =AK21/AK$10 -> #DIV/0! | AM21: =MSBC!P69 -> 0 | AN21: =AM21/AM$10 -> #DIV/0! | AO21: =MSBC!R69 -> 0 | AP21: =AO21/AO$10 -> #DIV/0! | AQ21: =Kaspers!P73 -> 0 | AS21: =Kaspers!R73 -> 0 | AU21: ='MSBC Andheri'!P78 -> 0 | AW21: ='MSBC Andheri'!R78 -> 0 | AY21: ='MSBC Dahisar'!P65 -> 0 | BA21: ='MSBC Dahisar'!R65 -> 0 | BC21: ='MSBC Juhu Goregoan'!P80 -> 0 | BE21: ='MSBC Juhu Goregoan'!R80 -> 0 | BG21: ='LOUD MOUTH'!P63 -> 0 | BI21: ='LOUD MOUTH'!R63 -> 0
B22: Rental & Utility Expenses | C22: =G22+K22 -> 0 | D22: =C22/C$10 -> #DIV/0! | E22: =I22+M22 -> 0 | F22: =E22/E$10 -> #DIV/0! | G22: =HO!P70 -> 0 | I22: =HO!R70 -> 0 | K22: =O22+S22+W22+AA22+AE22+AI22+AM22+AQ22+AU22+AY22+BC22+BG22 -> 0 | L22: =K22/K$10 -> #DIV/0! | M22: =Q22+U22+Y22+AC22+AG22+AK22+AO22+AS22+AW22+BA22+BE22+BI22 -> 0 | N22: =M22/M$10 -> #DIV/0! | O22: ='The Table'!P75 -> 0 | P22: =O22/O$10 -> #DIV/0! | Q22: ='The Table'!R75 -> 0 | R22: =Q22/Q$10 -> #DIV/0! | S22: =Iktara!P70 -> 0 | T22: =S22/S$10 -> #DIV/0! | U22: =Iktara!R70 | V22: =U22/U$10 -> #DIV/0! | W22: ='Mg St Colaba'!P88 -> 0 | X22: =W22/W$10 -> #DIV/0! | Y22: ='Mg St Colaba'!R88 -> 0 | Z22: =Y22/Y$10 -> #DIV/0! | AA22: ='Mg St LP'!P90 -> 0 | AB22: =AA22/AA$10 -> #DIV/0! | AC22: ='Mg St LP'!R90 -> 0 | AD22: =AC22/AC$10 -> #DIV/0! | AE22: ='Mg St Bandra'!P88 -> 0 | AF22: =AE22/AE$10 -> #DIV/0! | AG22: ='Mg St Bandra'!R88 -> 0 | AH22: =AG22/AG$10 -> #DIV/0! | AI22: ='MSK Events'!P84 -> 0 | AJ22: =AI22/AI$10 -> #DIV/0! | AK22: ='MSK Events'!R84 -> 0 | AL22: =AK22/AK$10 -> #DIV/0! | AM22: =MSBC!P75 -> 0 | AN22: =AM22/AM$10 -> #DIV/0! | AO22: =MSBC!R75 -> 0 | AP22: =AO22/AO$10 -> #DIV/0! | AQ22: =Kaspers!P80 -> 0 | AS22: =Kaspers!R80 -> 0 | AU22: ='MSBC Andheri'!P87 -> 0 | AW22: ='MSBC Andheri'!R87 -> 0 | AY22: ='MSBC Dahisar'!P74 -> 0 | BA22: ='MSBC Dahisar'!R74 -> 0 | BC22: ='MSBC Juhu Goregoan'!P87 -> 0 | BE22: 0 | BG22: ='LOUD MOUTH'!P70 -> 0 | BI22: ='LOUD MOUTH'!R70 -> 0
B23: Salary & Staff Expenses | C23: =G23+K23 -> 0 | D23: =C23/C$10 -> #DIV/0! | E23: =I23+M23 -> 0 | F23: =E23/E$10 -> #DIV/0! | G23: =HO!P76 -> 0 | I23: =HO!R76 -> 0 | K23: =O23+S23+W23+AA23+AE23+AI23+AM23+AQ23+AU23+AY23+BC23+BG23 -> 0 | L23: =K23/K$10 -> #DIV/0! | M23: =Q23+U23+Y23+AC23+AG23+AK23+AO23+AS23+AW23+BA23+BE23+BI23 -> 0 | N23: =M23/M$10 -> #DIV/0! | O23: ='The Table'!P81 -> 0 | P23: =O23/O$10 -> #DIV/0! | Q23: ='The Table'!R81 -> 0 | R23: =Q23/Q$10 -> #DIV/0! | S23: =Iktara!P76 -> 0 | T23: =S23/S$10 -> #DIV/0! | U23: =Iktara!R76 -> 0 | V23: =U23/U$10 -> #DIV/0! | W23: ='Mg St Colaba'!P94 -> 0 | X23: =W23/W$10 -> #DIV/0! | Y23: ='Mg St Colaba'!R94 -> 0 | Z23: =Y23/Y$10 -> #DIV/0! | AA23: ='Mg St LP'!P97 -> 0 | AB23: =AA23/AA$10 -> #DIV/0! | AC23: ='Mg St LP'!R97 -> 0 | AD23: =AC23/AC$10 -> #DIV/0! | AE23: ='Mg St Bandra'!P96 -> 0 | AF23: =AE23/AE$10 -> #DIV/0! | AG23: ='Mg St Bandra'!R96 -> 0 | AH23: =AG23/AG$10 -> #DIV/0! | AI23: ='MSK Events'!P90 -> 0 | AJ23: =AI23/AI$10 -> #DIV/0! | AK23: ='MSK Events'!R90 -> 0 | AL23: =AK23/AK$10 -> #DIV/0! | AM23: =MSBC!P81 -> 0 | AN23: =AM23/AM$10 -> #DIV/0! | AO23: =MSBC!R81 -> 0 | AP23: =AO23/AO$10 -> #DIV/0! | AQ23: =Kaspers!P86 -> 0 | AS23: =Kaspers!R86 -> 0 | AU23: ='MSBC Andheri'!P93 -> 0 | AW23: ='MSBC Andheri'!R93 -> 0 | AY23: ='MSBC Dahisar'!P80 -> 0 | BA23: ='MSBC Dahisar'!R80 -> 0 | BC23: ='MSBC Juhu Goregoan'!P93 -> 0 | BE23: 0 | BG23: ='LOUD MOUTH'!P77 -> 0 | BI23: ='LOUD MOUTH'!R77 -> 0
B24: Bank and Finance Charges | C24: =G24+K24 -> 0 | D24: =C24/C$10 -> #DIV/0! | E24: =I24+M24 -> 0 | F24: =E24/E$10 -> #DIV/0! | G24: =HO!P87 -> 0 | I24: =HO!R87 -> 0 | K24: =O24+S24+W24+AA24+AE24+AI24+AM24+AQ24+AU24+AY24+BC24+BG24 -> 0 | L24: =K24/K$10 -> #DIV/0! | M24: =Q24+U24+Y24+AC24+AG24+AK24+AO24+AS24+AW24+BA24+BE24+BI24 -> 0 | N24: =M24/M$10 -> #DIV/0! | O24: ='The Table'!P92 -> 0 | P24: =O24/O$10 -> #DIV/0! | Q24: ='The Table'!R92 -> 0 | R24: =Q24/Q$10 -> #DIV/0! | S24: =Iktara!P86 -> 0 | T24: =S24/S$10 -> #DIV/0! | U24: =Iktara!R86 -> 0 | V24: =U24/U$10 -> #DIV/0! | W24: ='Mg St Colaba'!P104 -> 0 | X24: =W24/W$10 -> #DIV/0! | Y24: ='Mg St Colaba'!R104 -> 0 | Z24: =Y24/Y$10 -> #DIV/0! | AA24: ='Mg St LP'!P107 -> 0 | AB24: =AA24/AA$10 -> #DIV/0! | AC24: ='Mg St LP'!R107 -> 0 | AD24: =AC24/AC$10 -> #DIV/0! | AE24: ='Mg St Bandra'!P107 -> 0 | AF24: =AE24/AE$10 -> #DIV/0! | AG24: ='Mg St Bandra'!R107 -> 0 | AH24: =AG24/AG$10 -> #DIV/0! | AI24: ='MSK Events'!P100 -> 0 | AJ24: =AI24/AI$10 -> #DIV/0! | AK24: ='MSK Events'!R100 -> 0 | AL24: =AK24/AK$10 -> #DIV/0! | AM24: =MSBC!P92 -> 0 | AN24: =AM24/AM$10 -> #DIV/0! | AO24: =MSBC!R92 -> 0 | AP24: =AO24/AO$10 -> #DIV/0! | AQ24: =Kaspers!P97 -> 0 | AS24: =Kaspers!R97 -> 0 | AU24: ='MSBC Andheri'!P103 -> 0 | AW24: ='MSBC Andheri'!R103 -> 0 | AY24: ='MSBC Dahisar'!P90 -> 0 | BA24: ='MSBC Dahisar'!R90 -> 0 | BC24: ='MSBC Juhu Goregoan'!P103 -> 0 | BE24: ='MSBC Juhu Goregoan'!R103 -> 0 | BG24: ='LOUD MOUTH'!P89 -> 0 | BI24: ='LOUD MOUTH'!R89 -> 0
B25: Software and Subscription | C25: =G25+K25 -> 0 | D25: =C25/C$10 -> #DIV/0! | E25: =I25+M25 -> 0 | F25: =E25/E$10 -> #DIV/0! | G25: =HO!P94 -> 0 | I25: =HO!R94 -> 0 | K25: =O25+S25+W25+AA25+AE25+AI25+AM25+AQ25+AU25+AY25+BC25+BG25 -> 0 | L25: =K25/K$10 -> #DIV/0! | M25: =Q25+U25+Y25+AC25+AG25+AK25+AO25+AS25+AW25+BA25+BE25+BI25 -> 0 | N25: =M25/M$10 -> #DIV/0! | O25: ='The Table'!P95 -> 0 | P25: =O25/O$10 -> #DIV/0! | Q25: ='The Table'!R95 -> 0 | R25: =Q25/Q$10 -> #DIV/0! | S25: =Iktara!P89 -> 0 | T25: =S25/S$10 -> #DIV/0! | U25: =Iktara!R89 -> 0 | V25: =U25/U$10 -> #DIV/0! | W25: ='Mg St Colaba'!P107 -> 0 | X25: =W25/W$10 -> #DIV/0! | Y25: ='Mg St Colaba'!R107 | Z25: =Y25/Y$10 -> #DIV/0! | AA25: ='Mg St LP'!P110 -> 0 | AB25: =AA25/AA$10 -> #DIV/0! | AC25: ='Mg St LP'!R110 -> 0 | AD25: =AC25/AC$10 -> #DIV/0! | AE25: ='Mg St Bandra'!P110 -> 0 | AF25: =AE25/AE$10 -> #DIV/0! | AG25: ='Mg St Bandra'!R110 -> 0 | AH25: =AG25/AG$10 -> #DIV/0! | AI25: ='MSK Events'!P103 -> 0 | AJ25: =AI25/AI$10 -> #DIV/0! | AK25: ='MSK Events'!R103 -> 0 | AL25: =AK25/AK$10 -> #DIV/0! | AM25: =MSBC!P95 -> 0 | AN25: =AM25/AM$10 -> #DIV/0! | AO25: =MSBC!R95 -> 0 | AP25: =AO25/AO$10 -> #DIV/0! | AQ25: =Kaspers!P100 -> 0 | AS25: =Kaspers!R100 -> 0 | AU25: ='MSBC Andheri'!P106 -> 0 | AW25: ='MSBC Andheri'!R106 -> 0 | AY25: ='MSBC Dahisar'!P93 -> 0 | BA25: ='MSBC Dahisar'!R93 -> 0 | BC25: ='MSBC Juhu Goregoan'!P106 -> 0 | BE25: ='MSBC Juhu Goregoan'!R106 -> 0 | BG25: ='LOUD MOUTH'!P92 -> 0 | BI25: ='LOUD MOUTH'!R92 -> 0
B26: Other Outlet Costs | C26: =G26+K26 -> 0 | D26: =C26/C$10 -> #DIV/0! | E26: =I26+M26 -> 0 | F26: =E26/E$10 -> #DIV/0! | G26: =HO!P98 -> 0 | I26: =HO!R98 -> 0 | K26: =O26+S26+W26+AA26+AE26+AI26+AM26+AQ26+AU26+AY26+BC26+BG26 -> 0 | L26: =K26/K$10 -> #DIV/0! | M26: =Q26+U26+Y26+AC26+AG26+AK26+AO26+AS26+AW26+BA26+BE26+BI26 -> 0 | N26: =M26/M$10 -> #DIV/0! | O26: ='The Table'!P99+'The Table'!P106+'The Table'!P112+'The Table'!P114+'The Table'!P116+'The Table'!P118+'The Table'!P120 -> 0 | P26: =O26/O$10 -> #DIV/0! | Q26: ='The Table'!R99+'The Table'!R106+'The Table'!R112+'The Table'!R114+'The Table'!R116+'The Table'!R118+'The Table'!R120 -> 0 | R26: =Q26/Q$10 -> #DIV/0! | S26: =Iktara!P93 -> 0 | T26: =S26/S$10 -> #DIV/0! | U26: =Iktara!R93 -> 0 | V26: =U26/U$10 -> #DIV/0! | W26: ='Mg St Colaba'!P111 -> 0 | X26: =W26/W$10 -> #DIV/0! | Y26: ='Mg St Colaba'!R111 | Z26: =Y26/Y$10 -> #DIV/0! | AA26: ='Mg St LP'!P114 -> 0 | AB26: =AA26/AA$10 -> #DIV/0! | AC26: ='Mg St LP'!R114 -> 0 | AD26: =AC26/AC$10 -> #DIV/0! | AE26: ='Mg St Bandra'!P114 -> 0 | AF26: =AE26/AE$10 -> #DIV/0! | AG26: ='Mg St Bandra'!R114 -> 0 | AH26: =AG26/AG$10 -> #DIV/0! | AI26: ='MSK Events'!P107 -> 0 | AJ26: =AI26/AI$10 -> #DIV/0! | AK26: ='MSK Events'!R107 -> 0 | AL26: =AK26/AK$10 -> #DIV/0! | AM26: =MSBC!P99 -> 0 | AN26: =AM26/AM$10 -> #DIV/0! | AO26: =MSBC!R99 -> 0 | AP26: =AO26/AO$10 -> #DIV/0! | AQ26: =Kaspers!P104 -> 0 | AS26: =Kaspers!R104 -> 0 | AU26: ='MSBC Andheri'!P110 -> 0 | AW26: ='MSBC Andheri'!R110 -> 0 | AY26: ='MSBC Dahisar'!P97 -> 0 | BA26: ='MSBC Dahisar'!R97 -> 0 | BC26: ='MSBC Juhu Goregoan'!P110 -> 0 | BE26: ='MSBC Juhu Goregoan'!R110 -> 0 | BG26: ='LOUD MOUTH'!P96 -> 0 | BI26: ='LOUD MOUTH'!R96 -> 0
B27: Other Professional Fees | C27: =G27+K27 -> 0 | D27: =C27/C$10 -> #DIV/0! | E27: =I27+M27 -> 0 | F27: =E27/E$10 -> #DIV/0! | G27: =HO!P113 -> 0 | I27: =HO!R113 -> 0 | K27: =O27+S27+W27+AA27+AE27+AI27+AM27+AQ27+AU27+AY27+BC27+BG27 -> 0 | L27: =K27/K$10 -> #DIV/0! | M27: =Q27+U27+Y27+AC27+AG27+AK27+AO27+AS27+AW27+BA27+BE27+BI27 -> 0 | N27: =M27/M$10 -> #DIV/0! | O27: ='The Table'!P122 -> 0 | P27: =O27/O$10 -> #DIV/0! | Q27: ='The Table'!R122 -> 0 | R27: =Q27/Q$10 -> #DIV/0! | S27: =Iktara!P106 -> 0 | T27: =S27/S$10 -> #DIV/0! | U27: =Iktara!R106 -> 0 | V27: =U27/U$10 -> #DIV/0! | W27: ='Mg St Colaba'!P127 -> 0 | X27: =W27/W$10 -> #DIV/0! | Y27: ='Mg St Colaba'!R127 | Z27: =Y27/Y$10 -> #DIV/0! | AA27: ='Mg St LP'!P130 -> 0 | AB27: =AA27/AA$10 -> #DIV/0! | AC27: ='Mg St LP'!R130 -> 0 | AD27: =AC27/AC$10 -> #DIV/0! | AE27: ='Mg St Bandra'!P131 -> 0 | AF27: =AE27/AE$10 -> #DIV/0! | AG27: ='Mg St Bandra'!R131 -> 0 | AH27: =AG27/AG$10 -> #DIV/0! | AI27: ='MSK Events'!P125 -> 0 | AJ27: =AI27/AI$10 -> #DIV/0! | AK27: ='MSK Events'!R125 -> 0 | AL27: =AK27/AK$10 -> #DIV/0! | AM27: =MSBC!P115 -> 0 | AN27: =AM27/AM$10 -> #DIV/0! | AO27: =MSBC!R115 -> 0 | AP27: =AO27/AO$10 -> #DIV/0! | AQ27: =Kaspers!P127 -> 0 | AS27: =Kaspers!R127 -> 0 | AU27: ='MSBC Andheri'!P125 -> 0 | AW27: ='MSBC Andheri'!R125 -> 0 | AY27: ='MSBC Dahisar'!P112 -> 0 | BA27: ='MSBC Dahisar'!R112 -> 0 | BC27: ='MSBC Juhu Goregoan'!P125 -> 0 | BE27: ='MSBC Juhu Goregoan'!R125 -> 0 | BG27: ='LOUD MOUTH'!P112 -> 0 | BI27: ='LOUD MOUTH'!R112 -> 0
B28: Other Expenses | C28: =G28+K28 -> 0 | D28: =C28/C$10 -> #DIV/0! | E28: =I28+M28 -> 0 | F28: =E28/E$10 -> #DIV/0! | G28: =HO!P117 -> 0 | I28: =HO!R117 -> 0 | K28: =O28+S28+W28+AA28+AE28+AI28+AM28+AQ28+AU28+AY28+BC28+BG28 -> 0 | L28: =K28/K$10 -> #DIV/0! | M28: =Q28+U28+Y28+AC28+AG28+AK28+AO28+AS28+AW28+BA28+BE28+BI28 -> 0 | N28: =M28/M$10 -> #DIV/0! | O28: ='The Table'!J126 -> 0 | P28: =O28/O$10 -> #DIV/0! | Q28: ='The Table'!L126 -> 0 | R28: =Q28/Q$10 -> #DIV/0! | S28: =Iktara!P110 -> 0 | T28: =S28/S$10 -> #DIV/0! | U28: =Iktara!R110 -> 0 | V28: =U28/U$10 -> #DIV/0! | W28: ='Mg St Colaba'!P131 -> 0 | X28: =W28/W$10 -> #DIV/0! | Y28: ='Mg St Colaba'!R131 | Z28: =Y28/Y$10 -> #DIV/0! | AA28: ='Mg St LP'!P134 -> 0 | AB28: =AA28/AA$10 -> #DIV/0! | AC28: ='Mg St LP'!R134 -> 0 | AD28: =AC28/AC$10 -> #DIV/0! | AE28: ='Mg St Bandra'!P135 -> 0 | AF28: =AE28/AE$10 -> #DIV/0! | AG28: ='Mg St Bandra'!R135 -> 0 | AH28: =AG28/AG$10 -> #DIV/0! | AI28: ='MSK Events'!P129 -> 0 | AJ28: =AI28/AI$10 -> #DIV/0! | AK28: ='MSK Events'!R129 -> 0 | AL28: =AK28/AK$10 -> #DIV/0! | AM28: =MSBC!P119 -> 0 | AN28: =AM28/AM$10 -> #DIV/0! | AO28: =MSBC!R119 -> 0 | AP28: =AO28/AO$10 -> #DIV/0! | AQ28: =Kaspers!P131 -> 0 | AS28: =Kaspers!R131 -> 0 | AU28: ='MSBC Andheri'!P129 -> 0 | AW28: ='MSBC Andheri'!R129 -> 0 | AY28: ='MSBC Dahisar'!P116 -> 0 | BA28: ='MSBC Dahisar'!R116 -> 0 | BC28: ='MSBC Juhu Goregoan'!P129 -> 0 | BE28: ='MSBC Juhu Goregoan'!R129 -> 0 | BG28: ='LOUD MOUTH'!P117 -> 0 | BI28: ='LOUD MOUTH'!R117 -> 0
B29: Total Other Expenses | C29: =SUM(C19:C28) -> 0 | D29: =C29/C$10 -> #DIV/0! | E29: =I29+M29 -> #REF! | F29: =E29/E$10 -> #REF! | G29: =SUM(G19:G28) -> 0 | I29: =SUM(I19:I28) -> 0 | K29: =SUM(K19:K28) -> 0 | L29: =K29/K$10 -> #DIV/0! | M29: =SUM(M19:M28) -> #REF! | N29: =M29/M$10 -> #REF! | O29: =SUM(O19:O28) -> 0 | P29: =O29/O$10 -> #DIV/0! | Q29: =SUM(Q19:Q28) -> 0 | R29: =Q29/Q$10 -> #DIV/0! | S29: =SUM(S19:S28) -> 0 | T29: =S29/S$10 -> #DIV/0! | U29: =SUM(U19:U28) -> 0 | V29: =U29/U$10 -> #DIV/0! | W29: =SUM(W19:W28) -> 0 | X29: =W29/W$10 -> #DIV/0! | Y29: =SUM(Y19:Y28) -> #REF! | Z29: =Y29/Y$10 -> #REF! | AA29: =SUM(AA19:AA28) -> 0 | AB29: =AA29/AA$10 -> #DIV/0! | AC29: =SUM(AC19:AC28) -> 0 | AD29: =AC29/AC$10 -> #DIV/0! | AE29: =SUM(AE19:AE28) -> 0 | AF29: =AE29/AE$10 -> #DIV/0! | AG29: =SUM(AG19:AG28) -> 0 | AH29: =AG29/AG$10 -> #DIV/0! | AI29: =SUM(AI19:AI28) -> 0 | AK29: =SUM(AK19:AK28) -> 0 | AM29: =SUM(AM19:AM28) -> 0 | AN29: =AM29/AM$10 -> #DIV/0! | AO29: =SUM(AO19:AO28) -> 0 | AP29: =AO29/AO$10 -> #DIV/0! | AQ29: =SUM(AQ19:AQ28) -> 0 | AS29: =SUM(AS19:AS28) -> 0 | AU29: =SUM(AU19:AU28) -> 0 | AW29: =SUM(AW19:AW28) -> 0 | AY29: =SUM(AY19:AY28) -> 0 | BA29: =SUM(BA19:BA28) -> 0 | BC29: =SUM(BC19:BC28) -> 0 | BE29: =SUM(BE19:BE28) -> 0 | BG29: =SUM(BG19:BG28) -> 0 | BI29: =SUM(BI19:BI28) -> 0
AW30: =AW17-AW29 -> 0 | BA30: =BA17-BA29 -> 0 | BE30: =BE17-BE29 -> 0 | BI30: =BI17-BI29 -> 0
B31: EBIDTA | C31: =C17-C29 -> 0 | D31: =C31/C$10 -> #DIV/0! | E31: =E17-E29 -> #REF! | F31: =E31/E$10 -> #REF! | G31: =G17-G29 -> 0 | I31: =I17-I29 -> 0 | K31: =K17-K29 -> 0 | L31: =K31/K$10 -> #DIV/0! | M31: =M17-M29 -> #REF! | N31: =M31/M$10 -> #REF! | O31: =O17-O29 -> 0 | P31: =O31/O$10 -> #DIV/0! | Q31: =Q17-Q29 -> 0 | R31: =Q31/Q$10 -> #DIV/0! | S31: =S17-S29 -> 0 | T31: =S31/S$10 -> #DIV/0! | U31: =U17-U29 -> 0 | V31: =U31/U$10 -> #DIV/0! | W31: =W17-W29 -> 0 | X31: =W31/W$10 -> #DIV/0! | Y31: =Y17-Y29 -> #REF! | Z31: =Y31/Y$10 -> #REF! | AA31: =AA17-AA29 -> 0 | AB31: =AA31/AA$10 -> #DIV/0! | AC31: =AC17-AC29 -> 0 | AD31: =AC31/AC$10 -> #DIV/0! | AE31: =AE17-AE29 -> 0 | AF31: =AE31/AE$10 -> #DIV/0! | AG31: =AG17-AG29 -> 0 | AH31: =AG31/AG$10 -> #DIV/0! | AI31: =AI17-AI29 -> 0 | AK31: =AK17-AK29 -> 0 | AM31: =AM17-AM29 -> 0 | AN31: =AM31/AM$10 -> #DIV/0! | AO31: =AO17-AO29 -> 0 | AP31: =AO31/AO$10 -> #DIV/0! | AQ31: =AQ17-AQ29 -> 0 | AS31: =AS17-AS29 -> 0 | AU31: =AU17-AU29 -> 0 | AV31: =AV17-AV29 -> 0 | AW31: =AW17-AW29 -> 0 | AX31: =AX17-AX29 -> 0 | AY31: =AY17-AY29 -> 0 | AZ31: =AZ17-AZ29 -> 0 | BA31: =BA17-BA29 -> 0 | BB31: =BB17-BB29 -> 0 | ... BJ31: =BJ17-BJ29 -> 0
C33: =+G33+K33 -> 1539521.9 | G33: =HO!J123 -> -8100762.3 | K33: =SUM(O33:BJ33) -> 9640284.1 | O33: ='The Table'!J132 -> 3953343.5 | S33: =Iktara!J117 -> -258983.06 | W33: ='Mg St Colaba'!J137 -> 631729.58 | AA33: ='Mg St LP'!J141 -> 1234107.6 | AE33: ='Mg St Bandra'!J142 -> 4336730.2 | AI33: ='MSK Events'!J136 -> -1131355.8 | AM33: =MSBC!J125 -> -526562.19 | AQ33: =Kaspers!J138 -> 2018857.3 | AU33: ='MSBC Andheri'!J136 -> 81836.53 | AY33: ='MSBC Dahisar'!J123 -> -123284.31 | BC33: ='MSBC Juhu Goregoan'!J135 -> -139322.66 | BG33: ='LOUD MOUTH'!J123 -> -436812.58
C34: =+C31-C33 -> -1539521.9 | G34: =+G31-G33 -> 8100762.3 | K34: =+K31-K33 -> -9640284.1 | O34: =+O31-O33 -> -3953343.5 | S34: =+S31-S33 -> 258983.06 | W34: =+W31-W33 -> -631729.58 | AA34: =+AA31-AA33 -> -1234107.6 | AE34: =+AE31-AE33 -> -4336730.2 | AI34: =+AI31-AI33 -> 1131355.8 | AM34: =+AM31-AM33 -> 526562.19 | AQ34: =+AQ31-AQ33 -> -2018857.3 | AU34: =+AU31-AU33 -> -81836.53 | AY34: =+AY31-AY33 -> 123284.31 | BC34: =+BC31-BC33 -> 139322.66 | BG34: =+BG31-BG33 -> 436812.58 | BH34: =+BH31-BH33 -> 0 | BI34: =+BI31-BI33 -> 0 | BJ34: =+BJ31-BJ33 -> 0

Sheet Summary Sheet - May 2026
A1: FY26-27 Budgeted vs Actual MIS | AE1: =AE12/$K$12 -> 0.20744696
A2: Food Matters Group
C3: Total with HO | G3: HO | K3: Outlets Total | O3: Table Total | S3: Iktara | W3: Mg St Colaba | AA3: Mg St LP | AE3: Mg St Bandra | AI3: MSK Events | AM3: MSBC | AQ3: Kaspers | AU3: MSBC Andheri | AY3: MSBC Dahisar | BC3: MSBC Juhu / Goregaon | BG3: Loud Mouth
C4: Actual | D4: %age | E4: Budgeted | F4: %age | G4: Actual | H4: %age | I4: Budgeted | J4: %age | K4: Actual | L4: %age | M4: Budgeted | N4: %age | O4: Actual | P4: %age | Q4: Budgeted | R4: %age | S4: Actual | T4: %age | U4: Budgeted | V4: %age | W4: Actual | X4: %age | Y4: Budgeted | Z4: %age | AA4: Actual | AB4: %age | AC4: Budgeted | AD4: %age | AE4: Actual | AF4: %age | AG4: Budgeted | AH4: %age | AI4: Actual | AJ4: %age | AK4: Budgeted | AL4: %age | AM4: Actual | AN4: %age | AO4: Budgeted | AP4: %age | AQ4: Actual | AR4: %age | AS4: Budgeted | AT4: %age | AU4: Amount | AV4: %age | AW4: Budgeted | AX4: %age | AY4: Amount | AZ4: %age | BA4: Budgeted | BB4: %age | BC4: Amount | BD4: %age | BE4: Budgeted | BF4: %age | BG4: Amount | BH4: %age | BI4: Budgeted | BJ4: %age
B5: Beverage | C5: =G5+K5 -> 5897856 | D5: =C5/C$10 -> 0.080114561 | E5: =I5+M5 -> 0 | F5: =E5/E$10 -> #DIV/0! | G5: =HO!J14 -> 0 | I5: =HO!L14 | K5: =O5+S5+W5+AA5+AE5+AI5+AM5+AQ5+AU5+AY5+BC5+BG5 -> 5897856 | L5: =K5/K$10 -> 0.080114561 | M5: =Q5+U5+Y5+AC5+AG5+AK5+AO5+AS5+AW5+BA5+BE5+BI5 -> 0 | N5: =M5/M$10 -> #DIV/0! | O5: ='The Table'!J24 -> 1235475 | P5: =O5/O$10 -> 0.060540005 | Q5: ='The Table'!L24 | R5: =Q5/Q$10 -> #DIV/0! | S5: =Iktara!J24 -> 0 | T5: =S5/S$10 -> 0 | U5: =Iktara!L24 | V5: =U5/U$10 -> #DIV/0! | W5: ='Mg St Colaba'!J24 -> 1217044 | X5: =W5/W$10 -> 0.097889177 | Z5: =Y5/Y$10 -> #DIV/0! | AA5: ='Mg St LP'!J24 -> 1116341 | AB5: =AA5/AA$10 -> 0.11986451 | AC5: ='Mg St LP'!L24 | AD5: =AC5/AC$10 -> #DIV/0! | AE5: ='Mg St Bandra'!J24 -> 1681871 | AF5: =AE5/AE$10 -> 0.099598095 | AG5: ='Mg St Bandra'!L24 | AH5: =AG5/AG$10 -> #DIV/0! | AI5: ='MSK Events'!J24 | AJ5: =AI5/AI$10 -> #DIV/0! | AK5: ='MSK Events'!L24 | AM5: =MSBC!J24 | AN5: =AM5/AM$10 -> 0 | AO5: =MSBC!L24 -> 0 | AP5: =AO5/AO$10 -> #DIV/0! | AQ5: =Kaspers!J24 -> 647125 | AS5: =Kaspers!L24 | AU5: ='MSBC Andheri'!J24 -> 0 | AW5: ='MSBC Andheri'!L24 | AY5: ='MSBC Dahisar'!J22 -> 0 | BA5: ='MSBC Dahisar'!L22 | BC5: ='MSBC Juhu Goregoan'!J22 -> 0 | BE5: ='MSBC Juhu Goregoan'!L22 -> 0 | BG5: ='LOUD MOUTH'!J24 | BI5: ='LOUD MOUTH'!L24
B6: Liquor | C6: =G6+K6 -> 11792046 | D6: =C6/C$10 -> 0.16017933 | E6: =I6+M6 -> 0 | F6: =E6/E$10 -> #DIV/0! | G6: =HO!J15 -> 0 | I6: =HO!L15 | K6: =O6+S6+W6+AA6+AE6+AI6+AM6+AQ6+AU6+AY6+BC6+BG6 -> 11792046 | L6: =K6/K$10 -> 0.16017933 | M6: =Q6+U6+Y6+AC6+AG6+AK6+AO6+AS6+AW6+BA6+BE6+BI6 -> 0 | N6: =M6/M$10 -> #DIV/0! | O6: ='The Table'!J25 -> 4851470 | P6: =O6/O$10 -> 0.23772882 | Q6: ='The Table'!L25 | R6: =Q6/Q$10 -> #DIV/0! | S6: =Iktara!J25 -> 0 | T6: =S6/S$10 -> 0 | U6: =Iktara!L25 | V6: =U6/U$10 -> #DIV/0! | W6: ='Mg St Colaba'!J25 -> 735380 | X6: =W6/W$10 -> 0.05914802 | Z6: =Y6/Y$10 -> #DIV/0! | AA6: ='Mg St LP'!J25 -> 0 | AB6: =AA6/AA$10 -> 0 | AC6: ='Mg St LP'!L25 | AD6: =AC6/AC$10 -> #DIV/0! | AE6: ='Mg St Bandra'!J25 -> 2074971 | AF6: =AE6/AE$10 -> 0.12287694 | AG6: ='Mg St Bandra'!L25 | AH6: =AG6/AG$10 -> #DIV/0! | AI6: ='MSK Events'!J25 | AJ6: =AI6/AI$10 -> #DIV/0! | AK6: ='MSK Events'!L25 | AM6: =MSBC!J25 | AN6: =AM6/AM$10 -> 0 | AO6: =MSBC!L25 -> 0 | AP6: =AO6/AO$10 -> #DIV/0! | AQ6: =Kaspers!J25 -> 4130225 | AS6: =Kaspers!L25 | AU6: ='MSBC Andheri'!J25 -> 0 | AW6: ='MSBC Andheri'!L25 | AY6: ='MSBC Dahisar'!J23 -> 0 | BA6: ='MSBC Dahisar'!L23 | BC6: ='MSBC Juhu Goregoan'!J23 -> 0 | BE6: ='MSBC Juhu Goregoan'!L23 -> 0 | BG6: ='LOUD MOUTH'!J25 | BI6: ='LOUD MOUTH'!L25
B7: Food | C7: =G7+K7 -> 55892645 | D7: =C7/C$10 -> 0.75922755 | E7: =I7+M7 -> 0 | F7: =E7/E$10 -> #DIV/0! | G7: =HO!J16 -> 0 | I7: =HO!L16 | K7: =O7+S7+W7+AA7+AE7+AI7+AM7+AQ7+AU7+AY7+BC7+BG7 -> 55892645 | L7: =K7/K$10 -> 0.75922755 | M7: =Q7+U7+Y7+AC7+AG7+AK7+AO7+AS7+AW7+BA7+BE7+BI7 -> 0 | N7: =M7/M$10 -> #DIV/0! | O7: ='The Table'!J26 -> 14320635 | P7: =O7/O$10 -> 0.70173117 | Q7: ='The Table'!L26 | R7: =Q7/Q$10 -> #DIV/0! | S7: =Iktara!J26 -> 807500 | T7: =S7/S$10 -> 1 | U7: =Iktara!L26 | V7: =U7/U$10 -> #DIV/0! | W7: ='Mg St Colaba'!J26 -> 10480452 | X7: =W7/W$10 -> 0.8429628 | Z7: =Y7/Y$10 -> #DIV/0! | AA7: ='Mg St LP'!J26 -> 8189016 | AB7: =AA7/AA$10 -> 0.87927651 | AC7: ='Mg St LP'!L26 | AD7: =AC7/AC$10 -> #DIV/0! | AE7: ='Mg St Bandra'!J26 -> 13116005 | AF7: =AE7/AE$10 -> 0.77671184 | AG7: ='Mg St Bandra'!L26 | AH7: =AG7/AG$10 -> #DIV/0! | AI7: ='MSK Events'!J26 | AJ7: =AI7/AI$10 -> #DIV/0! | AK7: ='MSK Events'!L26 | AM7: =MSBC!J26 -> 460464 | AN7: =AM7/AM$10 -> 1 | AO7: =MSBC!L26 -> 0 | AP7: =AO7/AO$10 -> #DIV/0! | AQ7: =Kaspers!J26 -> 7349352 | AS7: =Kaspers!L26 -> 0 | AU7: ='MSBC Andheri'!J26 -> 332317 | AW7: ='MSBC Andheri'!L26 | AY7: ='MSBC Dahisar'!J24 -> 103369 | BA7: ='MSBC Dahisar'!L24 | BC7: ='MSBC Juhu Goregoan'!J24 -> 132839 | BE7: ='MSBC Juhu Goregoan'!L24 -> 0 | BG7: ='LOUD MOUTH'!J26 -> 600696 | BI7: ='LOUD MOUTH'!L26
B8: Service Charge | C8: =G8+K8 -> 0 | D8: =C8/C$10 -> 0 | E8: =I8+M8 -> 0 | F8: =E8/E$10 -> #DIV/0! | G8: =HO!J18 -> 0 | I8: =HO!L18 | K8: =O8+S8+W8+AA8+AE8+AI8+AM8+AQ8+AU8+AY8+BC8+BG8 -> 0 | L8: =K8/K$10 -> 0 | M8: =Q8+U8+Y8+AC8+AG8+AK8+AO8+AS8+AW8+BA8+BE8+BI8 -> 0 | N8: =M8/M$10 -> #DIV/0! | O8: ='The Table'!J28 | P8: =O8/O$10 -> 0 | Q8: ='The Table'!L28 | R8: =Q8/Q$10 -> #DIV/0! | S8: =Iktara!J28 | T8: =S8/S$10 -> 0 | U8: =Iktara!L28 -> 0 | V8: =U8/U$10 -> #DIV/0! | W8: ='Mg St Colaba'!J27 | X8: =W8/W$10 -> 0 | Z8: =Y8/Y$10 -> #DIV/0! | AA8: ='Mg St LP'!J28 | AB8: =AA8/AA$10 -> 0 | AC8: ='Mg St LP'!L28 | AD8: =AC8/AC$10 -> #DIV/0! | AE8: ='Mg St Bandra'!J28 | AF8: =AE8/AE$10 -> 0 | AG8: ='Mg St Bandra'!L28 -> 0 | AH8: =AG8/AG$10 -> #DIV/0! | AI8: ='MSK Events'!J28 | AJ8: =AI8/AI$10 -> #DIV/0! | AK8: ='MSK Events'!L28 | AM8: =MSBC!J28 | AN8: =AM8/AM$10 -> 0 | AO8: =MSBC!L28 | AP8: =AO8/AO$10 -> #DIV/0! | AQ8: =Kaspers!J28 | AS8: =Kaspers!L28 | AU8: 0 | AW8: ='MSBC Andheri'!L28 | AY8: 0 | BA8: 0 | BC8: 0 | BE8: 0 | BG8: ='LOUD MOUTH'!J28 | BI8: ='LOUD MOUTH'!L28
B9: Other revenue | C9: =G9+K9 -> 35231 | D9: =C9/C$10 -> 0.00047856647 | E9: =I9+M9 -> 0 | F9: =E9/E$10 -> #DIV/0! | K9: =O9+S9+W9+AA9+AE9+AI9+AM9+AQ9+AU9+AY9+BC9+BG9 -> 35231 | L9: =K9/K$10 -> 0.00047856647 | M9: =Q9+U9+Y9+AC9+AG9+AK9+AO9+AS9+AW9+BA9+BE9+BI9 -> 0 | N9: =M9/M$10 -> #DIV/0! | O9: ='The Table'!J22 | Q9: ='The Table'!L22 | S9: 0 | U9: 0 | W9: 0 | AA9: ='Mg St LP'!J22 -> 8000 | AC9: ='Mg St LP'!L22 | AE9: ='Mg St Bandra'!J22 -> 13731 | AG9: ='Mg St Bandra'!L22 | AI9: 0 | AK9: 0 | AM9: 0 | AO9: 0 | AQ9: =Kaspers!J22 -> 13500 | AS9: =Kaspers!L22 | AU9: 0 | AW9: 0 | AY9: 0 | BA9: 0 | BC9: 0 | BE9: 0 | BI9: 0
B10: Total Sales Revenue | C10: =SUM(C5:C9) -> 73617778 | D10: =C10/C$10 -> 1 | E10: =SUM(E5:E9) -> 0 | F10: =E10/E$10 -> #DIV/0! | G10: =SUM(G5:G9) -> 0 | I10: =SUM(I5:I9) -> 0 | K10: =SUM(K5:K9) -> 73617778 | L10: =K10/K$10 -> 1 | M10: =SUM(M5:M9) -> 0 | N10: =M10/M$10 -> #DIV/0! | O10: =SUM(O5:O9) -> 20407580 | Q10: =SUM(Q5:Q9) -> 0 | S10: =SUM(S5:S9) -> 807500 | U10: =SUM(U5:U9) -> 0 | W10: =SUM(W5:W9) -> 12432876 | Y10: =SUM(Y5:Y9) -> 0 | AA10: =SUM(AA5:AA9) -> 9313357 | AC10: =SUM(AC5:AC9) -> 0 | AE10: =SUM(AE5:AE9) -> 16886578 | AG10: =SUM(AG5:AG9) -> 0 | AI10: =SUM(AI5:AI9) -> 0 | AK10: =SUM(AK5:AK9) -> 0 | AM10: =SUM(AM5:AM9) -> 460464 | AO10: =SUM(AO5:AO9) -> 0 | AQ10: =SUM(AQ5:AQ9) -> 12140202 | AS10: =SUM(AS5:AS9) -> 0 | AU10: =SUM(AU5:AU9) -> 332317 | AW10: =SUM(AW5:AW9) -> 0 | AY10: =SUM(AY5:AY9) -> 103369 | BA10: =SUM(BA5:BA9) -> 0 | BC10: =SUM(BC5:BC9) -> 132839 | BE10: =SUM(BE5:BE9) -> 0 | BG10: =SUM(BG5:BG9) -> 600696 | BI10: =SUM(BI5:BI9) -> 0
AU11: 0 | BI11: 0
B12: COGS | C12: =G12+K12 -> 28301882 | D12: =C12/C$10 -> 0.38444357 | E12: =I12+M12 -> 0 | F12: =E12/E$10 -> #DIV/0! | G12: =HO!J32 -> 0 | I12: =HO!L32 | K12: =O12+S12+W12+AA12+AE12+AI12+AM12+AQ12+AU12+AY12+BC12+BG12 -> 28301882 | L12: =K12/K$10 -> 0.38444357 | M12: =Q12+U12+Y12+AC12+AG12+AK12+AO12+AS12+AW12+BA12+BE12+BI12 -> 0 | N12: =M12/M$10 -> #DIV/0! | O12: ='The Table'!J39 -> 7196374.9 | P12: =O12/O$10 -> 0.35263245 | Q12: ='The Table'!L39 -> 0 | R12: =Q12/Q$10 -> #DIV/0! | S12: =Iktara!J40 -> 287157.02 | T12: =S12/S$10 -> 0.35561241 | U12: =Iktara!L40 -> 0 | V12: =U12/U$10 -> #DIV/0! | W12: ='Mg St Colaba'!J47 -> 5012275.5 | X12: =W12/W$10 -> 0.4031469 | Z12: =Y12/Y$10 -> #DIV/0! | AA12: ='Mg St LP'!J49 -> 3629432.9 | AB12: =AA12/AA$10 -> 0.3897019 | AC12: ='Mg St LP'!L49 | AD12: =AC12/AC$10 -> #DIV/0! | AE12: ='Mg St Bandra'!J47 -> 5871139.3 | AF12: =AE12/AE$10 -> 0.34768082 | AG12: ='Mg St Bandra'!L47 -> 0 | AH12: =AG12/AG$10 -> #DIV/0! | AI12: ='MSK Events'!J47 -> 0 | AJ12: =AI12/AI$10 -> #DIV/0! | AK12: ='MSK Events'!L47 -> 0 | AM12: =MSBC!J47 -> 877373.14 | AO12: =MSBC!L47 -> 0 | AQ12: =Kaspers!J47 -> 4712035.4 | AS12: =Kaspers!L47 -> 0 | AU12: ='MSBC Andheri'!J46 -> 99085.77 | AW12: ='MSBC Andheri'!L46 -> 0 | AY12: ='MSBC Dahisar'!J44 -> 182309.39 | BA12: ='MSBC Dahisar'!L44 -> 0 | BC12: ='MSBC Juhu Goregoan'!J37 -> 221635.66 | BE12: ='MSBC Juhu Goregoan'!L37 -> 0 | BG12: ='LOUD MOUTH'!J39 -> 213062.58 | BI12: ='LOUD MOUTH'!L39
B13: Packaging Cost | C13: =G13+K13 -> 996226.27 | D13: =C13/C$10 -> 0.013532414 | E13: =I13+M13 -> 0 | F13: =E13/E$10 -> #DIV/0! | G13: =HO!J33 | I13: =HO!L33 | K13: =O13+S13+W13+AA13+AE13+AI13+AM13+AQ13+AU13+AY13+BC13+BG13 -> 996226.27 | L13: =K13/K$10 -> 0.013532414 | M13: =Q13+U13+Y13+AC13+AG13+AK13+AO13+AS13+AW13+BA13+BE13+BI13 -> 0 | N13: =M13/M$10 -> #DIV/0! | O13: ='The Table'!J40 -> 58949.25 | P13: =O13/O$10 -> 0.0028885958 | Q13: ='The Table'!L40 -> 0 | R13: =Q13/Q$10 -> #DIV/0! | S13: =Iktara!J41 -> 29560 | T13: =S13/S$10 -> 0.036606811 | U13: =Iktara!L41 | V13: =U13/U$10 -> #DIV/0! | W13: ='Mg St Colaba'!J48 -> 179370 | X13: =W13/W$10 -> 0.014427072 | Z13: =Y13/Y$10 -> #DIV/0! | AA13: ='Mg St LP'!J50 -> 229061 | AB13: =AA13/AA$10 -> 0.024594891 | AC13: ='Mg St LP'!L50 | AD13: =AC13/AC$10 -> #DIV/0! | AE13: ='Mg St Bandra'!J48 -> 309372.52 | AF13: =AE13/AE$10 -> 0.018320617 | AG13: ='Mg St Bandra'!L48 | AH13: =AG13/AG$10 -> #DIV/0! | AI13: ='MSK Events'!J48 -> 1030 | AK13: ='MSK Events'!L48 | AM13: =MSBC!J48 -> 109653 | AO13: =MSBC!L48 | AQ13: =Kaspers!J48 -> 27761.5 | AS13: =Kaspers!L48 -> 0 | AU13: ='MSBC Andheri'!J47 -> 6379 | AW13: ='MSBC Andheri'!L47 | AY13: ='MSBC Dahisar'!J45 -> 668 | BA13: ='MSBC Dahisar'!L45 | BC13: ='MSBC Juhu Goregoan'!J38 -> 3293 | BE13: ='MSBC Juhu Goregoan'!L38 | BG13: ='LOUD MOUTH'!J40 -> 41129 | BI13: ='LOUD MOUTH'!L40
B14: NC & DQ | C14: =G14+K14 -> 0 | D14: =C14/C$10 -> 0 | K14: =O14+S14+W14+AA14+AE14+AI14+AM14+AQ14+AU14+AY14+BC14+BG14 -> 0 | M14: =Q14+U14+Y14+AC14+AG14+AK14+AO14+AS14+AW14+BA14+BE14+BI14 -> 0
B15: Total COGS & Packaging | C15: =SUM(C12:C14) -> 29298108 | D15: =SUM(D12:D14) -> 0.39797599 | E15: =SUM(E12:E14) -> 0 | F15: =SUM(F12:F14) -> #DIV/0! | G15: =SUM(G12:G14) -> 0 | H15: =SUM(H12:H14) -> 0 | I15: =SUM(I12:I14) -> 0 | J15: =SUM(J12:J14) -> 0 | ... AM15: =SUM(AM12:AM14) -> 987026.14 | AO15: =SUM(AO12:AO14) -> 0 | AQ15: =SUM(AQ12:AQ13) -> 4739796.9 | AS15: =SUM(AS12:AS14) -> 0 | AU15: =SUM(AU12:AU14) -> 105464.77 | AV15: =SUM(AV12:AV14) -> 0 | AW15: =SUM(AW12:AW14) -> 0 | AX15: =SUM(AX12:AX14) -> 0 | AY15: =SUM(AY12:AY14) -> 182977.39 | AZ15: =SUM(AZ12:AZ14) -> 0 | BA15: =SUM(BA12:BA14) -> 0 | BB15: =SUM(BB12:BB14) -> 0 | ... BJ15: =SUM(BJ12:BJ14) -> 0
AU16: 0 | AW16: 0
B17: Gross Margin | C17: =C10-C15 -> 44319670 | D17: =C17/C$10 -> 0.60202401 | E17: =E10-E15 -> 0 | F17: =E17/E$10 -> #DIV/0! | G17: =G10-G15 -> 0 | I17: =I10-I15 -> 0 | K17: =K10-K15 -> 44319670 | L17: =K17/K$10 -> 0.60202401 | M17: =Q17+U17+Y17+AC17+AG17+AK17+AO17 -> 0 | N17: =M17/M$10 -> #DIV/0! | O17: =O10-O15 -> 13152256 | P17: =O17/O$10 -> 0.64447895 | Q17: =Q10-Q15 -> 0 | R17: =Q17/Q$10 -> #DIV/0! | S17: =S10-S15 -> 490782.98 | T17: =S17/S$10 -> 0.60778078 | U17: =U10-U15 -> 0 | V17: =U17/U$10 -> #DIV/0! | W17: =W10-W15 -> 7241230.5 | X17: =W17/W$10 -> 0.58242602 | Y17: =Y10-Y15 -> 0 | Z17: =Y17/Y$10 -> #DIV/0! | AA17: =AA10-AA15 -> 5454863.1 | AB17: =AA17/AA$10 -> 0.58570321 | AC17: =AC10-AC15 -> 0 | AD17: =AC17/AC$10 -> #DIV/0! | AE17: =AE10-AE15 -> 10706066 | AF17: =AE17/AE$10 -> 0.63399856 | AG17: =AG10-AG15 -> 0 | AH17: =AG17/AG$10 -> #DIV/0! | AI17: =AI10-AI15 -> -1030 | AJ17: =AI17/AI$10 -> #DIV/0! | AK17: =AK10-AK15 -> 0 | AM17: =AM10-AM15 -> -526562.14 | AO17: =AO10-AO15 -> 0 | AQ17: =AQ10-AQ15 -> 7400405.1 | AS17: =AS10-AS15 -> 0 | AU17: =AU10-AU15 -> 226852.23 | AV17: =AV10-AV15 -> 0 | AW17: =AW10-AW15 -> 0 | AX17: =AX10-AX15 -> 0 | AY17: =AY10-AY15 -> -79608.387 | AZ17: =AZ10-AZ15 -> 0 | BA17: =BA10-BA15 -> 0 | BB17: =BB10-BB15 -> 0 | ... BJ17: =BJ10-BJ15 -> 0
B19: Other Direct Expenses | C19: =G19+K19 -> 1907328.9 | D19: =C19/C$10 -> 0.025908537 | E19: =I19+M19 -> 0 | F19: =E19/E$10 -> #DIV/0! | G19: =HO!J43 -> 21275 | I19: =HO!L43 | K19: =O19+S19+W19+AA19+AE19+AI19+AM19+AQ19+AU19+AY19+BC19+BG19 -> 1886053.9 | L19: =K19/K$10 -> 0.025619545 | M19: =Q19+U19+Y19+AC19+AG19+AK19+AO19+AS19+AW1+BA19+BE19+BI19 -> 0 | N19: =M19/M$10 -> #DIV/0! | O19: ='The Table'!J51 -> 421384.94 | P19: =O19/O$10 -> 0.020648452 | Q19: ='The Table'!L51 -> 0 | R19: =Q19/Q$10 -> #DIV/0! | S19: =Iktara!J52 -> 43391 | T19: =S19/S$10 -> 0.053734985 | U19: =Iktara!L52 -> 0 | V19: =U19/U$10 -> #DIV/0! | W19: ='Mg St Colaba'!J60 -> 356741 | X19: =W19/W$10 -> 0.028693361 | Z19: =Y19/Y$10 -> #DIV/0! | AA19: ='Mg St LP'!J61 -> 253717 | AB19: =AA19/AA$10 -> 0.027242272 | AC19: ='Mg St LP'!L61 -> 0 | AD19: =AC19/AC$10 -> #DIV/0! | AE19: ='Mg St Bandra'!J58 -> 549979 | AF19: =AE19/AE$10 -> 0.032569002 | AG19: ='Mg St Bandra'!L58 -> 0 | AH19: =AG19/AG$10 -> #DIV/0! | AI19: ='MSK Events'!J59 -> 24234 | AJ19: =AI19/AI$10 -> #DIV/0! | AK19: ='MSK Events'!L59 -> 0 | AL19: =AK19/AK$10 -> #DIV/0! | AM19: =MSBC!J59 -> 42515 | AN19: =AM19/AM$10 -> 0.092330779 | AO19: =MSBC!L59 -> 0 | AP19: =AO19/AO$10 -> #DIV/0! | AQ19: =Kaspers!J62 -> 189879 | AS19: =Kaspers!L62 -> 0 | AU19: ='MSBC Andheri'!J58 -> 0 | AW19: ='MSBC Andheri'!L58 -> 0 | AY19: ='MSBC Dahisar'!J55 -> 0 | BA19: ='MSBC Dahisar'!L55 -> 0 | BC19: ='MSBC Juhu Goregoan'!J60 -> 0 | BE19: ='MSBC Juhu Goregoan'!L60 -> 0 | BG19: ='LOUD MOUTH'!J51 -> 4213 | BI19: ='LOUD MOUTH'!L51 -> 0
B20: Marketing Expenses | C20: =G20+K20 -> 775680 | D20: =C20/C$10 -> 0.010536585 | E20: =I20+M20 -> 0 | F20: =E20/E$10 -> #DIV/0! | G20: =HO!J52 -> 53100 | I20: =HO!L52 -> 0 | K20: =O20+S20+W20+AA20+AE20+AI20+AM20+AQ20+AU20+AY20+BC20+BG20 -> 722580 | L20: =K20/K$10 -> 0.0098152922 | M20: =Q20+U20+Y20+AC20+AG20+AK20+AO20+AS20+AW2+BA20+BE20+BI20 -> 0 | N20: =M20/M$10 -> #DIV/0! | O20: ='The Table'!J60 -> 0 | P20: =O20/O$10 -> 0 | Q20: ='The Table'!L60 -> 0 | R20: =Q20/Q$10 -> #DIV/0! | S20: =Iktara!J54 -> 89697 | T20: =S20/S$10 -> 0.11107988 | U20: =Iktara!L54 -> 0 | V20: =U20/U$10 -> #DIV/0! | W20: ='Mg St Colaba'!J69 -> 210682 | X20: =W20/W$10 -> 0.016945556 | Z20: =Y20/Y$10 -> #DIV/0! | AA20: ='Mg St LP'!J70 -> 116275 | AB20: =AA20/AA$10 -> 0.012484757 | AC20: ='Mg St LP'!L70 -> 0 | AD20: =AC20/AC$10 -> #DIV/0! | AE20: ='Mg St Bandra'!J70 -> 100602 | AF20: =AE20/AE$10 -> 0.0059575125 | AG20: ='Mg St Bandra'!L70 -> 0 | AH20: =AG20/AG$10 -> #DIV/0! | AI20: ='MSK Events'!J70 -> 80000 | AJ20: =AI20/AI$10 -> #DIV/0! | AK20: ='MSK Events'!L70 -> 0 | AL20: =AK20/AK$10 -> #DIV/0! | AM20: =MSBC!J61 -> 25981 | AN20: =AM20/AM$10 -> 0.056423521 | AO20: =MSBC!L61 -> 0 | AP20: =AO20/AO$10 -> #DIV/0! | AQ20: =Kaspers!J65 -> 35000 | AS20: =Kaspers!L65 -> 0 | AU20: ='MSBC Andheri'!J70 -> 56065 | AW20: ='MSBC Andheri'!L70 -> 0 | AY20: ='MSBC Dahisar'!J57 -> 4563 | BA20: ='MSBC Dahisar'!L57 -> 0 | BC20: ='MSBC Juhu Goregoan'!J72 -> 3715 | BE20: ='MSBC Juhu Goregoan'!L72 -> 0 | BG20: ='LOUD MOUTH'!J54 -> 0 | BI20: ='LOUD MOUTH'!L54 -> 0
B21: Sales Commission | C21: =G21+K21 -> 2295835.2 | D21: =C21/C$10 -> 0.03118588 | E21: =I21+M21 -> 0 | F21: =E21/E$10 -> #DIV/0! | G21: =HO!J63 -> 0 | I21: =HO!L63 -> 0 | K21: =O21+S21+W21+AA21+AE21+AI21+AM21+AQ21+AU21+AY21+BC21+BG21 -> 2295835.2 | L21: =K21/K$10 -> 0.03118588 | M21: =Q21+U21+Y21+AC21+AG21+AK21+AO21+AS21+AW3+BA21+BE21+BI21 -> 0 | N21: =M21/M$10 -> #DIV/0! | O21: ='The Table'!J69 -> 83781 | P21: =O21/O$10 -> 0.0041053863 | Q21: ='The Table'!L69 -> 0 | R21: =Q21/Q$10 -> #DIV/0! | S21: =Iktara!J64 -> 116787.55 | T21: =S21/S$10 -> 0.14462854 | U21: =Iktara!L64 | V21: =U21/U$10 -> #DIV/0! | W21: ='Mg St Colaba'!J81 -> 480329 | X21: =W21/W$10 -> 0.03863378 | Z21: =Y21/Y$10 -> #DIV/0! | AA21: ='Mg St LP'!J83 -> 721776 | AB21: =AA21/AA$10 -> 0.077499016 | AC21: ='Mg St LP'!L83 -> 0 | AD21: =AC21/AC$10 -> #DIV/0! | AE21: ='Mg St Bandra'!J81 -> 679501 | AF21: =AE21/AE$10 -> 0.040239118 | AG21: ='Mg St Bandra'!L81 -> 0 | AH21: =AG21/AG$10 -> #DIV/0! | AI21: ='MSK Events'!J77 -> 0 | AJ21: =AI21/AI$10 -> #DIV/0! | AK21: ='MSK Events'!L77 -> 0 | AL21: =AK21/AK$10 -> #DIV/0! | AM21: =MSBC!J69 -> 38464 | AN21: =AM21/AM$10 -> 0.083533132 | AO21: =MSBC!L69 -> 0 | AP21: =AO21/AO$10 -> #DIV/0! | AQ21: =Kaspers!J73 -> 0 | AS21: =Kaspers!L73 -> 0 | AU21: ='MSBC Andheri'!J78 -> 65859.7 | AW21: ='MSBC Andheri'!L78 -> 0 | AY21: ='MSBC Dahisar'!J65 -> 16021.92 | BA21: ='MSBC Dahisar'!L65 -> 0 | BC21: ='MSBC Juhu Goregoan'!J80 -> 20427 | BE21: ='MSBC Juhu Goregoan'!L80 -> 0 | BG21: ='LOUD MOUTH'!J63 -> 72888 | BI21: ='LOUD MOUTH'!L63 -> 0
B22: Rental & Utility Expenses | C22: =G22+K22 -> 7979501 | D22: =C22/C$10 -> 0.10839095 | E22: =I22+M22 -> 0 | F22: =E22/E$10 -> #DIV/0! | G22: =HO!J70 -> 814333 | I22: =HO!L70 -> 0 | K22: =O22+S22+W22+AA22+AE22+AI22+AM22+AQ22+AU22+AY22+BC22+BG22 -> 7165168 | L22: =K22/K$10 -> 0.097329317 | M22: =Q22+U22+Y22+AC22+AG22+AK22+AO22+AS22+AW22+BA22+BE22+BI22 -> 0 | N22: =M22/M$10 -> #DIV/0! | O22: ='The Table'!J75 -> 1848628 | P22: =O22/O$10 -> 0.090585361 | Q22: ='The Table'!L75 -> 0 | R22: =Q22/Q$10 -> #DIV/0! | S22: =Iktara!J70 -> 109552 | T22: =S22/S$10 -> 0.13566811 | U22: =Iktara!L70 | V22: =U22/U$10 -> #DIV/0! | W22: ='Mg St Colaba'!J88 -> 1784689 | X22: =W22/W$10 -> 0.14354595 | Z22: =Y22/Y$10 -> #DIV/0! | AA22: ='Mg St LP'!J90 -> 1116762 | AB22: =AA22/AA$10 -> 0.11990972 | AC22: ='Mg St LP'!L90 -> 0 | AD22: =AC22/AC$10 -> #DIV/0! | AE22: ='Mg St Bandra'!J88 -> 808420 | AF22: =AE22/AE$10 -> 0.047873524 | AG22: ='Mg St Bandra'!L88 -> 0 | AH22: =AG22/AG$10 -> #DIV/0! | AI22: ='MSK Events'!J84 -> 278160 | AJ22: =AI22/AI$10 -> #DIV/0! | AK22: ='MSK Events'!L84 -> 0 | AL22: =AK22/AK$10 -> #DIV/0! | AM22: =MSBC!J75 -> 236678 | AN22: =AM22/AM$10 -> 0.51399892 | AO22: =MSBC!L75 -> 0 | AP22: =AO22/AO$10 -> #DIV/0! | AQ22: =Kaspers!J80 -> 982279 | AS22: =Kaspers!L80 -> 0 | AU22: ='MSBC Andheri'!J87 -> 0 | AW22: ='MSBC Andheri'!L87 -> 0 | AY22: ='MSBC Dahisar'!J74 -> 0 | BA22: ='MSBC Dahisar'!L74 -> 0 | BC22: 0 | BE22: 0 | BG22: ='LOUD MOUTH'!J70 -> 0 | BI22: ='LOUD MOUTH'!L70 -> 0
B23: Salary & Staff Expenses | C23: =G23+K23 -> 24466960 | D23: =C23/C$10 -> 0.33235124 | E23: =I23+M23 -> 0 | F23: =E23/E$10 -> #DIV/0! | G23: =HO!J76 -> 3975522.3 | I23: =HO!L76 -> 0 | K23: =O23+S23+W23+AA23+AE23+AI23+AM23+AQ23+AU23+AY23+BC23+BG23 -> 20491437 | L23: =K23/K$10 -> 0.27834903 | M23: =Q23+U23+Y23+AC23+AG23+AK23+AO23+AS23+AW5+BA23+BE23+BI23 -> 0 | N23: =M23/M$10 -> #DIV/0! | O23: ='The Table'!J81 -> 5055129.8 | P23: =O23/O$10 -> 0.24770844 | Q23: ='The Table'!L81 -> 0 | R23: =Q23/Q$10 -> #DIV/0! | S23: =Iktara!J76 -> 336606.49 | T23: =S23/S$10 -> 0.41685014 | U23: =Iktara!L76 -> 0 | V23: =U23/U$10 -> #DIV/0! | W23: ='Mg St Colaba'!J94 -> 3234308.3 | X23: =W23/W$10 -> 0.2601416 | Z23: =Y23/Y$10 -> #DIV/0! | AA23: ='Mg St LP'!J97 -> 1791147 | AB23: =AA23/AA$10 -> 0.19232024 | AC23: ='Mg St LP'!L97 -> 0 | AD23: =AC23/AC$10 -> #DIV/0! | AE23: ='Mg St Bandra'!J96 -> 3833654.9 | AF23: =AE23/AE$10 -> 0.22702379 | AG23: ='Mg St Bandra'!L96 -> 0 | AH23: =AG23/AG$10 -> #DIV/0! | AI23: ='MSK Events'!J90 -> 189246 | AJ23: =AI23/AI$10 -> #DIV/0! | AK23: ='MSK Events'!L90 -> 0 | AL23: =AK23/AK$10 -> #DIV/0! | AM23: =MSBC!J81 -> 1547667.7 | AN23: =AM23/AM$10 -> 3.3611047 | AO23: =MSBC!L81 -> 0 | AP23: =AO23/AO$10 -> #DIV/0! | AQ23: =Kaspers!J86 -> 3797461 | AS23: =Kaspers!L86 -> 0 | AU23: ='MSBC Andheri'!J93 -> 0 | AW23: ='MSBC Andheri'!L93 -> 0 | AY23: ='MSBC Dahisar'!J80 -> 0 | BA23: ='MSBC Dahisar'!L80 -> 0 | BC23: 0 | BE23: 0 | BG23: ='LOUD MOUTH'!J77 -> 706216 | BI23: ='LOUD MOUTH'!L77 -> 0
B24: Bank and Finance Charges | C24: =G24+K24 -> 1003551.2 | D24: =C24/C$10 -> 0.013631913 | E24: =I24+M24 -> 0 | F24: =E24/E$10 -> #DIV/0! | G24: =HO!J87 -> 401791 | I24: =HO!L87 -> 0 | K24: =O24+S24+W24+AA24+AE24+AI24+AM24+AQ24+AU24+AY24+BC24+BG24 -> 601760.15 | L24: =K24/K$10 -> 0.0081741145 | M24: =Q24+U24+Y24+AC24+AG24+AK24+AO24+AS24+AW6+BA24+BE24+BI24 -> 0 | N24: =M24/M$10 -> #DIV/0! | O24: ='The Table'!J92 -> 521738 | P24: =O24/O$10 -> 0.025565893 | Q24: ='The Table'!L92 -> 0 | R24: =Q24/Q$10 -> #DIV/0! | S24: =Iktara!J86 -> 0 | T24: =S24/S$10 -> 0 | U24: =Iktara!L86 -> 0 | V24: =U24/U$10 -> #DIV/0! | W24: ='Mg St Colaba'!J104 -> 22441.6 | X24: =W24/W$10 -> 0.0018050208 | Z24: =Y24/Y$10 -> #DIV/0! | AA24: ='Mg St LP'!J107 -> 29639.82 | AB24: =AA24/AA$10 -> 0.0031825066 | AC24: ='Mg St LP'!L107 -> 0 | AD24: =AC24/AC$10 -> #DIV/0! | AE24: ='Mg St Bandra'!J107 -> 20525.73 | AF24: =AE24/AE$10 -> 0.0012155056 | AG24: ='Mg St Bandra'!L107 -> 0 | AH24: =AG24/AG$10 -> #DIV/0! | AI24: ='MSK Events'!J100 -> 0 | AJ24: =AI24/AI$10 -> #DIV/0! | AK24: ='MSK Events'!L100 -> 0 | AL24: =AK24/AK$10 -> #DIV/0! | AM24: =MSBC!J92 -> 5388 | AN24: =AM24/AM$10 -> 0.01170124 | AO24: =MSBC!L92 -> 0 | AP24: =AO24/AO$10 -> #DIV/0! | AQ24: =Kaspers!J97 -> 2027 | AS24: =Kaspers!L97 -> 0 | AU24: ='MSBC Andheri'!J103 -> 0 | AW24: ='MSBC Andheri'!L103 -> 0 | AY24: ='MSBC Dahisar'!J90 -> 0 | BA24: ='MSBC Dahisar'!L90 -> 0 | BC24: ='MSBC Juhu Goregoan'!J103 -> 0 | BE24: ='MSBC Juhu Goregoan'!L103 -> 0 | BG24: ='LOUD MOUTH'!J89 -> 0 | BI24: ='LOUD MOUTH'!L89 -> 0
B25: Software and Subscription | C25: =G25+K25 -> 468332.42 | D25: =C25/C$10 -> 0.0063616755 | E25: =I25+M25 -> 0 | F25: =E25/E$10 -> #DIV/0! | G25: =HO!J94 -> 113293.5 | I25: =HO!L94 -> 0 | K25: =O25+S25+W25+AA25+AE25+AI25+AM25+AQ25+AU25+AY25+BC25+BG25 -> 355038.92 | L25: =K25/K$10 -> 0.0048227334 | M25: =Q25+U25+Y25+AC25+AG25+AK25+AO25+AS25+AW7+BA25+BE25+BI25 -> 0 | N25: =M25/M$10 -> #DIV/0! | O25: ='The Table'!J95 -> 25091 | P25: =O25/O$10 -> 0.0012294941 | Q25: ='The Table'!L95 -> 0 | R25: =Q25/Q$10 -> #DIV/0! | S25: =Iktara!J89 -> 23090 | T25: =S25/S$10 -> 0.028594427 | U25: =Iktara!L89 -> 0 | V25: =U25/U$10 -> #DIV/0! | W25: ='Mg St Colaba'!J107 -> 63685.333 | X25: =W25/W$10 -> 0.0051223332 | Z25: =Y25/Y$10 -> #DIV/0! | AA25: ='Mg St LP'!J110 -> 49820.333 | AB25: =AA25/AA$10 -> 0.0053493422 | AC25: ='Mg St LP'!L110 -> 0 | AD25: =AC25/AC$10 -> #DIV/0! | AE25: ='Mg St Bandra'!J110 -> 77845.333 | AF25: =AE25/AE$10 -> 0.0046098939 | AG25: ='Mg St Bandra'!L110 -> 0 | AH25: =AG25/AG$10 -> #DIV/0! | AI25: ='MSK Events'!J103 -> 6806.25 | AJ25: =AI25/AI$10 -> #DIV/0! | AK25: ='MSK Events'!L103 -> 0 | AL25: =AK25/AK$10 -> #DIV/0! | AM25: =MSBC!J95 -> 36281 | AN25: =AM25/AM$10 -> 0.078792262 | AO25: =MSBC!L95 -> 0 | AP25: =AO25/AO$10 -> #DIV/0! | AQ25: =Kaspers!J100 -> 3146.6667 | AS25: =Kaspers!L100 -> 0 | AU25: ='MSBC Andheri'!J106 -> 23091 | AW25: ='MSBC Andheri'!L106 -> 0 | AY25: ='MSBC Dahisar'!J93 -> 23091 | BA25: ='MSBC Dahisar'!L93 -> 0 | BC25: ='MSBC Juhu Goregoan'!J106 -> 23091 | BE25: ='MSBC Juhu Goregoan'!L106 -> 0 | BG25: ='LOUD MOUTH'!J92 -> 0 | BI25: ='LOUD MOUTH'!L92 -> 0
B26: Other Outlet Costs | C26: =G26+K26 -> 5072114.1 | D26: =C26/C$10 -> 0.068897951 | E26: =I26+M26 -> 0 | F26: =E26/E$10 -> #DIV/0! | G26: =HO!J98 -> 1937450.5 | I26: =HO!L98 -> 0 | K26: =O26+S26+W26+AA26+AE26+AI26+AM26+AQ26+AU26+AY26+BC26+BG26 -> 3134663.6 | L26: =K26/K$10 -> 0.042580253 | M26: =Q26+U26+Y26+AC26+AG26+AK26+AO26+AS26+AW8+BA26+BE26+BI26 -> 0 | N26: =M26/M$10 -> #DIV/0! | O26: ='The Table'!J99+'The Table'!J106+'The Table'!J112+'The Table'!J114+'The Table'!J116+'The Table'!J118+'The Table'!J120 -> 1210775.7 | P26: =O26/O$10 -> 0.059329703 | Q26: ='The Table'!L99 -> 0 | R26: =Q26/Q$10 -> #DIV/0! | S26: =Iktara!J93 -> 30642 | T26: =S26/S$10 -> 0.037946749 | U26: =Iktara!L93 -> 0 | V26: =U26/U$10 -> #DIV/0! | W26: ='Mg St Colaba'!J111 -> 446614.75 | X26: =W26/W$10 -> 0.035922079 | Z26: =Y26/Y$10 -> #DIV/0! | AA26: ='Mg St LP'!J114 -> 141618.25 | AB26: =AA26/AA$10 -> 0.01520593 | AC26: ='Mg St LP'!L114 -> 0 | AD26: =AC26/AC$10 -> #DIV/0! | AE26: ='Mg St Bandra'!J114 -> 288798 | AF26: =AE26/AE$10 -> 0.017102222 | AG26: ='Mg St Bandra'!L114 -> 0 | AH26: =AG26/AG$10 -> #DIV/0! | AI26: ='MSK Events'!J107 -> 551879.51 | AJ26: =AI26/AI$10 -> #DIV/0! | AK26: ='MSK Events'!L107 -> 0 | AL26: =AK26/AK$10 -> #DIV/0! | AM26: =MSBC!J99 -> 100840.33 | AN26: =AM26/AM$10 -> 0.21899721 | AO26: =MSBC!L99 -> 0 | AP26: =AO26/AO$10 -> #DIV/0! | AQ26: =Kaspers!J104 -> 363495.08 | AS26: =Kaspers!L104 -> 0 | AU26: ='MSBC Andheri'!J110 -> 0 | AW26: ='MSBC Andheri'!L110 -> 0 | AY26: ='MSBC Dahisar'!J97 -> 0 | BA26: ='MSBC Dahisar'!L97 -> 0 | BC26: ='MSBC Juhu Goregoan'!J110 -> 0 | BE26: ='MSBC Juhu Goregoan'!L110 -> 0 | BG26: ='LOUD MOUTH'!J96 -> 0 | BI26: ='LOUD MOUTH'!L96 -> 0
B27: Other Professional Fees | C27: =G27+K27 -> 748613 | D27: =C27/C$10 -> 0.010168916 | E27: =I27+M27 -> 0 | F27: =E27/E$10 -> #DIV/0! | G27: =HO!J113 -> 687949 | I27: =HO!L113 -> 0 | K27: =O27+S27+W27+AA27+AE27+AI27+AM27+AQ27+AU27+AY27+BC27+BG27 -> 60664 | L27: =K27/K$10 -> 0.00082404008 | M27: =Q27+U27+Y27+AC27+AG27+AK27+AO27+AS27+AW9+BA27+BE27+BI27 -> 0 | N27: =M27/M$10 -> #DIV/0! | O27: ='The Table'!J122 -> 32384 | P27: =O27/O$10 -> 0.0015868614 | Q27: ='The Table'!L122 -> 0 | R27: =Q27/Q$10 -> #DIV/0! | S27: =Iktara!J106 -> 0 | T27: =S27/S$10 -> 0 | U27: =Iktara!L106 -> 0 | V27: =U27/U$10 -> #DIV/0! | W27: ='Mg St Colaba'!J127 -> 10010 | X27: =W27/W$10 -> 0.00080512345 | Z27: =Y27/Y$10 -> #DIV/0! | AA27: ='Mg St LP'!J130 -> 0 | AB27: =AA27/AA$10 -> 0 | AC27: ='Mg St LP'!L130 -> 0 | AD27: =AC27/AC$10 -> #DIV/0! | AE27: ='Mg St Bandra'!J131 -> 10010 | AF27: =AE27/AE$10 -> 0.00059277848 | AG27: ='Mg St Bandra'!L131 -> 0 | AH27: =AG27/AG$10 -> #DIV/0! | AI27: ='MSK Events'!J125 -> 0 | AJ27: =AI27/AI$10 -> #DIV/0! | AK27: ='MSK Events'!L125 -> 0 | AL27: =AK27/AK$10 -> #DIV/0! | AM27: =MSBC!J115 -> 0 | AN27: =AM27/AM$10 -> 0 | AO27: =MSBC!L115 -> 0 | AP27: =AO27/AO$10 -> #DIV/0! | AQ27: =Kaspers!J127 -> 8260 | AS27: =Kaspers!L127 -> 0 | AU27: ='MSBC Andheri'!J125 -> 0 | AW27: ='MSBC Andheri'!L125 -> 0 | AY27: ='MSBC Dahisar'!J112 -> 0 | BA27: ='MSBC Dahisar'!L112 -> 0 | BC27: ='MSBC Juhu Goregoan'!J125 -> 0 | BE27: ='MSBC Juhu Goregoan'!L125 -> 0 | BG27: ='LOUD MOUTH'!J112 -> 0 | BI27: ='LOUD MOUTH'!L112 -> 0
B28: Other Expenses | C28: =G28+K28 -> -1937767 | D28: =C28/C$10 -> -0.026321998 | E28: =I28+M28 -> 0 | F28: =E28/E$10 -> #DIV/0! | G28: =HO!J117 -> 96048 | I28: =HO!L117 -> 0 | K28: =O28+S28+W28+AA28+AE28+AI28+AM28+AQ28+AU28+AY28+BC28+BG28 -> -2033815 | L28: =K28/K$10 -> -0.027626683 | M28: =Q28+U28+Y28+AC28+AG28+AK28+AO28+AS28+AW10+BA28+BE28+BI28 -> 0 | N28: =M28/M$10 -> #DIV/0! | O28: ='The Table'!J126 -> 0 | P28: =O28/O$10 -> 0 | Q28: ='The Table'!L126 -> 0 | R28: =Q28/Q$10 -> #DIV/0! | S28: =Iktara!J110 -> 0 | T28: =S28/S$10 -> 0 | U28: =Iktara!L110 -> 0 | V28: =U28/U$10 -> #DIV/0! | W28: ='Mg St Colaba'!J131 -> 0 | X28: =W28/W$10 -> 0 | Z28: =Y28/Y$10 -> #DIV/0! | AA28: ='Mg St LP'!J134 -> 0 | AB28: =AA28/AA$10 -> 0 | AC28: ='Mg St LP'!L134 -> 0 | AD28: =AC28/AC$10 -> #DIV/0! | AE28: ='Mg St Bandra'!J135 -> 0 | AF28: =AE28/AE$10 -> 0 | AG28: ='Mg St Bandra'!L135 -> 0 | AH28: =AG28/AG$10 -> #DIV/0! | AI28: ='MSK Events'!J129 -> 0 | AJ28: =AI28/AI$10 -> #DIV/0! | AK28: ='MSK Events'!L129 -> 0 | AL28: =AK28/AK$10 -> #DIV/0! | AM28: =MSBC!J119 -> -2033815 | AN28: =AM28/AM$10 -> -4.4168817 | AO28: =MSBC!L119 -> 0 | AP28: =AO28/AO$10 -> #DIV/0! | AQ28: =Kaspers!J131 -> 0 | AS28: =Kaspers!L131 -> 0 | AU28: ='MSBC Andheri'!J129 -> 0 | AW28: ='MSBC Andheri'!L129 -> 0 | AY28: ='MSBC Dahisar'!J116 -> 0 | BA28: ='MSBC Dahisar'!L116 -> 0 | BC28: ='MSBC Juhu Goregoan'!J129 -> 0 | BE28: ='MSBC Juhu Goregoan'!L129 -> 0 | BG28: ='LOUD MOUTH'!J117 -> 0 | BI28: ='LOUD MOUTH'!L117 -> 0
B29: Total Other Expenses | C29: =SUM(C19:C28) -> 42780148 | D29: =C29/C$10 -> 0.58111165 | E29: =I29+M29 -> 0 | F29: =E29/E$10 -> #DIV/0! | G29: =SUM(G19:G28) -> 8100762.3 | I29: =SUM(I19:I28) -> 0 | K29: =SUM(K19:K28) -> 34679386 | L29: =K29/K$10 -> 0.47107352 | M29: =SUM(M19:M28) -> 0 | N29: =M29/M$10 -> #DIV/0! | O29: =SUM(O19:O28) -> 9198912.4 | P29: =O29/O$10 -> 0.45075959 | Q29: =SUM(Q19:Q28) -> 0 | R29: =Q29/Q$10 -> #DIV/0! | S29: =SUM(S19:S28) -> 749766.04 | T29: =S29/S$10 -> 0.92850284 | U29: =SUM(U19:U28) -> 0 | V29: =U29/U$10 -> #DIV/0! | W29: =SUM(W19:W28) -> 6609501 | X29: =W29/W$10 -> 0.53161481 | Y29: =SUM(Y19:Y28) -> 0 | Z29: =Y29/Y$10 -> #DIV/0! | AA29: =SUM(AA19:AA28) -> 4220755.5 | AB29: =AA29/AA$10 -> 0.45319378 | AC29: =SUM(AC19:AC28) -> 0 | AD29: =AC29/AC$10 -> #DIV/0! | AE29: =SUM(AE19:AE28) -> 6369336 | AF29: =AE29/AE$10 -> 0.37718335 | AG29: =SUM(AG19:AG28) -> 0 | AH29: =AG29/AG$10 -> #DIV/0! | AI29: =SUM(AI19:AI28) -> 1130325.8 | AK29: =SUM(AK19:AK28) -> 0 | AM29: =SUM(AM19:AM28) -> 0.053333333 | AN29: =AM29/AM$10 -> 1.158252e-07 | AO29: =SUM(AO19:AO28) -> 0 | AP29: =AO29/AO$10 -> #DIV/0! | AQ29: =SUM(AQ19:AQ28) -> 5381547.8 | AS29: =SUM(AS19:AS28) -> 0 | AU29: =SUM(AU19:AU28) -> 145015.7 | AW29: =SUM(AW19:AW28) -> 0 | AY29: =SUM(AY19:AY28) -> 43675.92 | BA29: =SUM(BA19:BA28) -> 0 | BC29: =SUM(BC19:BC28) -> 47233 | BE29: =SUM(BE19:BE28) -> 0 | BG29: =SUM(BG19:BG28) -> 783317 | BI29: =SUM(BI19:BI28) -> 0
AW30: =AW17-AW29 -> 0 | BA30: =BA17-BA29 -> 0 | BE30: =BE17-BE29 -> 0 | BI30: =BI17-BI29 -> 0
B31: EBIDTA | C31: =C17-C29 -> 1539521.9 | D31: =C31/C$10 -> 0.020912365 | E31: =E17-E29 -> 0 | F31: =E31/E$10 -> #DIV/0! | G31: =G17-G29 -> -8100762.3 | I31: =I17-I29 -> 0 | K31: =K17-K29 -> 9640284.1 | L31: =K31/K$10 -> 0.13095049 | M31: =M17-M29 -> 0 | N31: =M31/M$10 -> #DIV/0! | O31: =O17-O29 -> 3953343.5 | P31: =O31/O$10 -> 0.19371937 | Q31: =Q17-Q29 -> 0 | R31: =Q31/Q$10 -> #DIV/0! | S31: =S17-S29 -> -258983.06 | T31: =S31/S$10 -> -0.32072206 | U31: =U17-U29 -> 0 | V31: =U31/U$10 -> #DIV/0! | W31: =W17-W29 -> 631729.58 | X31: =W31/W$10 -> 0.050811219 | Y31: =Y17-Y29 -> 0 | Z31: =Y31/Y$10 -> #DIV/0! | AA31: =AA17-AA29 -> 1234107.6 | AB31: =AA31/AA$10 -> 0.13250942 | AC31: =AC17-AC29 -> 0 | AD31: =AC31/AC$10 -> #DIV/0! | AE31: =AE17-AE29 -> 4336730.2 | AF31: =AE31/AE$10 -> 0.25681522 | AG31: =AG17-AG29 -> 0 | AH31: =AG31/AG$10 -> #DIV/0! | AI31: =AI17-AI29 -> -1131355.8 | AK31: =AK17-AK29 -> 0 | AM31: =AM17-AM29 -> -526562.19 | AN31: =AM31/AM$10 -> -1.1435469 | AO31: =AO17-AO29 -> 0 | AP31: =AO31/AO$10 -> #DIV/0! | AQ31: =AQ17-AQ29 -> 2018857.3 | AS31: =AS17-AS29 -> 0 | AU31: =AU17-AU29 -> 81836.53 | AV31: =AV17-AV29 -> 0 | AW31: =AW17-AW29 -> 0 | AX31: =AX17-AX29 -> 0 | AY31: =AY17-AY29 -> -123284.31 | AZ31: =AZ17-AZ29 -> 0 | BA31: =BA17-BA29 -> 0 | BB31: =BB17-BB29 -> 0 | ... BJ31: =BJ17-BJ29 -> 0
C33: =+G33+K33 -> 1539521.9 | G33: =HO!J123 -> -8100762.3 | K33: =SUM(O33:BJ33) -> 9640284.1 | O33: ='The Table'!J132 -> 3953343.5 | S33: =Iktara!J117 -> -258983.06 | W33: ='Mg St Colaba'!J137 -> 631729.58 | AA33: ='Mg St LP'!J141 -> 1234107.6 | AE33: ='Mg St Bandra'!J142 -> 4336730.2 | AI33: ='MSK Events'!J136 -> -1131355.8 | AM33: =MSBC!J125 -> -526562.19 | AQ33: =Kaspers!J138 -> 2018857.3 | AU33: ='MSBC Andheri'!J136 -> 81836.53 | AY33: ='MSBC Dahisar'!J123 -> -123284.31 | BC33: ='MSBC Juhu Goregoan'!J135 -> -139322.66 | BG33: ='LOUD MOUTH'!J123 -> -436812.58
C34: =+C31-C33 -> 1.8626451e-09 | G34: =+G31-G33 -> 0 | K34: =+K31-K33 -> -1.8626451e-09 | O34: =+O31-O33 -> 0 | S34: =+S31-S33 -> 0 | W34: =+W31-W33 -> 0 | AA34: =+AA31-AA33 -> 0 | AE34: =+AE31-AE33 -> 0 | AI34: =+AI31-AI33 -> 0 | AM34: =+AM31-AM33 -> 0 | AQ34: =+AQ31-AQ33 -> 0 | AU34: =+AU31-AU33 -> 0 | AY34: =+AY31-AY33 -> 0 | BC34: =+BC31-BC33 -> 0 | BG34: =+BG31-BG33 -> 0

Sheet Summary Sheet - April 2026
A1: FY26-27 Budgeted vs Actual MIS | W1: =W12/$K$12 -> 0.17642996 | AA1: =AA12/$K$12 -> 0.12037017 | AE1: =AE12/$K$12 -> 0.2016668 | BC1: c | BG1: c
A2: Food Matters Group
C3: Total with HO | G3: HO | K3: Outlets Total | O3: Table Total | S3: Iktara | W3: Mg St Colaba | AA3: Mg St LP | AE3: Mg St Bandra | AI3: MSK Events | AM3: MSBC | AQ3: Kaspers | AU3: MSBC Andheri | AY3: MSBC Dahisar | BC3: MSBC Juhu / Goregaon | BG3: Loud Mouth
C4: Actual | D4: %age | E4: Budgeted | F4: %age | G4: Actual | H4: %age | I4: Budgeted | J4: %age | K4: Actual | L4: %age | M4: Budgeted | N4: %age | O4: Actual | P4: %age | Q4: Budgeted | R4: %age | S4: Actual | T4: %age | U4: Budgeted | V4: %age | W4: Actual | X4: %age | Y4: Budgeted | Z4: %age | AA4: Actual | AB4: %age | AC4: Budgeted | AD4: %age | AE4: Actual | AF4: %age | AG4: Budgeted | AH4: %age | AI4: Actual | AJ4: %age | AK4: Budgeted | AL4: %age | AM4: Actual | AN4: %age | AO4: Budgeted | AP4: %age | AQ4: Actual | AR4: %age | AS4: Budgeted | AT4: %age | AU4: Amount | AV4: %age | AW4: Budgeted | AX4: %age | AY4: Amount | AZ4: %age | BA4: Budgeted | BB4: %age | BC4: Amount | BD4: %age | BE4: Budgeted | BF4: %age | BG4: Amount | BH4: %age | BI4: Budgeted | BJ4: %age
B5: Beverage | C5: =G5+K5 -> 5710543.8 | D5: =C5/C$10 -> 0.075936842 | E5: =I5+M5 -> 0 | F5: =E5/E$10 -> #DIV/0! | G5: =HO!D14 -> 0 | I5: =HO!F14 | K5: =O5+S5+W5+AA5+AE5+AI5+AM5+AQ5+AU5+AY5+BC5+BG5 -> 5710543.8 | L5: =K5/K$10 -> 0.075936842 | M5: =Q5+U5+Y5+AC5+AG5+AK5+AO5+AS5+AW5+BA5+BE5+BI5 -> 0 | N5: =M5/M$10 -> #DIV/0! | O5: ='The Table'!D24 -> 1172105 | P5: =O5/O$10 -> 0.057101447 | Q5: ='The Table'!F24 | R5: =Q5/Q$10 -> #DIV/0! | S5: =Iktara!D24 -> 0 | T5: =S5/S$10 -> 0 | U5: =Iktara!F24 | V5: =U5/U$10 -> #DIV/0! | W5: ='Mg St Colaba'!D24 -> 1181100 | X5: =W5/W$10 -> 0.091912963 | Y5: ='Mg St Colaba'!F24 | Z5: =Y5/Y$10 -> #DIV/0! | AA5: ='Mg St LP'!D24 -> 1273758.8 | AB5: =AA5/AA$10 -> 0.12954836 | AC5: ='Mg St LP'!F24 | AD5: =AC5/AC$10 -> #DIV/0! | AE5: ='Mg St Bandra'!D24 -> 1555917.5 | AF5: =AE5/AE$10 -> 0.089698088 | AG5: ='Mg St Bandra'!F24 | AH5: =AG5/AG$10 -> #DIV/0! | AI5: ='MSK Events'!D24 | AJ5: =AI5/AI$10 -> #DIV/0! | AK5: ='MSK Events'!F24 | AM5: =MSBC!D24 | AN5: =AM5/AM$10 -> 0 | AO5: =MSBC!F24 -> 0 | AP5: =AO5/AO$10 -> #DIV/0! | AQ5: =Kaspers!D24 -> 527662.5 | AS5: =Kaspers!F24 | AU5: ='MSBC Andheri'!D24 -> 0 | AW5: 0 | AY5: ='MSBC Dahisar'!D22 -> 0 | BA5: 0 | BC5: ='MSBC Juhu Goregoan'!D22 -> 0 | BE5: 0 | BG5: ='LOUD MOUTH'!D24 | BI5: 0
B6: Liquor | C6: =G6+K6 -> 12228470 | D6: =C6/C$10 -> 0.16260998 | E6: =I6+M6 -> 0 | F6: =E6/E$10 -> #DIV/0! | G6: =HO!D15 -> 0 | I6: =HO!F15 | K6: =O6+S6+W6+AA6+AE6+AI6+AM6+AQ6+AU6+AY6+BC6+BG6 -> 12228470 | L6: =K6/K$10 -> 0.16260998 | M6: =Q6+U6+Y6+AC6+AG6+AK6+AO6+AS6+AW6+BA6+BE6+BI6 -> 0 | N6: =M6/M$10 -> #DIV/0! | O6: ='The Table'!D25 -> 4966546 | P6: =O6/O$10 -> 0.24195525 | Q6: ='The Table'!F25 | R6: =Q6/Q$10 -> #DIV/0! | S6: =Iktara!D25 -> 0 | T6: =S6/S$10 -> 0 | U6: =Iktara!F25 | V6: =U6/U$10 -> #DIV/0! | W6: ='Mg St Colaba'!D25 -> 769660 | X6: =W6/W$10 -> 0.059894785 | Y6: ='Mg St Colaba'!F25 | Z6: =Y6/Y$10 -> #DIV/0! | AA6: ='Mg St LP'!D25 -> 0 | AB6: =AA6/AA$10 -> 0 | AC6: ='Mg St LP'!F25 | AD6: =AC6/AC$10 -> #DIV/0! | AE6: ='Mg St Bandra'!D25 -> 2119471.5 | AF6: =AE6/AE$10 -> 0.12218677 | AG6: ='Mg St Bandra'!F25 | AH6: =AG6/AG$10 -> #DIV/0! | AI6: ='MSK Events'!D25 | AJ6: =AI6/AI$10 -> #DIV/0! | AK6: ='MSK Events'!F25 | AM6: =MSBC!D25 | AN6: =AM6/AM$10 -> 0 | AO6: =MSBC!F25 -> 0 | AP6: =AO6/AO$10 -> #DIV/0! | AQ6: =Kaspers!D25 -> 4372792.5 | AS6: =Kaspers!F25 | AU6: ='MSBC Andheri'!D25 -> 0 | AW6: 0 | AY6: ='MSBC Dahisar'!D23 -> 0 | BA6: 0 | BC6: ='MSBC Juhu Goregoan'!D23 -> 0 | BE6: 0 | BG6: ='LOUD MOUTH'!D25 | BI6: 0
B7: Food | C7: =G7+K7 -> 52367609 | D7: =C7/C$10 -> 0.69636641 | E7: =I7+M7 -> 0 | F7: =E7/E$10 -> #DIV/0! | G7: =HO!D16 -> 0 | I7: =HO!F16 | K7: =O7+S7+W7+AA7+AE7+AI7+AM7+AQ7+AU7+AY7+BC7+BG7 -> 52367609 | L7: =K7/K$10 -> 0.69636641 | M7: =Q7+U7+Y7+AC7+AG7+AK7+AO7+AS7+AW7+BA7+BE7+BI7 -> 0 | N7: =M7/M$10 -> #DIV/0! | O7: ='The Table'!D26 -> 12668924 | P7: =O7/O$10 -> 0.61719204 | Q7: ='The Table'!F26 | R7: =Q7/Q$10 -> #DIV/0! | S7: =Iktara!D26 -> 859748 | T7: =S7/S$10 -> 1 | U7: =Iktara!F26 | V7: =U7/U$10 -> #DIV/0! | W7: ='Mg St Colaba'!D26 -> 10177814 | X7: =W7/W$10 -> 0.79203546 | Y7: ='Mg St Colaba'!F26 | Z7: =Y7/Y$10 -> #DIV/0! | AA7: ='Mg St LP'!D26 -> 8201572.2 | AB7: =AA7/AA$10 -> 0.83414559 | AC7: ='Mg St LP'!F26 | AD7: =AC7/AC$10 -> #DIV/0! | AE7: ='Mg St Bandra'!D26 -> 12642063 | AF7: =AE7/AE$10 -> 0.72881043 | AG7: ='Mg St Bandra'!F26 | AH7: =AG7/AG$10 -> #DIV/0! | AI7: ='MSK Events'!D26 | AJ7: =AI7/AI$10 -> #DIV/0! | AK7: ='MSK Events'!F26 | AM7: =MSBC!D26 -> 510529.82 | AN7: =AM7/AM$10 -> 1 | AO7: =MSBC!F26 -> 0 | AP7: =AO7/AO$10 -> #DIV/0! | AQ7: =Kaspers!D26 -> 6037327.5 | AS7: =Kaspers!F26 -> 0 | AU7: ='MSBC Andheri'!D26 -> 334509.99 | AW7: 0 | AY7: ='MSBC Dahisar'!D24 -> 124708.89 | BA7: 0 | BC7: ='MSBC Juhu Goregoan'!D24 -> 174122.08 | BE7: 0 | BG7: ='LOUD MOUTH'!D26 -> 636289 | BI7: 0
